Workbook

Sheet README
B1: Oda / Odaamsterderm Hub - Product Taxonomy & Amsterdam Test Data
B2: Version 1 draft, 27 Oct 2026. Test data only - every price, stock level, address, phone, batch, registration number and clinical field is dummy.
B4: Reference date (test 'today') | C4: 46322
C5: Expiry and stock-status formulas in Store_Inventory count days from this date. Change it to re-run scenarios.
B7: HOW THE TAXONOMY WORKS
B8: 1. Category = what it is | C8: Each product has ONE primary category (max 2 levels). Category never encodes animal, life stage, brand or pack size.
B9: 2. Animal type is multi-select | C9: Tag every animal the label covers, at the most specific level that is true (e.g. Albendazole = Cattle + Goats + Sheep). Filtering on a parent (Poultry, Cattle, Goats & Sheep, Fish) must include its children.
B10: 3. Life stage is an attribute | C10: Starter / Grower / Finisher / Laying are no longer sub-categories. They live in life_stages and depend on the animal (a pig 'grower' is LS-PIG-GRW, a chicken grower is LS-POU-GRW).
B11: 4. Pack size is a variant | C11: One product, many SKUs (Vitamix Chick 30 g / 100 g / 250 g). Product names never contain pack size. Cross-seller comparison happens at SKU level.
B12: 5. Brand vs producer vs seller | C12: Brand = name on the pack; producer = who made it; seller/store = who sells it. All three are separate fields.
B13: 6. Category vs regulatory class | C13: Category answers 'what does it do'. regulatory_class + prescription_required answer 'how may it be sold'. Set them from registration status, never from packaging wording.
B14: 7. Price and stock belong to the store | C14: The same SKU can have different prices and stock in Tegeta, Mbeya, Mwanza etc. Nothing price-related sits on the product.
B15: 8. Search uses keywords + use cases | C15: search_keywords (pipe-separated, Kiswahili first) plus use_cases tags. Index 'ngombe' and 'ng'ombe' both. See Search_Keywords tab for the shared dictionary.
B16: 9. Cold chain gating | C16: Products with cold_chain_required=TRUE may only be stocked/fulfilled by stores with cold_chain_capable=TRUE, and delivery must respect it.
B17: 10. Chicks are booked, not stocked | C17: Day-old chicks (C7010) have no Store_Inventory rows. Each hatchery publishes hatch dates with price and fixed capacity in Hatch_Schedule; a date shows FULL when booked >= capacity, as on Oda today. Minimum order 50 chicks.
B19: IMPORT ORDER (foreign keys)
C20: Animal_Types > Life_Stages > Categories > Attributes / Attribute_Values > Search_Keywords > Brands > Sellers > Regions > Stores > Products > Variants > Store_Inventory > Hatch_Schedule. Map_* tabs are for migrating the live catalogue.
B22: TABS
B23: Tab | C23: Purpose (row count in column D) | D23: Rows
B24: Animal_Types | C24: Animal hierarchy (parent/child). | D24: =COUNTA(Animal_Types!A:A)-1 -> 14
B25: Life_Stages | C25: Life stages per animal group. | D25: =COUNTA(Life_Stages!A:A)-1 -> 26
B26: Categories | C26: Category tree with definitions and tie-break rules. 'status_vs_live' shows what changed. | D26: =COUNTA(Categories!A:A)-1 -> 38
B27: Attributes | C27: Every product / variant / store-inventory field: type, required-for, source of allowed values. | D27: =COUNTA(Attributes!A:A)-1 -> 44
B28: Attribute_Values | C28: Allowed values (EN + SW) for every enum attribute. | D28: =COUNTA(Attribute_Values!A:A)-1 -> 118
B29: Search_Keywords | C29: Kiswahili/English search dictionary mapped to categories, animals, use cases and diseases. | D29: =COUNTA(Search_Keywords!A:A)-1 -> 75
B30: Brands | C30: Brands / producers. '(demo)' = fictional, following the live system's convention. | D30: =COUNTA(Brands!A:A)-1 -> 24
B31: Sellers | C31: Amsterdam Group plus the 11 hatcheries migrated from Oda. | D31: =COUNTA(Sellers!A:A)-1 -> 12
B32: Regions | C32: Regions with city centroids (GeoNames). A region can hold several stores. | D32: =COUNTA(Regions!A:A)-1 -> 5
B33: Stores | C33: Amsterdam's 6 stores in 5 regions with bio (EN/SW), coordinates, hours, delivery settings and a distance-to-HQ formula. | D33: =COUNTA(Stores!A:A)-1 -> 6
B34: Products | C34: Catalogue products with all taxonomy fields filled. | D34: =COUNTA(Products!A:A)-1 -> 115
B35: Variants | C35: SKUs: pack size, selling unit, shipping weight, dummy barcode, reference price. | D35: =COUNTA(Variants!A:A)-1 -> 150
B36: Store_Inventory | C36: Stock and price per store per SKU, with formula columns and deliberate test scenarios (column 'test_scenario'). No day-old chicks here. | D36: =COUNTA(Store_Inventory!A:A)-1 -> 605
B37: Hatch_Schedule | C37: Day-old chick availability: hatchery x SKU x hatch date with price, capacity, booked, FULL/Open/Closed status and Oda commission. | D37: =COUNTA(Hatch_Schedule!A:A)-1 -> 87
B38: Map_Categories | C38: Old live categories / animal types > new taxonomy. | D38: =COUNTA(Map_Categories!A:A)-1 -> 25
B39: Map_Live_Products | C39: The 15 products currently in the live shared catalogue > new product, SKU, category and animals. | D39: =COUNTA(Map_Live_Products!A:A)-1 -> 15
B40: Map_Stores_Sellers | C40: Live seller/store names > new records, with decisions needed. | D40: =COUNTA(Map_Stores_Sellers!A:A)-1 -> 7
B41: Map_Oda_Chicks | C41: How each Oda concept (tenants, chick types, hatch schedule, CSV, commission) moves into the catalogue, in migration order, plus the 11 hatcheries x chick types. | D41: =COUNTA(Map_Oda_Chicks!A:A)-1 -> 10
B43: ASSUMPTIONS & TO VERIFY
B44: Branch count | C44: Your message said four branches but listed Tegeta, Posta (both Dar es Salaam), Morogoro, Mbeya, Arusha and Mwanza. This file uses all six stores in five regions; delete rows if fewer are wanted.
B45: Coordinates | C45: Store points are approximate area locations (town centres from GeoNames, adjusted to the named area). Replace with each branch's real map pin before testing delivery routing.
B46: Addresses, phones, managers | C46: Dummy. Only the HQ phone and website come from the Amsterdam catalogue. Emails use example.com so no test message reaches a real inbox.
B47: Pig Protein Concentrate '20%' | C47: The bag says '20%' without saying whether it is crude protein or inclusion rate. Confirm with Amsterdam.
B48: Clinical & regulatory fields | C48: Withdrawal periods, prescription flags, regulatory classes and registration numbers are placeholders for testing the fields only. Every medicine and vaccine must be checked against its registered label and the applicable veterinary regulations before go-live.
B49: Kiswahili terms | C49: Names and keywords are standard Kiswahili/sector usage but should be reviewed by the team; add local terms farmers actually type.
B50: Day-old chicks (decided 27 Oct) | C50: Chicks move into this catalogue via Hatch_Schedule. Hatchery names and chick types follow the Oda supplier roster; chick prices, capacities, hatch dates, the 60 TZS commission and storefront slugs are dummy or assumed.
B51: 'Main' store (decided 27 Oct) | C51: Live store 'Amsterdem Group - Main' is the Tegeta HQ: rename and keep its stock and history under ST-AMS-TEG.
B52: Prices | C52: Dummy TZS prices, plausible for Oct 2026 but not market data. Regional multipliers: Posta +3%, Morogoro +2%, Mbeya/Arusha +5%, Mwanza +7%; raw materials cheaper in Mbeya/Morogoro; fish inputs cheaper in Mwanza.

Sheet Animal_Types
A1: animal_id | B1: parent_id | C1: slug | D1: name_en | E1: name_sw | F1: status_vs_live | G1: notes
A2: AN-POU | C2: poultry | D2: Poultry | E2: Kuku na ndege wafugwao | F2: Existing | G2: Parent. Filtering on Poultry must include all children.
A3: AN-CHK | B3: AN-POU | C3: chicken | D3: Chicken | E3: Kuku | F3: Existing | G3: Broiler, layer, improved indigenous (Sasso, Kuroiler, Tanbro) are production_purpose values, not separate animals.
A4: AN-OPO | B4: AN-POU | C4: other-poultry | D4: Other poultry (ducks, turkeys, guinea fowl, quail) | E4: Bata, bata mzinga, kanga, kware | F4: Existing
A5: AN-CAT | C5: cattle | D5: Cattle | E5: Ng'ombe | F5: Existing | G5: Parent. Tag a product here when it applies to both dairy and beef.
A6: AN-DCT | B6: AN-CAT | C6: dairy-cattle | D6: Dairy cattle | E6: Ng'ombe wa maziwa | F6: New | G6: Use for dairy meal, milking equipment, dairy semen.
A7: AN-BCT | B7: AN-CAT | C7: beef-cattle | D7: Beef cattle | E7: Ng'ombe wa nyama | F7: New | G7: Use for fattening rations.
A8: AN-GTS | C8: goats-sheep | D8: Goats & Sheep | E8: Mbuzi na kondoo | F8: Existing | G8: Parent.
A9: AN-GOT | B9: AN-GTS | C9: goats | D9: Goats | E9: Mbuzi | F9: New
A10: AN-SHP | B10: AN-GTS | C10: sheep | D10: Sheep | E10: Kondoo | F10: New
A11: AN-PIG | C11: pigs | D11: Pigs | E11: Nguruwe | F11: Existing
A12: AN-FSH | C12: fish-aquaculture | D12: Fish / Aquaculture | E12: Samaki / ufugaji wa samaki | F12: Existing | G12: Parent.
A13: AN-TIL | B13: AN-FSH | C13: tilapia | D13: Tilapia | E13: Sato | F13: New
A14: AN-CAF | B14: AN-FSH | C14: catfish | D14: Catfish | E14: Kambale | F14: New
A15: AN-OTH | C15: other-animals | D15: Other livestock / animals (rabbits, dogs, bees) | E15: Mifugo mingine (sungura, mbwa, nyuki) | F15: Existing

Sheet Life_Stages
A1: life_stage_id | B1: applies_to_animal_id | C1: slug | D1: name_en | E1: name_sw | F1: sort_order | G1: notes
A2: LS-ALL | B2: * | C2: all-stages | D2: All stages | E2: Hatua zote | F2: 0 | G2: Use only when the label genuinely says all ages.
A3: LS-POU-STR | B3: AN-POU | C3: starter | D3: Starter / chick (0-4 wks) | E3: Vifaranga (wiki 0-4) | F3: 1
A4: LS-POU-GRW | B4: AN-POU | C4: grower | D4: Grower | E4: Kuku wanaokua | F4: 2 | G4: Broiler grower and layer pullet grower share this stage; production_purpose separates them.
A5: LS-POU-FIN | B5: AN-POU | C5: finisher | D5: Finisher (broiler) | E5: Kumalizia (kuku wa nyama) | F5: 3
A6: LS-POU-LAY | B6: AN-POU | C6: laying | D6: Laying | E6: Kuku wanaotaga | F6: 4
A7: LS-POU-BRD | B7: AN-POU | C7: breeder | D7: Breeder / parent stock | E7: Kuku wazazi | F7: 5
A8: LS-PIG-CRP | B8: AN-PIG | C8: creep | D8: Piglet / creep (pre-weaning) | E8: Watoto wanaonyonya | F8: 1
A9: LS-PIG-WEA | B9: AN-PIG | C9: weaner | D9: Weaner | E9: Walioachishwa kunyonya | F9: 2
A10: LS-PIG-GRW | B10: AN-PIG | C10: grower | D10: Grower | E10: Wanaokua | F10: 3
A11: LS-PIG-FIN | B11: AN-PIG | C11: finisher | D11: Finisher | E11: Kunenepesha | F11: 4
A12: LS-PIG-SOW | B12: AN-PIG | C12: sow | D12: Sow (gestating / lactating) | E12: Nguruwe jike mzazi | F12: 5
A13: LS-PIG-BOR | B13: AN-PIG | C13: boar | D13: Boar | E13: Nguruwe dume | F13: 6
A14: LS-CAT-CLF | B14: AN-CAT | C14: calf | D14: Calf | E14: Ndama | F14: 1
A15: LS-CAT-HEF | B15: AN-CAT | C15: heifer | D15: Heifer | E15: Mtamba | F15: 2
A16: LS-CAT-LAC | B16: AN-CAT | C16: lactating | D16: Lactating cow | E16: Ng'ombe anayekamuliwa | F16: 3
... A27: LS-FSH-BRD | B27: AN-FSH | C27: broodstock | D27: Broodstock | E27: Samaki wazazi | F27: 4

Sheet Categories
A1: category_id | B1: parent_id | C1: level | D1: slug | E1: name_en | F1: name_sw | G1: includes | H1: excludes_tie_break | I1: extra_required_attributes | J1: status_vs_live | K1: product_count
A2: C10 | C2: 1 | D2: feed | E2: Feed | F2: Vyakula vya mifugo | G2: Anything the animal eats as its ration or that is mixed into the ration. | H2: Water-soluble nutritional products go to Supplements (C20), not Feed. | J2: Existing (restructured) | K2: =IF(C2=1,COUNTIF(Products!$F:$F,A2),COUNTIF(Products!$G:$G,A2)) -> 33
A3: C1010 | B3: C10 | C3: 2 | D3: complete-feed | E3: Complete feed | F3: Chakula kamili | G3: Ready-to-feed rations: starter, grower, finisher, layers mash, dairy meal, pig pellets, fish feed. | H3: Life stage is an attribute, NOT a sub-category. Old Feed>Starter/Grower/Finisher/Layers Mash all map here. | I3: life_stages, crude_protein_pct, form | J3: New (replaces Starter/Grower/Finisher/Layers Mash) | K3: =IF(C3=1,COUNTIF(Products!$F:$F,A3),COUNTIF(Products!$G:$G,A3)) -> 17
A4: C1020 | B4: C10 | C4: 2 | D4: concentrates | E4: Concentrates | F4: Kontsentreti (chakula cha kuchanganya) | G4: Protein/vitamin/mineral concentrates the farmer mixes with an energy source (maize bran, maize). | H4: If it needs mixing at more than ~5% of the ration it is a concentrate; under ~5% it is a premix. | I4: crude_protein_pct, inclusion_or_dosage | J4: Existing | K4: =IF(C4=1,COUNTIF(Products!$F:$F,A4),COUNTIF(Products!$G:$G,A4)) -> 4
A5: C1030 | B5: C10 | C5: 2 | D5: premixes | E5: Premixes & base mixes | F5: Premiksi (vitamini na madini ya kuchanganya) | G5: Vitamin-mineral premixes mixed into feed at low inclusion (typically 0.25-5%). | H5: Vitamins given in drinking water go to C2010. | I5: inclusion_or_dosage | J5: New | K5: =IF(C5=1,COUNTIF(Products!$F:$F,A5),COUNTIF(Products!$G:$G,A5)) -> 3
A6: C1040 | B6: C10 | C6: 2 | D6: raw-materials | E6: Raw materials & ingredients | F6: Malighafi za chakula | G6: Single ingredients: maize bran, maize, sunflower cake, soybean meal, fish meal/dagaa, limestone, DCP. | H6: Usually multi-species: tag every animal it is fed to. | I6: crude_protein_pct | J6: New | K6: =IF(C6=1,COUNTIF(Products!$F:$F,A6),COUNTIF(Products!$G:$G,A6)) -> 7
A7: C1050 | B7: C10 | C7: 2 | D7: forage-fodder | E7: Forage & fodder | F7: Malisho na majani | G7: Hay, silage, pasture/fodder seed and cuttings. | J7: New | K7: =IF(C7=1,COUNTIF(Products!$F:$F,A7),COUNTIF(Products!$G:$G,A7)) -> 2
A8: C20 | C8: 1 | D8: supplements-additives | E8: Supplements & additives | F8: Virutubisho na viongezeo | G8: Nutritional products given on top of the ration, in water or feed. | H8: Category describes what the product does; regulatory_class (separate field) decides how it may be sold. Never infer one from the other. | I8: administration_route, use_cases | J8: Existing (was 'Vitamins & Supplements', now split) | K8: =IF(C8=1,COUNTIF(Products!$F:$F,A8),COUNTIF(Products!$G:$G,A8)) -> 14
A9: C2010 | B9: C20 | C9: 2 | D9: vitamins | E9: Vitamins & multivitamins | F9: Vitamini | G9: Single or multivitamin products incl. water-soluble sachets and injectable vitamins. | H9: If the main claim is electrolytes/heat stress use C2020 even when vitamin C is present. | J9: New | K9: =IF(C9=1,COUNTIF(Products!$F:$F,A9),COUNTIF(Products!$G:$G,A9)) -> 4
A10: C2020 | B10: C20 | C10: 2 | D10: electrolytes | E10: Electrolytes & heat-stress | F10: Elektrolaiti na kinga ya joto | G10: Electrolytes, oral rehydration salts, anti-heat-stress products. | J10: New | K10: =IF(C10=1,COUNTIF(Products!$F:$F,A10),COUNTIF(Products!$G:$G,A10)) -> 2
A11: C2030 | B11: C20 | C11: 2 | D11: minerals-licks | E11: Minerals & licks | F11: Madini na mawe ya kulamba | G11: Mineral licks, blocks and loose mineral mixes for direct feeding. | H11: Feed-mill premixes go to C1030. | J11: New | K11: =IF(C11=1,COUNTIF(Products!$F:$F,A11),COUNTIF(Products!$G:$G,A11)) -> 3
A12: C2040 | B12: C20 | C12: 2 | D12: probiotics-enzymes | E12: Probiotics, enzymes & acidifiers | F12: Probiotiki, vimeng'enya na asidi | G12: Gut-health additives. | J12: New | K12: =IF(C12=1,COUNTIF(Products!$F:$F,A12),COUNTIF(Products!$G:$G,A12)) -> 2
A13: C2050 | B13: C20 | C13: 2 | D13: toxin-binders | E13: Toxin binders | F13: Vifunga sumu ya kuvu | G13: Mycotoxin/aflatoxin binders. | J13: New | K13: =IF(C13=1,COUNTIF(Products!$F:$F,A13),COUNTIF(Products!$G:$G,A13)) -> 1
A14: C2060 | B14: C20 | C14: 2 | D14: amino-acids-tonics | E14: Amino acids & tonics | F14: Amino asidi na tonik | G14: Liver tonics, amino-acid liquids, egg/production boosters. | J14: New | K14: =IF(C14=1,COUNTIF(Products!$F:$F,A14),COUNTIF(Products!$G:$G,A14)) -> 2
A15: C30 | C15: 1 | D15: medicines | E15: Medicines | F15: Dawa za mifugo | G15: Products that treat or prevent disease (excluding vaccines). | H15: Every item needs regulatory_class and prescription_required set before it is listed. | I15: active_ingredients, regulatory_class, prescription_required, withdrawal periods | J15: Existing (now split) | K15: =IF(C15=1,COUNTIF(Products!$F:$F,A15),COUNTIF(Products!$G:$G,A15)) -> 15
A16: C3010 | B16: C30 | C16: 2 | D16: antibiotics | E16: Antibiotics & antibacterials | F16: Viuavijasumu | J16: New | K16: =IF(C16=1,COUNTIF(Products!$F:$F,A16),COUNTIF(Products!$G:$G,A16)) -> 4
A17: C3020 | B17: C30 | C17: 2 | D17: dewormers | E17: Dewormers | F17: Dawa za minyoo | G17: Internal parasite control incl. endectocides (ivermectin). | J17: New | K17: =IF(C17=1,COUNTIF(Products!$F:$F,A17),COUNTIF(Products!$G:$G,A17)) -> 4
A18: C3030 | B18: C30 | C18: 2 | D18: anticoccidials | E18: Anticoccidials | F18: Dawa za kuhara damu (koksidiosisi) | J18: New | K18: =IF(C18=1,COUNTIF(Products!$F:$F,A18),COUNTIF(Products!$G:$G,A18)) -> 2
A19: C3040 | B19: C30 | C19: 2 | D19: external-parasites | E19: External parasite control | F19: Dawa za kupe, chawa na utitiri | G19: Acaricides, dips, sprays, pour-ons, mite/lice powders. | J19: New | K19: =IF(C19=1,COUNTIF(Products!$F:$F,A19),COUNTIF(Products!$G:$G,A19)) -> 3
A20: C3050 | B20: C30 | C20: 2 | D20: wound-care | E20: Wound care & topical | F20: Dawa za vidonda | J20: New | K20: =IF(C20=1,COUNTIF(Products!$F:$F,A20),COUNTIF(Products!$G:$G,A20)) -> 1
A21: C3060 | B21: C30 | C21: 2 | D21: other-medicines | E21: Other medicines | F21: Dawa nyingine | G21: Metabolic (milk fever), anti-inflammatories, hormones etc. | H21: Use sparingly; add a new sub-category once >5 products share a purpose. | J21: New | K21: =IF(C21=1,COUNTIF(Products!$F:$F,A21),COUNTIF(Products!$G:$G,A21)) -> 1
A22: C40 | C22: 1 | D22: vaccines | E22: Vaccines & biologicals | F22: Chanjo | G22: All vaccines. | H22: No sub-categories: animal type + disease_target do the filtering. | I22: disease_target, cold_chain_required, storage | J22: Existing | K22: =IF(C22=1,COUNTIF(Products!$F:$F,A22),COUNTIF(Products!$G:$G,A22)) -> 9
A23: C50 | C23: 1 | D23: biosecurity-hygiene | E23: Biosecurity & hygiene | F23: Usafi na kinga ya shamba | G23: Disinfectants, water sanitisers, foot-dip products, rodent and fly control. | H23: Replaces the undefined 'Veterinary Products' category. | J23: New (replaces 'Veterinary Products') | K23: =IF(C23=1,COUNTIF(Products!$F:$F,A23),COUNTIF(Products!$G:$G,A23)) -> 4
A24: C5010 | B24: C50 | C24: 2 | D24: disinfectants | E24: Disinfectants & sanitisers | F24: Dawa za kuua vijidudu | J24: New | K24: =IF(C24=1,COUNTIF(Products!$F:$F,A24),COUNTIF(Products!$G:$G,A24)) -> 3
A25: C5020 | B25: C50 | C25: 2 | D25: pest-rodent-control | E25: Pest & rodent control | F25: Udhibiti wa panya na wadudu | J25: New | K25: =IF(C25=1,COUNTIF(Products!$F:$F,A25),COUNTIF(Products!$G:$G,A25)) -> 1
A26: C60 | C26: 1 | D26: equipment | E26: Equipment & supplies | F26: Vifaa | G26: Durable goods and consumables. | I26: capacity, power_source where relevant | J26: Existing | K26: =IF(C26=1,COUNTIF(Products!$F:$F,A26),COUNTIF(Products!$G:$G,A26)) -> 19
A27: C6010 | B27: C60 | C27: 2 | D27: feeders-drinkers | E27: Feeders & drinkers | F27: Vyombo vya chakula na maji | J27: Existing | K27: =IF(C27=1,COUNTIF(Products!$F:$F,A27),COUNTIF(Products!$G:$G,A27)) -> 6
A28: C6020 | B28: C60 | C28: 2 | D28: brooding-heating | E28: Brooding & heating | F28: Vifaa vya kulelea vifaranga | J28: Split from 'Housing & Brooding' | K28: =IF(C28=1,COUNTIF(Products!$F:$F,A28),COUNTIF(Products!$G:$G,A28)) -> 2
A29: C6030 | B29: C60 | C29: 2 | D29: housing-cages | E29: Housing, cages & nests | F29: Mabanda, vizimba na viota | J29: Split from 'Housing & Brooding' | K29: =IF(C29=1,COUNTIF(Products!$F:$F,A29),COUNTIF(Products!$G:$G,A29)) -> 2
A30: C6040 | B30: C60 | C30: 2 | D30: incubators | E30: Incubators & hatching | F30: Mashine za kutotolesha | J30: New | K30: =IF(C30=1,COUNTIF(Products!$F:$F,A30),COUNTIF(Products!$G:$G,A30)) -> 2
A31: C6050 | B31: C60 | C31: 2 | D31: egg-handling | E31: Egg handling & packaging | F31: Trei na vifungashio vya mayai | J31: New | K31: =IF(C31=1,COUNTIF(Products!$F:$F,A31),COUNTIF(Products!$G:$G,A31)) -> 1
A32: C6060 | B32: C60 | C32: 2 | D32: vet-tools | E32: Veterinary tools | F32: Vifaa vya tiba ya mifugo | G32: Syringes, needles, drenching guns, thermometers. | J32: New | K32: =IF(C32=1,COUNTIF(Products!$F:$F,A32),COUNTIF(Products!$G:$G,A32)) -> 4
A33: C6070 | B33: C60 | C33: 2 | D33: milking-dairy | E33: Milking & dairy equipment | F33: Vifaa vya kukamua na maziwa | J33: New | K33: =IF(C33=1,COUNTIF(Products!$F:$F,A33),COUNTIF(Products!$G:$G,A33)) -> 1
A34: C6080 | B34: C60 | C34: 2 | D34: weighing | E34: Weighing & measuring | F34: Mizani na vipimo | J34: New | K34: =IF(C34=1,COUNTIF(Products!$F:$F,A34),COUNTIF(Products!$G:$G,A34)) -> 1
A35: C70 | C35: 1 | D35: live-animals-genetics | E35: Live animals & genetics | F35: Mifugo hai na mbegu | G35: Animals and genetic material. | H35: Decided: day-old chicks move into this catalogue. They are sold against hatch dates (Hatch_Schedule), not shelf stock; other live animals use Store_Inventory. | I35: breed_strain, vaccination_status | J35: New | K35: =IF(C35=1,COUNTIF(Products!$F:$F,A35),COUNTIF(Products!$G:$G,A35)) -> 21
A36: C7010 | B36: C70 | C36: 2 | D36: day-old-chicks | E36: Day-old chicks & hatching eggs | F36: Vifaranga na mayai ya kutotolesha | G36: One product per hatchery x chick type (e.g. 'Kibo Broiler Day-old Chicks'). Replaces Oda's chick-type list. | H36: Availability, price and capacity live on Hatch_Schedule rows; never put chicks in Store_Inventory. | I36: breed_strain, min_order_qty, hatch schedule | J36: New (absorbs Oda chick booking) | K36: =IF(C36=1,COUNTIF(Products!$F:$F,A36),COUNTIF(Products!$G:$G,A36)) -> 17
A37: C7020 | B37: C70 | C37: 2 | D37: young-stock | E37: Young stock | F37: Mifugo wachanga | G37: Piglets, calves, kids, fingerlings, point-of-lay pullets. | J37: New | K37: =IF(C37=1,COUNTIF(Products!$F:$F,A37),COUNTIF(Products!$G:$G,A37)) -> 3
A38: C7030 | B38: C70 | C38: 2 | D38: breeding-stock | E38: Breeding & mature stock | F38: Mifugo wazazi na waliokomaa | J38: New | K38: =IF(C38=1,COUNTIF(Products!$F:$F,A38),COUNTIF(Products!$G:$G,A38)) -> 0
A39: C7040 | B39: C70 | C39: 2 | D39: semen-ai | E39: Semen & AI | F39: Mbegu za uhimilishaji | I39: cold_chain_required | J39: New | K39: =IF(C39=1,COUNTIF(Products!$F:$F,A39),COUNTIF(Products!$G:$G,A39)) -> 1

Sheet Attributes
A1: attribute_key | B1: label_en | C1: label_sw | D1: level | E1: data_type | F1: multi_select | G1: required_for | H1: allowed_values_source | I1: notes
A2: animal_types | B2: Animal type(s) | C2: Aina ya mifugo | D2: product | E2: enum | F2: Y | G2: ALL | H2: Animal_Types | I2: MULTI-SELECT. Tag the most specific level that is true; parent filters include children.
A3: life_stages | B3: Life stage(s) | C3: Hatua ya ukuaji | D3: product | E3: enum | F3: Y | G3: C1010, C1020, C70 | H3: Life_Stages | I3: Only stages belonging to the chosen animal types.
A4: production_purpose | B4: Production purpose | C4: Lengo la ufugaji | D4: product | E4: enum | F4: Y | G4: C1010, C1020, C70 (optional elsewhere) | H4: Attribute_Values | I4: broiler / layer / improved indigenous / dairy / beef ...
A5: form | B5: Physical form | C5: Umbo | D5: product | E5: enum | F5: N | G5: ALL | H5: Attribute_Values
A6: administration_route | B6: How it is given | C6: Jinsi ya kutumia | D6: product | E6: enum | F6: Y | G6: C20, C30, C40, C50 | H6: Attribute_Values
A7: use_cases | B7: Problem / use case tags | C7: Tatizo / matumizi | D7: product | E7: enum | F7: Y | G7: Recommended for all; required C20, C30 | H7: Attribute_Values | I7: Powers problem-based search (e.g. 'joto' finds heat-stress products).
A8: disease_target | B8: Disease(s) targeted | C8: Ugonjwa unaolengwa | D8: product | E8: enum | F8: Y | G8: C40 (required); C30 (optional) | H8: Attribute_Values
A9: active_ingredients | B9: Active ingredients / composition | C9: Viambato | D9: product | E9: text | F9: N | G9: C20, C30, C40, C50 | H9: free text | I9: As printed on label.
A10: crude_protein_pct | B10: Crude protein % | C10: Protini % | D10: product | E10: number | F10: N | G10: C1010, C1020, C1040 | I10: Decimal number, e.g. 22.
A11: inclusion_or_dosage | B11: Inclusion rate / dosage | C11: Kiwango cha kuchanganya / dozi | D11: product | E11: text | F11: N | G11: C1020, C1030, C20, C30 | H11: free text | I11: Copy from label; never invent.
A12: withdrawal_meat_days | B12: Withdrawal - meat (days) | C12: Muda wa kusubiri - nyama | D12: product | E12: integer | F12: N | G12: C30 (where applicable) | I12: From label only.
A13: withdrawal_eggs_days | B13: Withdrawal - eggs (days) | C13: Muda wa kusubiri - mayai | D13: product | E13: integer | F13: N | G13: C30 poultry | I13: From label only.
A14: withdrawal_milk_days | B14: Withdrawal - milk (days) | C14: Muda wa kusubiri - maziwa | D14: product | E14: integer | F14: N | G14: C30 dairy | I14: From label only.
A15: regulatory_class | B15: Regulatory class | C15: Kundi la udhibiti | D15: product | E15: enum | F15: N | G15: ALL | H15: Attribute_Values | I15: Set from registration status, not from packaging wording.
A16: prescription_required | B16: Prescription / vet supervision required | C16: Inahitaji cheti cha daktari | D16: product | E16: boolean | F16: N | G16: C30, C40 | I16: If TRUE: checkout must collect prescription or route to vet; decide flow before go-live.
A17: registration_no | B17: Registration number | C17: Namba ya usajili | D17: product | E17: text | F17: N | G17: Regulated classes | I17: Dummy values in this file start DEMO-.
A18: cold_chain_required | B18: Cold chain required | C18: Inahitaji ubaridi | D18: product | E18: boolean | F18: N | G18: C40, C7040, some C30 | I18: Only stores with cold_chain_capable=TRUE may stock/fulfil.
A19: storage | B19: Storage conditions | C19: Uhifadhi | D19: product | E19: text | F19: N | G19: C20, C30, C40
A20: capacity | B20: Capacity / size | C20: Ujazo / ukubwa | D20: product | E20: text | F20: N | G20: C60 | I20: e.g. 10 L, 528 eggs, 96 birds.
A21: power_source | B21: Power source | C21: Chanzo cha nishati | D21: product | E21: enum | F21: N | G21: C6020, C6040 | H21: Attribute_Values
A22: breed_strain | B22: Breed / strain | C22: Aina / mbegu | D22: product | E22: text | F22: N | G22: C70
A23: brand_id | B23: Brand | C23: Chapa | D23: product | E23: fk | F23: N | G23: ALL | H23: Brands | I23: Brand = name on the pack.
A24: producer_id | B24: Producer / manufacturer | C24: Mtengenezaji | D24: product | E24: fk | F24: N | G24: Optional | H24: Brands | I24: Who made it. May differ from brand owner and from the seller.
A25: search_keywords | B25: Search keywords (SW/EN) | C25: Maneno ya utafutaji | D25: product | E25: text (pipe-separated) | F25: Y | G25: ALL | H25: Search_Keywords + free | I25: Kiswahili names, local names, problems solved.
A26: pack_size_value | B26: Pack size value | C26: Ukubwa wa kifurushi | D26: variant | E26: number | F26: N | G26: ALL variants | I26: Pack size lives on the VARIANT, never in the product name.
A27: pack_size_unit | B27: Pack size unit | C27: Kipimo | D27: variant | E27: enum | F27: N | G27: ALL variants | H27: Attribute_Values
A28: selling_unit | B28: Selling unit | C28: Kipimo cha kuuzia | D28: variant | E28: enum | F28: N | G28: ALL variants | H28: Attribute_Values | I28: Matches the live 'Selling unit' list plus bird/head/straw.
A29: net_weight_kg | B29: Shipping weight (kg) | C29: Uzito wa usafirishaji | D29: variant | E29: number | F29: N | G29: ALL variants | I29: Needed for delivery cost.
A30: gtin | B30: Barcode (GTIN-13) | C30: Msimbo pau | D30: variant | E30: text | F30: N | G30: Optional | I30: Dummy codes use the 200-299 in-store prefix.
A31: qty_on_hand | B31: Quantity on hand | C31: Idadi iliyopo | D31: store_inventory | E31: integer | F31: N | G31: ALL
A32: reorder_level | B32: Reorder level | C32: Kiwango cha kuagiza tena | D32: store_inventory | E32: integer | F32: N | G32: ALL | I32: Drives 'Low stock'.
A33: cost_price_tzs | B33: Cost price (TZS) | C33: Bei ya kununua | D33: store_inventory | E33: integer | F33: N | G33: ALL
A34: selling_price_tzs | B34: Selling price (TZS) | C34: Bei ya kuuza | D34: store_inventory | E34: integer | F34: N | G34: ALL | I34: Price is per STORE, so regions can differ.
A35: batch_no | B35: Batch number | C35: Namba ya batch | D35: store_inventory | E35: text | F35: N | G35: Perishables
A36: expiry_date | B36: Expiry date | C36: Tarehe ya kuisha muda | D36: store_inventory | E36: date | F36: N | G36: C10, C20, C30, C40, C50 | I36: Drives 'Expiring soon'; expired stock must not be sold.
A37: listed_online | B37: Listed online | C37: Imewekwa mtandaoni | D37: store_inventory | E37: boolean | F37: N | G37: ALL
A38: online_qty | B38: Units exposed online | C38: Idadi mtandaoni | D38: store_inventory | E38: integer | F38: N | G38: ALL | I38: <= qty_on_hand.
A39: min_order_qty | B39: Minimum order quantity | C39: Kiwango cha chini cha oda | D39: variant | E39: integer | F39: N | G39: ALL variants (50 for day-old chicks) | I39: Checkout must enforce it.
A40: hatch_date | B40: Hatch date | C40: Tarehe ya kutotoa | D40: hatch_schedule | E40: date | F40: N | G40: C7010 | I40: One row per seller x SKU x hatch date (Oda hatch schedule).
A41: order_cutoff_date | B41: Order cut-off date | C41: Mwisho wa kuagiza | D41: hatch_schedule | E41: date | F41: N | G41: C7010 | I41: Bookings close after this date.
A42: price_per_chick_tzs | B42: Price per chick (TZS) | C42: Bei kwa kifaranga | D42: hatch_schedule | E42: integer | F42: N | G42: C7010 | I42: Can differ per hatch date.
A43: capacity_chicks | B43: Capacity (chicks) | C43: Uwezo (vifaranga) | D43: hatch_schedule | E43: integer | F43: N | G43: C7010 | I43: Fixed volume set by the hatchery.
A44: booked_chicks | B44: Booked (chicks) | C44: Vilivyoagizwa | D44: hatch_schedule | E44: integer | F44: N | G44: C7010 | I44: Date shows FULL when booked >= capacity (Oda rule).
A45: oda_commission_per_chick_tzs | B45: Oda commission per chick (TZS) | C45: Kamisheni ya Oda kwa kifaranga | D45: hatch_schedule | E45: integer | F45: N | G45: C7010 | I45: Supplier-side commission, split by Selcom. Rates still being negotiated (50-70 TZS range).

Sheet Attribute_Values
A1: attribute_key | B1: value_code | C1: label_en | D1: label_sw
A2: production_purpose | B2: broiler | C2: Broiler (meat) | D2: Kuku wa nyama
A3: production_purpose | B3: layer | C3: Layer (eggs) | D3: Kuku wa mayai
A4: production_purpose | B4: improved_indigenous | C4: Improved indigenous (Sasso, Kuroiler, Tanbro) | D4: Kuku chotara / kienyeji kilichoboreshwa
A5: production_purpose | B5: breeder | C5: Breeder / parent stock | D5: Wazazi
A6: production_purpose | B6: dairy | C6: Dairy | D6: Maziwa
A7: production_purpose | B7: beef | C7: Beef | D7: Nyama ya ng'ombe
A8: production_purpose | B8: meat_small_ruminant | C8: Meat (goats/sheep) | D8: Nyama (mbuzi/kondoo)
A9: production_purpose | B9: pork | C9: Pork | D9: Nyama ya nguruwe
A10: production_purpose | B10: table_fish | C10: Table fish | D10: Samaki wa chakula
A11: production_purpose | B11: general | C11: General / multi-purpose | D11: Matumizi ya jumla
A12: form | B12: mash | C12: Mash | D12: Unga
... A119: selling_unit | B119: set | C119: set | D119: seti

Sheet Search_Keywords
A1: term | B1: language | C1: maps_to_type | D1: maps_to_id | E1: notes
A2: kuku | B2: sw | C2: animal | D2: AN-CHK
A3: vifaranga | B3: sw | C3: category | D3: C7010 | E3: Also boosts starter feed (LS-POU-STR).
A4: kuku wa nyama | B4: sw | C4: production_purpose | D4: broiler
A5: broila | B5: sw | C5: production_purpose | D5: broiler | E5: Common Swahili spelling
A6: kuku wa mayai | B6: sw | C6: production_purpose | D6: layer
A7: leya | B7: sw | C7: production_purpose | D7: layer | E7: Common Swahili spelling
A8: kuku wa kienyeji | B8: sw | C8: production_purpose | D8: improved_indigenous
A9: chotara | B9: sw | C9: production_purpose | D9: improved_indigenous
A10: bata | B10: sw | C10: animal | D10: AN-OPO
A11: ng'ombe | B11: sw | C11: animal | D11: AN-CAT | E11: Also index 'ngombe' without apostrophe
A12: ng'ombe wa maziwa | B12: sw | C12: animal | D12: AN-DCT
A13: mbuzi | B13: sw | C13: animal | D13: AN-GOT
A14: kondoo | B14: sw | C14: animal | D14: AN-SHP
A15: nguruwe | B15: sw | C15: animal | D15: AN-PIG
A16: samaki | B16: sw | C16: animal | D16: AN-FSH
A17: sato | B17: sw | C17: animal | D17: AN-TIL
A18: kambale | B18: sw | C18: animal | D18: AN-CAF
A19: sungura | B19: sw | C19: animal | D19: AN-OTH
A20: chakula | B20: sw | C20: category | D20: C10
A21: chakula cha kuku | B21: sw | C21: category+animal | D21: C10|AN-CHK
A22: pumba | B22: sw | C22: product_term | D22: maize bran | E22: Raw material C1040
A23: mashudu | B23: sw | C23: product_term | D23: sunflower cake | E23: Raw material C1040
A24: soya | B24: sw | C24: product_term | D24: soybean meal
A25: dagaa | B25: sw | C25: product_term | D25: fish meal
A26: chokaa | B26: sw | C26: product_term | D26: limestone
A27: mahindi | B27: sw | C27: product_term | D27: maize
A28: majani makavu | B28: sw | C28: product_term | D28: hay | E28: C1050
A29: kontsentreti | B29: sw | C29: category | D29: C1020 | E29: Also 'concentrate'
A30: premiksi | B30: sw | C30: category | D30: C1030
A31: vitamini | B31: sw | C31: category | D31: C2010
A32: madini | B32: sw | C32: category | D32: C2030
A33: jiwe la chumvi | B33: sw | C33: category | D33: C2030 | E33: Mineral lick
A34: dawa | B34: sw | C34: category | D34: C30
A35: dawa ya minyoo | B35: sw | C35: category | D35: C3020
A36: minyoo | B36: sw | C36: use_case | D36: worms
A37: kupe | B37: sw | C37: use_case | D37: ticks
A38: utitiri | B38: sw | C38: use_case | D38: mites_lice
A39: chawa | B39: sw | C39: use_case | D39: mites_lice
A40: kuhara damu | B40: sw | C40: use_case | D40: coccidiosis
A41: kuhara | B41: sw | C41: use_case | D41: diarrhoea
A42: mafua | B42: sw | C42: use_case | D42: respiratory
A43: vidonda | B43: sw | C43: use_case | D43: wounds
A44: joto | B44: sw | C44: use_case | D44: heat_stress
A45: joto kali | B45: sw | C45: use_case | D45: heat_stress
... A59: panya | B59: sw | C59: use_case | D59: rodents
A60: chombo cha maji | B60: sw | C60: category | D60: C6010 | E60: Drinker
A61: drinka | B61: sw | C61: category | D61: C6010 | E61: Common loan word
A62: fida | B62: sw | C62: category | D62: C6010 | E62: Feeder, common loan word
A63: bruda | B63: sw | C63: category | D63: C6020 | E63: Brooder
A64: taa ya joto | B64: sw | C64: category | D64: C6020
A65: banda | B65: sw | C65: category | D65: C6030
A66: kizimba | B66: sw | C66: category | D66: C6030 | E66: Cage
A67: mashine ya kutotolesha | B67: sw | C67: category | D67: C6040
A68: incubator | B68: en | C68: category | D68: C6040
A69: trei za mayai | B69: sw | C69: category | D69: C6050
A70: sindano | B70: sw | C70: category | D70: C6060
A71: mizani | B71: sw | C71: category | D71: C6080
A72: uhimilishaji | B72: sw | C72: category | D72: C7040 | E72: Artificial insemination
A73: mbegu ya ng'ombe | B73: sw | C73: category | D73: C7040
A74: heat stress | B74: en | C74: use_case | D74: heat_stress
A75: dewormer | B75: en | C75: category | D75: C3020
A76: electrolyte | B76: en | C76: category | D76: C2020

Sheet Brands
A1: brand_id | B1: name | C1: role | D1: country | E1: is_demo | F1: notes
A2: BR-AMS | B2: Amsterdam Group | C2: Brand owner / distributor / feed manufacturer | D2: Tanzania | E2: FALSE | F2: Real seller. Pig concentrate is made in Tegeta-Wazo per bag label; Vitamix/Clear Heat sachets are made by a contract manufacturer in China per label.
A3: BR-SIL | B3: Silverlands | C3: Manufacturer (feed, day-old chicks) | D3: Tanzania | E3: FALSE | F3: Already a producer in the live system. Products/prices here are dummy.
A4: BR-BORA | B4: Bora Feeds (demo) | C4: Manufacturer (feed) | D4: Tanzania | E4: TRUE | F4: Already in the live system as a demo producer.
A5: BR-SHF | B5: Shamba Feeds (demo) | C5: Manufacturer (feed) | D5: Tanzania | E5: TRUE | F5: Fictional.
A6: BR-ULU | B6: Uluguru Agro (demo) | C6: Manufacturer (ruminant feed, licks) | D6: Tanzania | E6: TRUE | F6: Fictional.
A7: BR-ZWA | B7: Ziwa Aqua (demo) | C7: Manufacturer (fish feed, fingerlings) | D7: Tanzania | E7: TRUE | F7: Fictional.
A8: BR-NYR | B8: Nyanda Raw Materials (demo) | C8: Supplier (raw materials) | D8: Tanzania | E8: TRUE | F8: Fictional.
A9: BR-NYN | B9: Nyanda Nutrition (demo) | C9: Manufacturer (premixes, additives) | D9: Tanzania | E9: TRUE | F9: Fictional.
A10: BR-KLV | B10: KiliVet (demo) | C10: Manufacturer (supplements) | D10: Kenya | E10: TRUE | F10: Fictional.
A11: BR-AFM | B11: Afya Mifugo Pharma (demo) | C11: Manufacturer (veterinary medicines) | D11: India | E11: TRUE | F11: Fictional.
A12: BR-KNG | B12: Kinga Vaccines (demo) | C12: Manufacturer (vaccines) | D12: Tanzania | E12: TRUE | F12: Fictional.
... A25: BR-INTR | B25: Interchick | C25: Hatchery (day-old chicks) | D25: Tanzania | E25: FALSE | F25: Oda supplier migrated into the catalogue. Chick types as on Oda; prices and capacities in this file are dummy.

Sheet Sellers
A1: seller_id | B1: seller_type | C1: display_name | D1: legal_name | E1: website | F1: hq_phone | G1: hq_store_id | H1: status | I1: notes
A2: SEL-AMS | B2: Agrovet (multi-store) | C2: Amsterdam Group | D2: Amsterdam Group (legal name to confirm) | E2: www.amsterdamgroup.co.tz | F2: +255 622 531 253 | G2: ST-AMS-TEG | H2: active | I2: Website and phone as printed on the Amsterdam product catalogue. Live system currently spells the seller 'Amsterderm Group' and stores 'Amsterdem Group' - standardise to 'Amsterdam'.
A3: SEL-KIBO | B3: Hatchery | C3: Kibo | D3: Kibo (legal name to confirm) | H3: migrate from Oda tenant | I3: Hatchery seller. Was Oda tenant at kibo.oda.co.tz (slug pattern assumed from kibo.oda.co.tz). Map its Selcom merchant account; Oda commission is charged per chick.
A4: SEL-HARS | B4: Hatchery | C4: Harsho | D4: Harsho (legal name to confirm) | H4: migrate from Oda tenant | I4: Hatchery seller. Was Oda tenant at harsho.oda.co.tz (slug pattern assumed from kibo.oda.co.tz). Map its Selcom merchant account; Oda commission is charged per chick.
A5: SEL-BACK | B5: Hatchery | C5: Backbone | D5: Backbone (legal name to confirm) | H5: migrate from Oda tenant | I5: Hatchery seller. Was Oda tenant at backbone.oda.co.tz (slug pattern assumed from kibo.oda.co.tz). Map its Selcom merchant account; Oda commission is charged per chick.
A6: SEL-IRVN | B6: Hatchery | C6: Irvines | D6: Irvines (legal name to confirm) | H6: migrate from Oda tenant | I6: Hatchery seller. Was Oda tenant at irvines.oda.co.tz (slug pattern assumed from kibo.oda.co.tz). Map its Selcom merchant account; Oda commission is charged per chick.
A7: SEL-ORGN | B7: Hatchery | C7: Organia | D7: Organia (legal name to confirm) | H7: migrate from Oda tenant | I7: Hatchery seller. Was Oda tenant at organia.oda.co.tz (slug pattern assumed from kibo.oda.co.tz). Map its Selcom merchant account; Oda commission is charged per chick.
A8: SEL-HAPP | B8: Hatchery | C8: Happy Chicks | D8: Happy Chicks (legal name to confirm) | H8: migrate from Oda tenant | I8: Hatchery seller. Was Oda tenant at happychicks.oda.co.tz (slug pattern assumed from kibo.oda.co.tz). Map its Selcom merchant account; Oda commission is charged per chick.
A9: SEL-CENT | B9: Hatchery | C9: Central Chicks (Animal Care) | D9: Central Chicks (Animal Care) (legal name to confirm) | H9: migrate from Oda tenant | I9: Hatchery seller. Was Oda tenant at centralchicks.oda.co.tz (slug pattern assumed from kibo.oda.co.tz). Map its Selcom merchant account; Oda commission is charged per chick.
A10: SEL-TPF | B10: Hatchery | C10: Tanzania Poultry Farms | D10: Tanzania Poultry Farms (legal name to confirm) | H10: migrate from Oda tenant | I10: Hatchery seller. Was Oda tenant at tpf.oda.co.tz (slug pattern assumed from kibo.oda.co.tz). Map its Selcom merchant account; Oda commission is charged per chick.
A11: SEL-MKUZ | B11: Hatchery | C11: Mkuza Chicks | D11: Mkuza Chicks (legal name to confirm) | H11: migrate from Oda tenant | I11: Hatchery seller. Was Oda tenant at mkuza.oda.co.tz (slug pattern assumed from kibo.oda.co.tz). Map its Selcom merchant account; Oda commission is charged per chick.
A12: SEL-INTR | B12: Hatchery | C12: Interchick | D12: Interchick (legal name to confirm) | H12: migrate from Oda tenant | I12: Hatchery seller. Was Oda tenant at interchick.oda.co.tz (slug pattern assumed from kibo.oda.co.tz). Map its Selcom merchant account; Oda commission is charged per chick.
A13: SEL-SIL | B13: Hatchery | C13: Silverlands | D13: Silverlands (legal name to confirm) | H13: migrate from Oda tenant | I13: Hatchery seller. Was Oda tenant at silverlands.oda.co.tz (slug pattern assumed from kibo.oda.co.tz). Map its Selcom merchant account; Oda commission is charged per chick.

Sheet Regions
A1: region_id | B1: region_name | C1: centroid_lat | D1: centroid_lng | E1: zone | F1: store_count
A2: REG-DAR | B2: Dar es Salaam | C2: -6.823 | D2: 39.27 | E2: Coastal | F2: =COUNTIF(Stores!$E:$E,A2) -> 2
A3: REG-MOR | B3: Morogoro | C3: -6.821 | D3: 37.661 | E3: Eastern / central corridor | F3: =COUNTIF(Stores!$E:$E,A3) -> 1
A4: REG-MBY | B4: Mbeya | C4: -8.9 | D4: 33.45 | E4: Southern Highlands | F4: =COUNTIF(Stores!$E:$E,A4) -> 1
A5: REG-ARU | B5: Arusha | C5: -3.367 | D5: 36.683 | E5: Northern | F5: =COUNTIF(Stores!$E:$E,A5) -> 1
A6: REG-MWZ | B6: Mwanza | C6: -2.517 | D6: 32.9 | E6: Lake Zone | F6: =COUNTIF(Stores!$E:$E,A6) -> 1

Sheet Stores
A1: store_id | B1: store_code | C1: seller_id | D1: store_name | E1: region_id | F1: district | G1: area | H1: street_address | I1: landmark | J1: latitude | K1: longitude | L1: store_type | M1: is_hq | N1: phone | O1: whatsapp | P1: email | Q1: opening_hours | R1: manager | S1: delivery_radius_km | T1: delivery_base_fee_tzs | U1: delivery_fee_per_km_tzs | V1: cold_chain_capable | W1: pickup_available | X1: vet_advice_on_site | Y1: bio_en | Z1: bio_sw | AA1: km_to_hq_straight_line
A2: ST-AMS-TEG | B2: TEG | C2: SEL-AMS | D2: Amsterdam Group - Tegeta (HQ & Warehouse) | E2: REG-DAR | F2: Kinondoni | G2: Tegeta / Wazo | H2: Bagamoyo Road, Tegeta-Wazo (demo address) | I2: Near Tegeta bus stand (demo) | J2: -6.6465 | K2: 39.2112 | L2: Flagship + central warehouse | M2: TRUE | N2: +255 622 531 253 | O2: +255 622 531 253 | P2: tegeta.amsterdam@example.com | Q2: Mon-Sat 07:30-18:30; Sun 09:00-14:00 | R2: Neema Mushi (demo) | S2: 30 | T2: 5000 | U2: 500 | V2: TRUE | W2: TRUE | X2: TRUE | Y2: Amsterdam Group's head office and main warehouse in Tegeta-Wazo, serving poultry and pig farmers across northern Dar es Salaam and Bagamoyo. Full range of feeds, concentrates, supplements, animal health products and equipment, with same-day delivery within 30 km and a livestock officer on site for advice. | Z2: Ofisi kuu na ghala kuu la Amsterdam Group lililopo Tegeta-Wazo, likiwahudumia wafugaji wa kuku na nguruwe wa kaskazini mwa Dar es Salaam na Bagamoyo. Tuna vyakula, kontsentreti, virutubisho, dawa na vifaa vya mifugo, pamoja na usafirishaji wa siku hiyo hiyo ndani ya kilomita 30 na afisa mifugo wa kukushauri. | AA2: =ROUND(6371*ACOS(MIN(1,COS(RADIANS(90-J2))*COS(RADIANS(90-$J$2))+SIN(RADIANS(90-J2))*SIN(RADIANS(90-$J$2))*COS(RADIANS(K2-$K$2)))),1) -> 0
A3: ST-AMS-PST | B3: PST | C3: SEL-AMS | D3: Amsterdam Group - Posta (City Centre) | E3: REG-DAR | F3: Ilala | G3: Posta / Kisutu | H3: Azikiwe Street, Posta (demo address) | I3: Near Posta Mpya (demo) | J3: -6.8163 | K3: 39.2886 | L3: City-centre outlet (small format) | M3: FALSE | N3: +255 700 000 102 | O3: +255 700 000 102 | P3: posta.amsterdam@example.com | Q3: Mon-Fri 08:00-17:30; Sat 08:30-14:00; Sun closed | R3: Juma Said (demo) | S3: 15 | T3: 4000 | U3: 600 | V3: TRUE | W3: TRUE | X3: FALSE | Y3: Compact city-centre outlet in Posta for vaccines, medicines, vitamins and small equipment. Vaccines are kept in a monitored 2-8 C fridge. Bulk feed ordered here is delivered from the Tegeta warehouse. | Z3: Duka dogo katikati ya jiji, Posta, kwa chanjo, dawa, vitamini na vifaa vidogo. Chanjo huhifadhiwa kwenye friji ya nyuzi joto 2-8 inayofuatiliwa. Vyakula vya jumla vinavyoagizwa hapa husafirishwa kutoka ghala la Tegeta. | AA3: =ROUND(6371*ACOS(MIN(1,COS(RADIANS(90-J3))*COS(RADIANS(90-$J$2))+SIN(RADIANS(90-J3))*SIN(RADIANS(90-$J$2))*COS(RADIANS(K3-$K$2)))),1) -> 20.7
A4: ST-AMS-MOR | B4: MOR | C4: SEL-AMS | D4: Amsterdam Group - Morogoro | E4: REG-MOR | F4: Morogoro Municipal | G4: Mji Mkuu / Main Market | H4: Boma Road, Morogoro (demo address) | I4: Near Morogoro central market (demo) | J4: -6.8243 | K4: 37.6618 | L4: Regional branch | M4: FALSE | N4: +255 700 000 103 | O4: +255 700 000 103 | P4: morogoro.amsterdam@example.com | Q4: Mon-Sat 07:30-18:00; Sun closed | R4: Rehema Mlay (demo) | S4: 25 | T4: 4000 | U4: 500 | V4: TRUE | W4: TRUE | X4: TRUE | Y4: Branch on the Dar-Dodoma corridor serving poultry, pig and dairy farmers in Morogoro Municipality, Mvomero and Kilosa. Stocks feeds, raw materials, supplements, vaccines and animal health products, with delivery within 25 km. | Z4: Tawi lililopo kwenye barabara ya Dar-Dodoma, likiwahudumia wafugaji wa kuku, nguruwe na ng'ombe wa maziwa wa Manispaa ya Morogoro, Mvomero na Kilosa. Tuna vyakula, malighafi, virutubisho, chanjo na dawa za mifugo, pamoja na usafirishaji ndani ya kilomita 25. | AA4: =ROUND(6371*ACOS(MIN(1,COS(RADIANS(90-J4))*COS(RADIANS(90-$J$2))+SIN(RADIANS(90-J4))*SIN(RADIANS(90-$J$2))*COS(RADIANS(K4-$K$2)))),1) -> 172.2
A5: ST-AMS-MBY | B5: MBY | C5: SEL-AMS | D5: Amsterdam Group - Mbeya | E5: REG-MBY | F5: Mbeya City | G5: Mwanjelwa | H5: Tanzam Highway, Mwanjelwa (demo address) | I5: Near Mwanjelwa market (demo) | J5: -8.9068 | K5: 33.4512 | L5: Regional branch | M5: FALSE | N5: +255 700 000 104 | O5: +255 700 000 104 | P5: mbeya.amsterdam@example.com | Q5: Mon-Sat 08:00-18:00; Sun closed | R5: Baraka Mwakyusa (demo) | S5: 30 | T5: 5000 | U5: 600 | V5: TRUE | W5: TRUE | X5: TRUE | Y5: Southern Highlands branch serving pig and dairy farmers in Mbeya City, Mbalizi and Rungwe, plus a growing broiler market. Strong on pig concentrates, locally sourced raw materials such as maize bran and sunflower cake, and cattle health products. | Z5: Tawi la Nyanda za Juu Kusini linalowahudumia wafugaji wa nguruwe na ng'ombe wa maziwa wa Jiji la Mbeya, Mbalizi na Rungwe, pamoja na wafugaji wa kuku wa nyama. Tuna kontsentreti za nguruwe, malighafi za ndani kama pumba na mashudu ya alizeti, na dawa za ng'ombe. | AA5: =ROUND(6371*ACOS(MIN(1,COS(RADIANS(90-J5))*COS(RADIANS(90-$J$2))+SIN(RADIANS(90-J5))*SIN(RADIANS(90-$J$2))*COS(RADIANS(K5-$K$2)))),1) -> 682.5
A6: ST-AMS-ARU | B6: ARU | C6: SEL-AMS | D6: Amsterdam Group - Arusha | E6: REG-ARU | F6: Arusha City | G6: Kilombero / Sokoine Road | H6: Sokoine Road, Arusha (demo address) | I6: Near Kilombero market (demo) | J6: -3.3745 | K6: 36.6862 | L6: Regional branch | M6: FALSE | N6: +255 700 000 105 | O6: +255 700 000 105 | P6: arusha.amsterdam@example.com | Q6: Mon-Sat 07:30-18:00; Sun 09:00-13:00 | R6: Lightness Laizer (demo) | S6: 30 | T6: 5000 | U6: 600 | V6: TRUE | W6: TRUE | X6: TRUE | Y6: Northern zone branch serving layer and dairy farmers in Arusha City, Arumeru and along the Moshi road. Wide range of layer feeds, dairy meal, mineral licks, tick control and cold-stored vaccines, plus dairy semen for AI technicians. | Z6: Tawi la Kanda ya Kaskazini linalowahudumia wafugaji wa kuku wa mayai na ng'ombe wa maziwa wa Jiji la Arusha, Arumeru na barabara ya Moshi. Tuna vyakula vya kuku wa mayai, chakula cha ng'ombe wa maziwa, mawe ya madini, dawa za kupe, chanjo zilizohifadhiwa kwenye ubaridi na mbegu za uhimilishaji. | AA6: =ROUND(6371*ACOS(MIN(1,COS(RADIANS(90-J6))*COS(RADIANS(90-$J$2))+SIN(RADIANS(90-J6))*SIN(RADIANS(90-$J$2))*COS(RADIANS(K6-$K$2)))),1) -> 458.9
A7: ST-AMS-MWZ | B7: MWZ | C7: SEL-AMS | D7: Amsterdam Group - Mwanza | E7: REG-MWZ | F7: Ilemela | G7: Kirumba | H7: Kenyatta Road, Kirumba (demo address) | I7: Near Kirumba market (demo) | J7: -2.5085 | K7: 32.9105 | L7: Regional branch | M7: FALSE | N7: +255 700 000 106 | O7: +255 700 000 106 | P7: mwanza.amsterdam@example.com | Q7: Mon-Sat 07:30-18:00; Sun closed | R7: Paulo Masanja (demo) | S7: 30 | T7: 5000 | U7: 600 | V7: TRUE | W7: TRUE | X7: FALSE | Y7: Lake Zone branch serving fish farmers around Lake Victoria as well as poultry and cattle keepers in Ilemela, Nyamagana and Misungwi. Stocks floating fish feeds and fingerlings, poultry feeds and cattle health products. | Z7: Tawi la Kanda ya Ziwa linalowahudumia wafugaji wa samaki wa Ziwa Victoria pamoja na wafugaji wa kuku na ng'ombe wa Ilemela, Nyamagana na Misungwi. Tuna vyakula vya samaki vinavyoelea, vifaranga vya samaki, vyakula vya kuku na dawa za ng'ombe. | AA7: =ROUND(6371*ACOS(MIN(1,COS(RADIANS(90-J7))*COS(RADIANS(90-$J$2))+SIN(RADIANS(90-J7))*SIN(RADIANS(90-$J$2))*COS(RADIANS(K7-$K$2)))),1) -> 836.2

Sheet Products
A1: product_id | B1: product_name | C1: brand_id | D1: brand_name | E1: producer_id | F1: top_category_id | G1: category_id | H1: category_path | I1: animal_types | J1: life_stages | K1: production_purpose | L1: form | M1: administration_route | N1: use_cases | O1: disease_target | P1: active_ingredients | Q1: crude_protein_pct | R1: inclusion_or_dosage | S1: withdrawal_meat_days | T1: withdrawal_eggs_days | U1: withdrawal_milk_days | V1: regulatory_class | W1: prescription_required | X1: cold_chain_required | Y1: storage | Z1: registration_no | AA1: capacity | AB1: power_source | AC1: breed_strain | AD1: country_of_origin | AE1: search_keywords | AF1: description_en | AG1: variant_count | AH1: is_demo_data
A2: P001 | B2: Broiler Starter Crumbs | C2: BR-SIL | D2: Silverlands | E2: BR-SIL | F2: C10 | G2: C1010 | H2: Feed > Complete feed | I2: AN-CHK | J2: LS-POU-STR | K2: broiler | L2: crumbs | M2: not_applicable | N2: early_growth|weight_gain | Q2: 22 | V2: feed | W2: FALSE | X2: FALSE | Y2: Cool, dry place below 30 C, off the floor | Z2: DEMO-FEE-0001 | AD2: Tanzania | AE2: chakula cha vifaranga|starter|broila|kuku wa nyama | AF2: Starter crumbs for broiler chicks from day 1 to about day 14. | AG2: =COUNTIF(Variants!$B:$B,A2) -> 2 | AH2: TRUE
A3: P002 | B3: Broiler Grower Pellets | C3: BR-SIL | D3: Silverlands | E3: BR-SIL | F3: C10 | G3: C1010 | H3: Feed > Complete feed | I3: AN-CHK | J3: LS-POU-GRW | K3: broiler | L3: pellets | M3: not_applicable | N3: weight_gain | Q3: 20 | V3: feed | W3: FALSE | X3: FALSE | Y3: Cool, dry place below 30 C, off the floor | Z3: DEMO-FEE-0002 | AD3: Tanzania | AE3: grower|broila|kuku wa nyama | AF3: Grower pellets for broilers from about day 15 to day 28. | AG3: =COUNTIF(Variants!$B:$B,A3) -> 2 | AH3: TRUE
A4: P003 | B4: Broiler Finisher Pellets | C4: BR-SIL | D4: Silverlands | E4: BR-SIL | F4: C10 | G4: C1010 | H4: Feed > Complete feed | I4: AN-CHK | J4: LS-POU-FIN | K4: broiler | L4: pellets | M4: not_applicable | N4: weight_gain | Q4: 19 | V4: feed | W4: FALSE | X4: FALSE | Y4: Cool, dry place below 30 C, off the floor | Z4: DEMO-FEE-0003 | AD4: Tanzania | AE4: finisher|broila|kunenepesha | AF4: Finisher pellets for broilers from day 29 to market. | AG4: =COUNTIF(Variants!$B:$B,A4) -> 2 | AH4: TRUE
A5: P004 | B5: Chick & Duck Mash | C5: BR-SHF | D5: Shamba Feeds (demo) | E5: BR-SHF | F5: C10 | G5: C1010 | H5: Feed > Complete feed | I5: AN-CHK|AN-OPO | J5: LS-POU-STR | K5: layer|improved_indigenous | L5: mash | M5: not_applicable | N5: early_growth | Q5: 20 | V5: feed | W5: FALSE | X5: FALSE | Y5: Cool, dry place below 30 C, off the floor | Z5: DEMO-FEE-0004 | AD5: Tanzania | AE5: chakula cha vifaranga|vifaranga wa mayai|bata | AF5: Starter mash for layer and improved-indigenous chicks and ducklings, 0-8 weeks. | AG5: =COUNTIF(Variants!$B:$B,A5) -> 1 | AH5: TRUE
A6: P005 | B6: Growers Mash | C6: BR-BORA | D6: Bora Feeds (demo) | E6: BR-BORA | F6: C10 | G6: C1010 | H6: Feed > Complete feed | I6: AN-CHK | J6: LS-POU-GRW | K6: layer | L6: mash | M6: not_applicable | N6: early_growth | Q6: 16 | V6: feed | W6: FALSE | X6: FALSE | Y6: Cool, dry place below 30 C, off the floor | Z6: DEMO-FEE-0005 | AD6: Tanzania | AE6: grower|leya|kuku wa mayai | AF6: Grower mash for layer pullets from 9 to 18 weeks. | AG6: =COUNTIF(Variants!$B:$B,A6) -> 2 | AH6: TRUE
A7: P006 | B7: Layers Mash | C7: BR-SIL | D7: Silverlands | E7: BR-SIL | F7: C10 | G7: C1010 | H7: Feed > Complete feed | I7: AN-CHK | J7: LS-POU-LAY | K7: layer | L7: mash | M7: not_applicable | N7: egg_production | Q7: 16.5 | V7: feed | W7: FALSE | X7: FALSE | Y7: Cool, dry place below 30 C, off the floor | Z7: DEMO-FEE-0006 | AD7: Tanzania | AE7: layers|leya|kuku wa mayai|kuongeza mayai | AF7: Complete layer ration from point of lay. | AG7: =COUNTIF(Variants!$B:$B,A7) -> 2 | AH7: TRUE
A8: P007 | B8: Kienyeji Grower Mash | C8: BR-BORA | D8: Bora Feeds (demo) | E8: BR-BORA | F8: C10 | G8: C1010 | H8: Feed > Complete feed | I8: AN-CHK | J8: LS-POU-GRW | K8: improved_indigenous | L8: mash | M8: not_applicable | N8: weight_gain | Q8: 17 | V8: feed | W8: FALSE | X8: FALSE | Y8: Cool, dry place below 30 C, off the floor | Z8: DEMO-FEE-0007 | AD8: Tanzania | AE8: kuku wa kienyeji|chotara|sasso|kuroiler | AF8: Grower mash for Sasso, Kuroiler and other improved indigenous chickens. | AG8: =COUNTIF(Variants!$B:$B,A8) -> 1 | AH8: TRUE
A9: P008 | B9: Pig Creep Pellets | C9: BR-SHF | D9: Shamba Feeds (demo) | E9: BR-SHF | F9: C10 | G9: C1010 | H9: Feed > Complete feed | I9: AN-PIG | J9: LS-PIG-CRP|LS-PIG-WEA | K9: pork | L9: pellets | M9: not_applicable | N9: early_growth | Q9: 20 | V9: feed | W9: FALSE | X9: FALSE | Y9: Cool, dry place below 30 C, off the floor | Z9: DEMO-FEE-0008 | AD9: Tanzania | AE9: nguruwe|watoto wa nguruwe|creep | AF9: Highly digestible pellets for piglets from 7 days to 2 weeks after weaning. | AG9: =COUNTIF(Variants!$B:$B,A9) -> 1 | AH9: TRUE
A10: P009 | B10: Pig Grower Pellets | C10: BR-BORA | D10: Bora Feeds (demo) | E10: BR-BORA | F10: C10 | G10: C1010 | H10: Feed > Complete feed | I10: AN-PIG | J10: LS-PIG-GRW | K10: pork | L10: pellets | M10: not_applicable | N10: weight_gain | Q10: 16 | V10: feed | W10: FALSE | X10: FALSE | Y10: Cool, dry place below 30 C, off the floor | Z10: DEMO-FEE-0009 | AD10: Tanzania | AE10: nguruwe|grower | AF10: Complete grower ration for pigs from about 25 to 60 kg live weight. | AG10: =COUNTIF(Variants!$B:$B,A10) -> 1 | AH10: TRUE
A11: P010 | B11: Sow & Weaner Meal | C11: BR-SHF | D11: Shamba Feeds (demo) | E11: BR-SHF | F11: C10 | G11: C1010 | H11: Feed > Complete feed | I11: AN-PIG | J11: LS-PIG-SOW|LS-PIG-WEA | K11: pork | L11: mash | M11: not_applicable | N11: early_growth | Q11: 16 | V11: feed | W11: FALSE | X11: FALSE | Y11: Cool, dry place below 30 C, off the floor | Z11: DEMO-FEE-0010 | AD11: Tanzania | AE11: nguruwe|mama nguruwe|sow | AF11: Meal for gestating and lactating sows and newly weaned pigs. | AG11: =COUNTIF(Variants!$B:$B,A11) -> 1 | AH11: TRUE
A12: P011 | B12: Dairy Meal | C12: BR-ULU | D12: Uluguru Agro (demo) | E12: BR-ULU | F12: C10 | G12: C1010 | H12: Feed > Complete feed | I12: AN-DCT | J12: LS-CAT-LAC | K12: dairy | L12: mash | M12: not_applicable | N12: milk_yield | Q12: 16 | V12: feed | W12: FALSE | X12: FALSE | Y12: Cool, dry place below 30 C, off the floor | Z12: DEMO-FEE-0011 | AD12: Tanzania | AE12: ng'ombe wa maziwa|dairy meal|maziwa mengi | AF12: Production ration for lactating dairy cows, fed alongside forage. | AG12: =COUNTIF(Variants!$B:$B,A12) -> 2 | AH12: TRUE
A13: P012 | B13: Calf Starter Pellets | C13: BR-ULU | D13: Uluguru Agro (demo) | E13: BR-ULU | F13: C10 | G13: C1010 | H13: Feed > Complete feed | I13: AN-DCT|AN-BCT | J13: LS-CAT-CLF | K13: dairy|beef | L13: pellets | M13: not_applicable | N13: early_growth | Q13: 20 | V13: feed | W13: FALSE | X13: FALSE | Y13: Cool, dry place below 30 C, off the floor | Z13: DEMO-FEE-0012 | AD13: Tanzania | AE13: ndama|calf | AF13: Starter pellets for calves from 1 week until weaning. | AG13: =COUNTIF(Variants!$B:$B,A13) -> 1 | AH13: TRUE
... A18: P017 | B18: Rabbit Pellets | C18: BR-SHF | D18: Shamba Feeds (demo) | E18: BR-SHF | F18: C10 | G18: C1010 | H18: Feed > Complete feed | I18: AN-OTH | J18: LS-ALL | K18: general | L18: pellets | M18: not_applicable | N18: weight_gain | Q18: 17 | V18: feed | W18: FALSE | X18: FALSE | Y18: Cool, dry place below 30 C, off the floor | Z18: DEMO-FEE-0017 | AD18: Tanzania | AE18: sungura | AF18: Complete pellets for growing and breeding rabbits. | AG18: =COUNTIF(Variants!$B:$B,A18) -> 1 | AH18: TRUE
A19: P018 | B19: Pig Protein Concentrate 20% | C19: BR-AMS | D19: Amsterdam Group | E19: BR-AMS | F19: C10 | G19: C1020 | H19: Feed > Concentrates | I19: AN-PIG | J19: LS-PIG-GRW|LS-PIG-FIN | K19: pork | L19: mash | M19: in_feed | N19: weight_gain|feed_mixing | P19: Protein, vitamins, minerals, amino acids, probiotics, enzymes, toxin binder and acidifier (per bag label) | Q19: 20 | R19: Mix with maize bran/maize as per bag label | V19: feed | W19: FALSE | X19: FALSE | Y19: Cool, dry place below 30 C, off the floor | Z19: DEMO-FEE-0018 | AD19: Tanzania | AE19: nguruwe|kontsentreti|concentrate|amsterdam feed | AF19: Amsterdam Feed high-performance pig protein concentrate. CHECK: the '20%' on the bag may be crude protein or inclusion rate; confirm with Amsterdam before publishing. | AG19: =COUNTIF(Variants!$B:$B,A19) -> 2 | AH19: TRUE
A20: P019 | B20: Broiler Concentrate 30% | C20: BR-BORA | D20: Bora Feeds (demo) | E20: BR-BORA | F20: C10 | G20: C1020 | H20: Feed > Concentrates | I20: AN-CHK | J20: LS-POU-STR|LS-POU-GRW|LS-POU-FIN | K20: broiler | L20: mash | M20: in_feed | N20: feed_mixing|weight_gain | Q20: 30 | R20: Mix with maize/maize bran as per bag label | V20: feed | W20: FALSE | X20: FALSE | Y20: Cool, dry place below 30 C, off the floor | Z20: DEMO-FEE-0019 | AD20: Tanzania | AE20: kontsentreti|broila|kuchanganya chakula | AF20: Protein concentrate for farmers mixing their own broiler feed. | AG20: =COUNTIF(Variants!$B:$B,A20) -> 1 | AH20: TRUE
A21: P020 | B21: Layers Concentrate | C21: BR-SHF | D21: Shamba Feeds (demo) | E21: BR-SHF | F21: C10 | G21: C1020 | H21: Feed > Concentrates | I21: AN-CHK | J21: LS-POU-LAY | K21: layer | L21: mash | M21: in_feed | N21: feed_mixing|egg_production | Q21: 32 | R21: Mix with maize/maize bran as per bag label | V21: feed | W21: FALSE | X21: FALSE | Y21: Cool, dry place below 30 C, off the floor | Z21: DEMO-FEE-0020 | AD21: Tanzania | AE21: kontsentreti|leya|kuku wa mayai | AF21: Concentrate for home-mixed layer rations. | AG21: =COUNTIF(Variants!$B:$B,A21) -> 1 | AH21: TRUE
A22: P021 | B22: Dairy Concentrate | C22: BR-ULU | D22: Uluguru Agro (demo) | E22: BR-ULU | F22: C10 | G22: C1020 | H22: Feed > Concentrates | I22: AN-DCT | J22: LS-CAT-LAC | K22: dairy | L22: mash | M22: in_feed | N22: feed_mixing|milk_yield | Q22: 24 | R22: Mix with maize bran as per bag label | V22: feed | W22: FALSE | X22: FALSE | Y22: Cool, dry place below 30 C, off the floor | Z22: DEMO-FEE-0021 | AD22: Tanzania | AE22: kontsentreti|ng'ombe wa maziwa | AF22: Concentrate for dairy farmers mixing with maize bran or cereal by-products. | AG22: =COUNTIF(Variants!$B:$B,A22) -> 1 | AH22: TRUE
A23: P022 | B23: Broiler Premix 2.5% | C23: BR-NYN | D23: Nyanda Nutrition (demo) | E23: BR-NYN | F23: C10 | G23: C1030 | H23: Feed > Premixes & base mixes | I23: AN-CHK | J23: LS-POU-STR|LS-POU-GRW|LS-POU-FIN | K23: broiler | L23: powder | M23: in_feed | N23: feed_mixing | P23: Vitamins, trace minerals, amino acids | R23: 2.5 kg per 100 kg of feed (per label) | V23: feed_additive | W23: FALSE | X23: FALSE | Y23: Cool, dry place below 30 C, off the floor | Z23: DEMO-FEE-0022 | AD23: Tanzania | AE23: premiksi|premix|kuchanganya chakula | AF23: Vitamin-mineral premix for on-farm feed mixing. | AG23: =COUNTIF(Variants!$B:$B,A23) -> 2 | AH23: TRUE
A24: P023 | B24: Layer Premix 2.5% | C24: BR-NYN | D24: Nyanda Nutrition (demo) | E24: BR-NYN | F24: C10 | G24: C1030 | H24: Feed > Premixes & base mixes | I24: AN-CHK | J24: LS-POU-LAY | K24: layer | L24: powder | M24: in_feed | N24: feed_mixing | P24: Vitamins, trace minerals, amino acids | R24: 2.5 kg per 100 kg of feed (per label) | V24: feed_additive | W24: FALSE | X24: FALSE | Y24: Cool, dry place below 30 C, off the floor | Z24: DEMO-FEE-0023 | AD24: Tanzania | AE24: premiksi|premix|kuchanganya chakula | AF24: Vitamin-mineral premix for on-farm feed mixing. | AG24: =COUNTIF(Variants!$B:$B,A24) -> 2 | AH24: TRUE
A25: P024 | B25: Pig Premix 2.5% | C25: BR-NYN | D25: Nyanda Nutrition (demo) | E25: BR-NYN | F25: C10 | G25: C1030 | H25: Feed > Premixes & base mixes | I25: AN-PIG | J25: LS-PIG-GRW|LS-PIG-FIN|LS-PIG-SOW | K25: pork | L25: powder | M25: in_feed | N25: feed_mixing | P25: Vitamins, trace minerals, amino acids | R25: 2.5 kg per 100 kg of feed (per label) | V25: feed_additive | W25: FALSE | X25: FALSE | Y25: Cool, dry place below 30 C, off the floor | Z25: DEMO-FEE-0024 | AD25: Tanzania | AE25: premiksi|premix|kuchanganya chakula | AF25: Vitamin-mineral premix for on-farm feed mixing. | AG25: =COUNTIF(Variants!$B:$B,A25) -> 2 | AH25: TRUE
A26: P025 | B26: Maize Bran | C26: BR-NYR | D26: Nyanda Raw Materials (demo) | E26: BR-NYR | F26: C10 | G26: C1040 | H26: Feed > Raw materials & ingredients | I26: AN-CHK|AN-PIG|AN-DCT|AN-GTS | L26: mash | M26: not_applicable | N26: feed_mixing | Q26: 10 | V26: feed | W26: FALSE | X26: FALSE | Y26: Cool, dry place below 30 C, off the floor | Z26: DEMO-FEE-0025 | AD26: Tanzania | AE26: pumba|pumba za mahindi|maize bran | AF26: Maize bran for on-farm feed mixing. | AG26: =COUNTIF(Variants!$B:$B,A26) -> 1 | AH26: TRUE
A27: P026 | B27: Sunflower Seed Cake | C27: BR-NYR | D27: Nyanda Raw Materials (demo) | E27: BR-NYR | F27: C10 | G27: C1040 | H27: Feed > Raw materials & ingredients | I27: AN-CHK|AN-PIG|AN-DCT|AN-GTS | L27: whole_grain | M27: not_applicable | N27: feed_mixing | Q27: 28 | V27: feed | W27: FALSE | X27: FALSE | Y27: Cool, dry place below 30 C, off the floor | Z27: DEMO-FEE-0026 | AD27: Tanzania | AE27: mashudu|mashudu ya alizeti|sunflower cake | AF27: Sunflower cake protein source. | AG27: =COUNTIF(Variants!$B:$B,A27) -> 1 | AH27: TRUE
A28: P027 | B28: Soybean Meal | C28: BR-NYR | D28: Nyanda Raw Materials (demo) | E28: BR-NYR | F28: C10 | G28: C1040 | H28: Feed > Raw materials & ingredients | I28: AN-CHK|AN-PIG|AN-DCT | L28: mash | M28: not_applicable | N28: feed_mixing | Q28: 44 | V28: feed | W28: FALSE | X28: FALSE | Y28: Cool, dry place below 30 C, off the floor | Z28: DEMO-FEE-0027 | AD28: Tanzania | AE28: soya|soybean meal | AF28: Solvent-extracted soybean meal. | AG28: =COUNTIF(Variants!$B:$B,A28) -> 1 | AH28: TRUE
A29: P028 | B29: Fish Meal (Dagaa) | C29: BR-NYR | D29: Nyanda Raw Materials (demo) | E29: BR-NYR | F29: C10 | G29: C1040 | H29: Feed > Raw materials & ingredients | I29: AN-CHK|AN-PIG|AN-FSH | L29: mash | M29: not_applicable | N29: feed_mixing | Q29: 55 | V29: feed | W29: FALSE | X29: FALSE | Y29: Cool, dry place below 30 C, off the floor | Z29: DEMO-FEE-0028 | AD29: Tanzania | AE29: dagaa|fish meal|unga wa samaki | AF29: Ground dagaa (Lake Victoria sardine) protein meal. | AG29: =COUNTIF(Variants!$B:$B,A29) -> 2 | AH29: TRUE
A30: P029 | B30: Feed Limestone | C30: BR-NYR | D30: Nyanda Raw Materials (demo) | E30: BR-NYR | F30: C10 | G30: C1040 | H30: Feed > Raw materials & ingredients | I30: AN-CHK|AN-DCT | L30: granules | M30: not_applicable | N30: feed_mixing|egg_production | V30: feed | W30: FALSE | X30: FALSE | Y30: Cool, dry place below 30 C, off the floor | Z30: DEMO-FEE-0029 | AD30: Tanzania | AE30: chokaa|limestone|shell grit | AF30: Calcium source for layer and dairy rations. | AG30: =COUNTIF(Variants!$B:$B,A30) -> 1 | AH30: TRUE
A31: P030 | B31: Dicalcium Phosphate (DCP) | C31: BR-NYR | D31: Nyanda Raw Materials (demo) | E31: BR-NYR | F31: C10 | G31: C1040 | H31: Feed > Raw materials & ingredients | I31: AN-CHK|AN-PIG|AN-DCT | L31: powder | M31: not_applicable | N31: feed_mixing | V31: feed | W31: FALSE | X31: FALSE | Y31: Cool, dry place below 30 C, off the floor | Z31: DEMO-FEE-0030 | AD31: Imported | AE31: dcp|phosphate | AF31: Phosphorus and calcium source for feed mixing. | AG31: =COUNTIF(Variants!$B:$B,A31) -> 1 | AH31: TRUE
A32: P031 | B32: Yellow Maize (Whole) | C32: BR-NYR | D32: Nyanda Raw Materials (demo) | E32: BR-NYR | F32: C10 | G32: C1040 | H32: Feed > Raw materials & ingredients | I32: AN-CHK|AN-PIG|AN-DCT | L32: whole_grain | M32: not_applicable | N32: feed_mixing | Q32: 8.5 | V32: feed | W32: FALSE | X32: FALSE | Y32: Cool, dry place below 30 C, off the floor | Z32: DEMO-FEE-0031 | AD32: Tanzania | AE32: mahindi|maize | AF32: Whole maize grain for milling into feed. | AG32: =COUNTIF(Variants!$B:$B,A32) -> 1 | AH32: TRUE
A33: P032 | B33: Rhodes Grass Hay Bale | C33: BR-ULU | D33: Uluguru Agro (demo) | E33: BR-ULU | F33: C10 | G33: C1050 | H33: Feed > Forage & fodder | I33: AN-DCT|AN-BCT|AN-GTS | L33: baled | M33: not_applicable | N33: milk_yield | V33: feed | W33: FALSE | X33: FALSE | Y33: Dry, covered store | Z33: DEMO-FEE-0032 | AD33: Tanzania | AE33: majani makavu|hay|nyasi | AF33: Square bale of Rhodes grass hay, about 15 kg. | AG33: =COUNTIF(Variants!$B:$B,A33) -> 1 | AH33: TRUE
A34: P033 | B34: Maize Silage (Bagged) | C34: BR-ULU | D34: Uluguru Agro (demo) | E34: BR-ULU | F34: C10 | G34: C1050 | H34: Feed > Forage & fodder | I34: AN-DCT|AN-BCT | L34: baled | M34: not_applicable | N34: milk_yield | V34: feed | W34: FALSE | X34: FALSE | Y34: Keep sealed, use within 3 days of opening | Z34: DEMO-FEE-0033 | AD34: Tanzania | AE34: silage|malisho | AF34: Vacuum-bagged maize silage. | AG34: =COUNTIF(Variants!$B:$B,A34) -> 1 | AH34: TRUE
A35: P034 | B35: Vitamix Chick | C35: BR-AMS | D35: Amsterdam Group | E35: BR-AMS | F35: C20 | G35: C2010 | H35: Supplements & additives > Vitamins & multivitamins | I35: AN-CHK | J35: LS-POU-STR | K35: broiler|layer|improved_indigenous | L35: powder | M35: drinking_water | N35: early_growth|immunity|stress_vaccination_transport | P35: Vitamins, glucose, amino acids, probiotics and trace elements (per label) | R35: As per sachet label | V35: feed_additive | W35: FALSE | X35: FALSE | Y35: Cool, dry place below 30 C, off the floor | Z35: DEMO-FEE-0034 | AD35: China (contract manufactured) | AE35: vitamini|vitamini ya vifaranga|vitamix | AF35: Water-soluble chick starter premix with vitamins, probiotics and glucose for strong early growth. | AG35: =COUNTIF(Variants!$B:$B,A35) -> 3 | AH35: TRUE
A36: P035 | B36: Vitamix Plus | C36: BR-AMS | D36: Amsterdam Group | E36: BR-AMS | F36: C20 | G36: C2010 | H36: Supplements & additives > Vitamins & multivitamins | I36: AN-POU | J36: LS-ALL | K36: broiler|layer|improved_indigenous | L36: powder | M36: drinking_water | N36: weight_gain|egg_production|immunity | P36: Vitamins A, D3, E, C, B-complex, K, niacin, calcium pantothenate, amino acids, probiotics, trace elements (per label) | R36: As per sachet label | V36: feed_additive | W36: FALSE | X36: FALSE | Y36: Cool, dry place below 30 C, off the floor | Z36: DEMO-FEE-0035 | AD36: China (contract manufactured) | AE36: vitamini|multivitamin|vitamix|kuongeza mayai | AF36: Feed-grade vitamin supplement with amino acids and trace elements for performance. | AG36: =COUNTIF(Variants!$B:$B,A36) -> 3 | AH36: TRUE
A37: P036 | B37: Multivitamin Soluble Powder | C37: BR-KLV | D37: KiliVet (demo) | E37: BR-KLV | F37: C20 | G37: C2010 | H37: Supplements & additives > Vitamins & multivitamins | I37: AN-POU|AN-PIG|AN-CAT | J37: LS-ALL | K37: general | L37: powder | M37: drinking_water | N37: immunity|stress_vaccination_transport | P37: Vitamins A, D3, E, K3, B-complex, C | R37: As per label | V37: feed_additive | W37: FALSE | X37: FALSE | Y37: Cool, dry place below 30 C, off the floor | Z37: DEMO-FEE-0036 | AD37: Kenya | AE37: vitamini|multivitamin | AF37: Multi-species water-soluble multivitamin. | AG37: =COUNTIF(Variants!$B:$B,A37) -> 2 | AH37: TRUE
A38: P037 | B38: Vitamin AD3E Injectable | C38: BR-AFM | D38: Afya Mifugo Pharma (demo) | E38: BR-AFM | F38: C20 | G38: C2010 | H38: Supplements & additives > Vitamins & multivitamins | I38: AN-CAT|AN-GTS|AN-PIG | J38: LS-ALL | K38: general | L38: injectable | M38: injection_im | N38: immunity | P38: Vitamin A, D3, E | R38: As per label | V38: otc_vet_medicine | W38: FALSE | X38: FALSE | Y38: Cool, dry place below 30 C, off the floor | Z38: DEMO-OTC-0037 | AD38: India | AE38: vitamini|sindano ya vitamini|ad3e | AF38: Injectable fat-soluble vitamins. Category = Vitamins by function; regulatory class = vet medicine. | AG38: =COUNTIF(Variants!$B:$B,A38) -> 1 | AH38: TRUE
A39: P038 | B39: Layer Tonic (Egg Booster) | C39: BR-KLV | D39: KiliVet (demo) | E39: BR-KLV | F39: C20 | G39: C2060 | H39: Supplements & additives > Amino acids & tonics | I39: AN-CHK | J39: LS-POU-LAY | K39: layer | L39: liquid | M39: drinking_water | N39: egg_production | P39: Vitamins, calcium, phosphorus, amino acids | R39: As per label | V39: feed_additive | W39: FALSE | X39: FALSE | Y39: Cool, dry place below 30 C, off the floor | Z39: DEMO-FEE-0038 | AD39: Kenya | AE39: kuongeza mayai|tonic|leya | AF39: Liquid tonic supporting egg production and shell quality. | AG39: =COUNTIF(Variants!$B:$B,A39) -> 2 | AH39: TRUE
A40: P039 | B40: Clear Heat Electrolyte | C40: BR-AMS | D40: Amsterdam Group | E40: BR-AMS | F40: C20 | G40: C2020 | H40: Supplements & additives > Electrolytes & heat-stress | I40: AN-POU | J40: LS-ALL | K40: broiler|layer|improved_indigenous | L40: powder | M40: drinking_water | N40: heat_stress|dehydration|stress_vaccination_transport | P40: Sodium, potassium and magnesium salts, sodium bicarbonate, vitamin C (per label) | R40: As per sachet label | V40: feed_additive | W40: FALSE | X40: FALSE | Y40: Cool, dry place below 30 C, off the floor | Z40: DEMO-FEE-0039 | AD40: China (contract manufactured) | AE40: joto|joto kali|elektrolaiti|electrolyte|clear heat|kupunguza joto | AF40: Electrolyte supplement against heat stress, dehydration and fluid imbalance in poultry. | AG40: =COUNTIF(Variants!$B:$B,A40) -> 3 | AH40: TRUE
A41: P040 | B41: Livestock Oral Rehydration Salts | C41: BR-KLV | D41: KiliVet (demo) | E41: BR-KLV | F41: C20 | G41: C2020 | H41: Supplements & additives > Electrolytes & heat-stress | I41: AN-CAT|AN-PIG|AN-GTS | J41: LS-CAT-CLF|LS-PIG-CRP|LS-GTS-KID | K41: general | L41: powder | M41: oral_drench | N41: dehydration|diarrhoea | P41: Glucose, sodium chloride, potassium chloride, bicarbonate | R41: As per label | V41: feed_additive | W41: FALSE | X41: FALSE | Y41: Cool, dry place below 30 C, off the floor | Z41: DEMO-FEE-0040 | AD41: Kenya | AE41: kuhara|upungufu wa maji|ors | AF41: Rehydration salts for scouring calves, piglets and kids. | AG41: =COUNTIF(Variants!$B:$B,A41) -> 1 | AH41: TRUE
A42: P041 | B42: Goat & Sheep Mineral Lick | C42: BR-ULU | D42: Uluguru Agro (demo) | E42: BR-ULU | F42: C20 | G42: C2030 | H42: Supplements & additives > Minerals & licks | I42: AN-GOT|AN-SHP | J42: LS-ALL | K42: general | L42: block | M42: free_choice | N42: weight_gain | P42: Salt, macro and trace minerals | V42: feed_additive | W42: FALSE | X42: FALSE | Y42: Cool, dry place below 30 C, off the floor | Z42: DEMO-FEE-0041 | AD42: Tanzania | AE42: jiwe la chumvi|madini|mbuzi|kondoo | AF42: Mineral lick block for goats and sheep. | AG42: =COUNTIF(Variants!$B:$B,A42) -> 1 | AH42: TRUE
A43: P042 | B43: Cattle Mineral Lick Block | C43: BR-ULU | D43: Uluguru Agro (demo) | E43: BR-ULU | F43: C20 | G43: C2030 | H43: Supplements & additives > Minerals & licks | I43: AN-CAT | J43: LS-ALL | K43: dairy|beef | L43: block | M43: free_choice | N43: milk_yield|weight_gain | P43: Salt, macro and trace minerals | V43: feed_additive | W43: FALSE | X43: FALSE | Y43: Cool, dry place below 30 C, off the floor | Z43: DEMO-FEE-0042 | AD43: Tanzania | AE43: jiwe la chumvi|madini|ng'ombe | AF43: Mineral lick block for cattle. | AG43: =COUNTIF(Variants!$B:$B,A43) -> 1 | AH43: TRUE
A44: P043 | B44: Dairy Mineral Mix | C44: BR-NYN | D44: Nyanda Nutrition (demo) | E44: BR-NYN | F44: C20 | G44: C2030 | H44: Supplements & additives > Minerals & licks | I44: AN-DCT | J44: LS-CAT-LAC|LS-CAT-DRY | K44: dairy | L44: powder | M44: in_feed | N44: milk_yield | P44: Calcium, phosphorus, magnesium, trace minerals | R44: As per label | V44: feed_additive | W44: FALSE | X44: FALSE | Y44: Cool, dry place below 30 C, off the floor | Z44: DEMO-FEE-0043 | AD44: Tanzania | AE44: madini|maziwa mengi | AF44: Loose mineral mix for dairy cows. | AG44: =COUNTIF(Variants!$B:$B,A44) -> 2 | AH44: TRUE
A45: P044 | B45: Poultry Probiotic | C45: BR-NYN | D45: Nyanda Nutrition (demo) | E45: BR-NYN | F45: C20 | G45: C2040 | H45: Supplements & additives > Probiotics, enzymes & acidifiers | I45: AN-POU | J45: LS-ALL | K45: broiler|layer|improved_indigenous | L45: powder | M45: drinking_water | N45: gut_health | P45: Lactobacillus and Bacillus strains | R45: As per label | V45: feed_additive | W45: FALSE | X45: FALSE | Y45: Cool, dry place below 30 C, off the floor | Z45: DEMO-FEE-0044 | AD45: Tanzania | AE45: probiotiki|afya ya tumbo | AF45: Probiotic for gut health. | AG45: =COUNTIF(Variants!$B:$B,A45) -> 2 | AH45: TRUE
A46: P045 | B46: Phytase Feed Enzyme | C46: BR-NYN | D46: Nyanda Nutrition (demo) | E46: BR-NYN | F46: C20 | G46: C2040 | H46: Supplements & additives > Probiotics, enzymes & acidifiers | I46: AN-POU|AN-PIG | J46: LS-ALL | K46: general | L46: granules | M46: in_feed | N46: gut_health|feed_mixing | P46: Phytase | R46: As per label | V46: feed_additive | W46: FALSE | X46: FALSE | Y46: Cool, dry place below 30 C, off the floor | Z46: DEMO-FEE-0045 | AD46: Imported | AE46: enzyme|kimeng'enya | AF46: Enzyme improving phosphorus use in home-mixed feeds. | AG46: =COUNTIF(Variants!$B:$B,A46) -> 1 | AH46: TRUE
A47: P046 | B47: Mycotoxin Binder | C47: BR-NYN | D47: Nyanda Nutrition (demo) | E47: BR-NYN | F47: C20 | G47: C2050 | H47: Supplements & additives > Toxin binders | I47: AN-POU|AN-PIG|AN-CAT | J47: LS-ALL | K47: general | L47: powder | M47: in_feed | N47: mycotoxins | P47: Clay minerals, yeast cell wall | R47: As per label | V47: feed_additive | W47: FALSE | X47: FALSE | Y47: Cool, dry place below 30 C, off the floor | Z47: DEMO-FEE-0046 | AD47: Tanzania | AE47: sumu ya kuvu|aflatoxin|toxin binder | AF47: Binds aflatoxins and other mycotoxins in feed. | AG47: =COUNTIF(Variants!$B:$B,A47) -> 2 | AH47: TRUE
A48: P047 | B48: Liver Tonic & Amino Acids | C48: BR-KLV | D48: KiliVet (demo) | E48: BR-KLV | F48: C20 | G48: C2060 | H48: Supplements & additives > Amino acids & tonics | I48: AN-POU|AN-PIG | J48: LS-ALL | K48: general | L48: liquid | M48: drinking_water | N48: stress_vaccination_transport|weight_gain | P48: Methionine, lysine, sorbitol, choline, vitamins | R48: As per label | V48: feed_additive | W48: FALSE | X48: FALSE | Y48: Cool, dry place below 30 C, off the floor | Z48: DEMO-FEE-0047 | AD48: Kenya | AE48: tonic|amino | AF48: Liver support and amino acid supplement after disease or treatment. | AG48: =COUNTIF(Variants!$B:$B,A48) -> 2 | AH48: TRUE
A49: P048 | B49: Oxytetracycline 20% LA Injection | C49: BR-AFM | D49: Afya Mifugo Pharma (demo) | E49: BR-AFM | F49: C30 | G49: C3010 | H49: Medicines > Antibiotics & antibacterials | I49: AN-CAT|AN-GTS|AN-PIG | J49: LS-ALL | K49: general | L49: injectable | M49: injection_im | N49: bacterial_infection|respiratory | P49: Oxytetracycline dihydrate 200 mg/ml | R49: As directed by a veterinarian | S49: 28 | U49: 7 | V49: prescription_vet_medicine | W49: TRUE | X49: FALSE | Y49: Cool, dry place below 30 C, off the floor | Z49: DEMO-PRE-0048 | AD49: India | AE49: dawa|oxytet|sindano|antibiotic | AF49: Long-acting broad-spectrum antibiotic injection. | AG49: =COUNTIF(Variants!$B:$B,A49) -> 2 | AH49: TRUE
A50: P049 | B50: Oxytetracycline Soluble Powder | C50: BR-AFM | D50: Afya Mifugo Pharma (demo) | E50: BR-AFM | F50: C30 | G50: C3010 | H50: Medicines > Antibiotics & antibacterials | I50: AN-POU | J50: LS-ALL | K50: general | L50: powder | M50: drinking_water | N50: bacterial_infection|respiratory|diarrhoea | P50: Oxytetracycline HCl | R50: As directed by a veterinarian | S50: 7 | T50: 7 | V50: prescription_vet_medicine | W50: TRUE | X50: FALSE | Y50: Cool, dry place below 30 C, off the floor | Z50: DEMO-PRE-0049 | AD50: India | AE50: dawa ya kuku|oxytet|mafua|kuhara | AF50: Water-soluble antibiotic for poultry. | AG50: =COUNTIF(Variants!$B:$B,A50) -> 1 | AH50: TRUE
A51: P050 | B51: Tylosin Soluble Powder | C51: BR-AFM | D51: Afya Mifugo Pharma (demo) | E51: BR-AFM | F51: C30 | G51: C3010 | H51: Medicines > Antibiotics & antibacterials | I51: AN-POU | J51: LS-ALL | K51: general | L51: powder | M51: drinking_water | N51: respiratory | O51: crd | P51: Tylosin tartrate | R51: As directed by a veterinarian | S51: 3 | T51: 0 | V51: prescription_vet_medicine | W51: TRUE | X51: FALSE | Y51: Cool, dry place below 30 C, off the floor | Z51: DEMO-PRE-0050 | AD51: India | AE51: mafua|crd|tylosin | AF51: Antibiotic for chronic respiratory disease in poultry. | AG51: =COUNTIF(Variants!$B:$B,A51) -> 1 | AH51: TRUE
A52: P051 | B52: Penicillin-Streptomycin Injection | C52: BR-AFM | D52: Afya Mifugo Pharma (demo) | E52: BR-AFM | F52: C30 | G52: C3010 | H52: Medicines > Antibiotics & antibacterials | I52: AN-CAT|AN-GTS|AN-PIG | J52: LS-ALL | K52: general | L52: suspension | M52: injection_im | N52: bacterial_infection | P52: Procaine penicillin + dihydrostreptomycin | R52: As directed by a veterinarian | S52: 21 | U52: 3 | V52: prescription_vet_medicine | W52: TRUE | X52: TRUE | Y52: 2-8 C, do not freeze, protect from light | Z52: DEMO-PRE-0051 | AD52: India | AE52: dawa|sindano|pen strep | AF52: Combination antibiotic injection. Stored refrigerated. | AG52: =COUNTIF(Variants!$B:$B,A52) -> 1 | AH52: TRUE
A53: P052 | B53: Albendazole 10% Oral Suspension | C53: BR-AFM | D53: Afya Mifugo Pharma (demo) | E53: BR-AFM | F53: C30 | G53: C3020 | H53: Medicines > Dewormers | I53: AN-CAT|AN-GTS | J53: LS-ALL | K53: general | L53: suspension | M53: oral_drench | N53: worms | P53: Albendazole 100 mg/ml | R53: By body weight, as per label | S53: 14 | U53: 4 | V53: otc_vet_medicine | W53: FALSE | X53: FALSE | Y53: Cool, dry place below 30 C, off the floor | Z53: DEMO-OTC-0052 | AD53: India | AE53: dawa ya minyoo|minyoo|albendazole|dewormer | AF53: Broad-spectrum oral dewormer for cattle, goats and sheep. Not to be used in early pregnancy (per label). | AG53: =COUNTIF(Variants!$B:$B,A53) -> 2 | AH53: TRUE
A54: P053 | B54: Piperazine Soluble Powder | C54: BR-KLV | D54: KiliVet (demo) | E54: BR-KLV | F54: C30 | G54: C3020 | H54: Medicines > Dewormers | I54: AN-POU|AN-PIG | J54: LS-ALL | K54: general | L54: powder | M54: drinking_water | N54: worms | P54: Piperazine citrate | R54: As per label | S54: 7 | T54: 7 | V54: otc_vet_medicine | W54: FALSE | X54: FALSE | Y54: Cool, dry place below 30 C, off the floor | Z54: DEMO-OTC-0053 | AD54: Kenya | AE54: dawa ya minyoo|minyoo ya kuku | AF54: Roundworm treatment for poultry and pigs. | AG54: =COUNTIF(Variants!$B:$B,A54) -> 1 | AH54: TRUE
A55: P054 | B55: Levamisole Oral Drench | C55: BR-AFM | D55: Afya Mifugo Pharma (demo) | E55: BR-AFM | F55: C30 | G55: C3020 | H55: Medicines > Dewormers | I55: AN-GOT|AN-SHP|AN-CAT | J55: LS-ALL | K55: general | L55: liquid | M55: oral_drench | N55: worms | P55: Levamisole HCl | R55: By body weight, as per label | S55: 7 | U55: 3 | V55: otc_vet_medicine | W55: FALSE | X55: FALSE | Y55: Cool, dry place below 30 C, off the floor | Z55: DEMO-OTC-0054 | AD55: India | AE55: dawa ya minyoo|minyoo | AF55: Oral dewormer for ruminants. | AG55: =COUNTIF(Variants!$B:$B,A55) -> 1 | AH55: TRUE
A56: P055 | B56: Ivermectin 1% Injection | C56: BR-AFM | D56: Afya Mifugo Pharma (demo) | E56: BR-AFM | F56: C30 | G56: C3020 | H56: Medicines > Dewormers | I56: AN-CAT|AN-GTS|AN-PIG | J56: LS-ALL | K56: general | L56: injectable | M56: injection_sc | N56: worms|mites_lice|ticks | P56: Ivermectin 10 mg/ml | R56: By body weight, as directed by a veterinarian | S56: 35 | V56: prescription_vet_medicine | W56: TRUE | X56: FALSE | Y56: Cool, dry place below 30 C, off the floor | Z56: DEMO-PRE-0055 | AD56: India | AE56: minyoo|kupe|ivermectin|ivomec | AF56: Endectocide injection for internal and external parasites. Not for lactating dairy animals (per typical labels - verify). | AG56: =COUNTIF(Variants!$B:$B,A56) -> 2 | AH56: TRUE
A57: P056 | B57: Amprolium 20% Soluble Powder | C57: BR-AFM | D57: Afya Mifugo Pharma (demo) | E57: BR-AFM | F57: C30 | G57: C3030 | H57: Medicines > Anticoccidials | I57: AN-POU | J57: LS-ALL | K57: general | L57: powder | M57: drinking_water | N57: coccidiosis | O57: coccidiosis | P57: Amprolium HCl 200 mg/g | R57: As per label | S57: 3 | T57: 0 | V57: otc_vet_medicine | W57: FALSE | X57: FALSE | Y57: Cool, dry place below 30 C, off the floor | Z57: DEMO-OTC-0056 | AD57: India | AE57: kuhara damu|koksidiosisi|amprolium | AF57: Treatment and control of coccidiosis in poultry. | AG57: =COUNTIF(Variants!$B:$B,A57) -> 2 | AH57: TRUE
A58: P057 | B58: Toltrazuril 2.5% Oral Solution | C58: BR-AFM | D58: Afya Mifugo Pharma (demo) | E58: BR-AFM | F58: C30 | G58: C3030 | H58: Medicines > Anticoccidials | I58: AN-POU | J58: LS-ALL | K58: general | L58: liquid | M58: drinking_water | N58: coccidiosis | O58: coccidiosis | P58: Toltrazuril 25 mg/ml | R58: As directed by a veterinarian | S58: 18 | V58: prescription_vet_medicine | W58: TRUE | X58: FALSE | Y58: Cool, dry place below 30 C, off the floor | Z58: DEMO-PRE-0057 | AD58: India | AE58: kuhara damu|toltrazuril | AF58: Anticoccidial solution for poultry. Not for layers producing eggs for consumption (per typical labels - verify). | AG58: =COUNTIF(Variants!$B:$B,A58) -> 2 | AH58: TRUE
A59: P058 | B59: Amitraz 12.5% Dip Concentrate | C59: BR-SFH | D59: SafiFarm Hygiene (demo) | E59: BR-SFH | F59: C30 | G59: C3040 | H59: Medicines > External parasite control | I59: AN-CAT|AN-GTS | J59: LS-ALL | K59: general | L59: liquid | M59: spray_dip | N59: ticks|mites_lice | O59: ecf | P59: Amitraz 12.5% EC | R59: Dilute as per label | S59: 1 | U59: 0 | V59: pesticide_acaricide | W59: FALSE | X59: FALSE | Y59: Cool, dry place below 30 C, off the floor | Z59: DEMO-PES-0058 | AD59: South Africa | AE59: kupe|dawa ya kuogesha|dipping|ndigana kali | AF59: Acaricide for spraying or dipping cattle, goats and sheep. | AG59: =COUNTIF(Variants!$B:$B,A59) -> 2 | AH59: TRUE
A60: P059 | B60: Cypermethrin Pour-On | C60: BR-SFH | D60: SafiFarm Hygiene (demo) | E60: BR-SFH | F60: C30 | G60: C3040 | H60: Medicines > External parasite control | I60: AN-CAT | J60: LS-ALL | K60: dairy|beef | L60: liquid | M60: pour_on | N60: ticks|mites_lice | P60: Cypermethrin | R60: By body weight, as per label | S60: 3 | U60: 0 | V60: pesticide_acaricide | W60: FALSE | X60: FALSE | Y60: Cool, dry place below 30 C, off the floor | Z60: DEMO-PES-0059 | AD60: South Africa | AE60: kupe|pour on|nzi | AF60: Pour-on for tick and fly control on cattle. | AG60: =COUNTIF(Variants!$B:$B,A60) -> 1 | AH60: TRUE
A61: P060 | B61: Poultry Mite & Lice Powder | C61: BR-SFH | D61: SafiFarm Hygiene (demo) | E61: BR-SFH | F61: C30 | G61: C3040 | H61: Medicines > External parasite control | I61: AN-POU | J61: LS-ALL | K61: general | L61: powder | M61: topical | N61: mites_lice | P61: Permethrin dusting powder | R61: As per label | V61: pesticide_acaricide | W61: FALSE | X61: FALSE | Y61: Cool, dry place below 30 C, off the floor | Z61: DEMO-PES-0060 | AD61: South Africa | AE61: utitiri|chawa|viroboto | AF61: Dusting powder against mites and lice on birds and in houses. | AG61: =COUNTIF(Variants!$B:$B,A61) -> 1 | AH61: TRUE
A62: P061 | B62: Antiseptic Wound Spray | C62: BR-AFM | D62: Afya Mifugo Pharma (demo) | E62: BR-AFM | F62: C30 | G62: C3050 | H62: Medicines > Wound care & topical | I62: AN-CAT|AN-GTS|AN-PIG|AN-POU | J62: LS-ALL | K62: general | L62: spray | M62: topical | N62: wounds | P62: Oxytetracycline + gentian violet | R62: Spray on cleaned wound | V62: otc_vet_medicine | W62: FALSE | X62: FALSE | Y62: Cool, dry place below 30 C, off the floor | Z62: DEMO-OTC-0061 | AD62: India | AE62: vidonda|spray|dawa ya vidonda | AF62: Antibiotic wound spray. | AG62: =COUNTIF(Variants!$B:$B,A62) -> 1 | AH62: TRUE
A63: P062 | B63: Calcium Borogluconate Injection | C63: BR-AFM | D63: Afya Mifugo Pharma (demo) | E63: BR-AFM | F63: C30 | G63: C3060 | H63: Medicines > Other medicines | I63: AN-DCT | J63: LS-CAT-LAC | K63: dairy | L63: injectable | M63: injection_sc | N63: milk_fever | P63: Calcium borogluconate 40% | R63: As directed by a veterinarian | V63: prescription_vet_medicine | W63: TRUE | X63: FALSE | Y63: Cool, dry place below 30 C, off the floor | Z63: DEMO-PRE-0062 | AD63: India | AE63: homa ya maziwa|milk fever|calcium | AF63: For treatment of milk fever (hypocalcaemia) in dairy cows. | AG63: =COUNTIF(Variants!$B:$B,A63) -> 1 | AH63: TRUE
A64: P063 | B64: Newcastle Disease Vaccine (LaSota) | C64: BR-KNG | D64: Kinga Vaccines (demo) | E64: BR-KNG | F64: C40 | G64: C40 | H64: Vaccines & biologicals | I64: AN-CHK | J64: LS-ALL | K64: general | L64: freeze_dried_vial | M64: drinking_water|eye_nasal_drop | N64: disease_prevention|immunity | O64: newcastle | P64: Live NDV LaSota strain | V64: vaccine_biological | W64: TRUE | X64: TRUE | Y64: 2-8 C, do not freeze, protect from light | Z64: DEMO-VAC-0063 | AD64: Tanzania | AE64: chanjo|kideri|mdondo|newcastle|lasota | AF64: Live Newcastle disease vaccine for chickens. | AG64: =COUNTIF(Variants!$B:$B,A64) -> 3 | AH64: TRUE
A65: P064 | B65: Newcastle Thermostable I-2 Vaccine | C65: BR-KNG | D65: Kinga Vaccines (demo) | E65: BR-KNG | F65: C40 | G65: C40 | H65: Vaccines & biologicals | I65: AN-CHK | J65: LS-ALL | K65: general | L65: freeze_dried_vial | M65: eye_nasal_drop|drinking_water | N65: disease_prevention|immunity | O65: newcastle | P65: Live NDV I-2 thermostable strain | V65: vaccine_biological | W65: TRUE | X65: TRUE | Y65: 2-8 C, do not freeze, protect from light | Z65: DEMO-VAC-0064 | AD65: Tanzania | AE65: chanjo|kideri|kuku wa kienyeji|i-2 | AF65: Thermostable Newcastle vaccine suited to village chickens. | AG65: =COUNTIF(Variants!$B:$B,A65) -> 2 | AH65: TRUE
A66: P065 | B66: Gumboro (IBD) Vaccine | C66: BR-KNG | D66: Kinga Vaccines (demo) | E66: BR-KNG | F66: C40 | G66: C40 | H66: Vaccines & biologicals | I66: AN-CHK | J66: LS-POU-STR | K66: general | L66: freeze_dried_vial | M66: drinking_water | N66: disease_prevention|immunity | O66: gumboro | P66: Live intermediate IBD strain | V66: vaccine_biological | W66: TRUE | X66: TRUE | Y66: 2-8 C, do not freeze, protect from light | Z66: DEMO-VAC-0065 | AD66: Tanzania | AE66: chanjo|gumboro|ibd | AF66: Live Gumboro vaccine for chicks. | AG66: =COUNTIF(Variants!$B:$B,A66) -> 2 | AH66: TRUE
A67: P066 | B67: Fowl Pox Vaccine | C67: BR-KNG | D67: Kinga Vaccines (demo) | E67: BR-KNG | F67: C40 | G67: C40 | H67: Vaccines & biologicals | I67: AN-CHK | J67: LS-POU-GRW | K67: general | L67: freeze_dried_vial | M67: wing_web | N67: disease_prevention|immunity | O67: fowl_pox | P67: Live fowl pox virus | V67: vaccine_biological | W67: TRUE | X67: TRUE | Y67: 2-8 C, do not freeze, protect from light | Z67: DEMO-VAC-0066 | AD67: Tanzania | AE67: chanjo|ndui ya kuku|fowl pox | AF67: Wing-web vaccine against fowl pox. | AG67: =COUNTIF(Variants!$B:$B,A67) -> 2 | AH67: TRUE
A68: P067 | B68: Marek's Disease Vaccine | C68: BR-KNG | D68: Kinga Vaccines (demo) | E68: BR-KNG | F68: C40 | G68: C40 | H68: Vaccines & biologicals | I68: AN-CHK | J68: LS-POU-STR | K68: general | L68: freeze_dried_vial | M68: injection_sc | N68: disease_prevention|immunity | O68: mareks | P68: HVT strain | V68: vaccine_biological | W68: TRUE | X68: TRUE | Y68: 2-8 C, do not freeze, protect from light | Z68: DEMO-VAC-0067 | AD68: Tanzania | AE68: chanjo|mareks | AF68: Day-old vaccine against Marek's disease (hatchery use). | AG68: =COUNTIF(Variants!$B:$B,A68) -> 1 | AH68: TRUE
A69: P068 | B69: Fowl Typhoid Vaccine | C69: BR-KNG | D69: Kinga Vaccines (demo) | E69: BR-KNG | F69: C40 | G69: C40 | H69: Vaccines & biologicals | I69: AN-CHK | J69: LS-POU-GRW | K69: general | L69: freeze_dried_vial | M69: injection_sc | N69: disease_prevention|immunity | O69: fowl_typhoid | P69: Salmonella Gallinarum 9R strain | V69: vaccine_biological | W69: TRUE | X69: TRUE | Y69: 2-8 C, do not freeze, protect from light | Z69: DEMO-VAC-0068 | AD69: Tanzania | AE69: chanjo|homa ya matumbo|fowl typhoid | AF69: Vaccine against fowl typhoid for growers and layers. | AG69: =COUNTIF(Variants!$B:$B,A69) -> 1 | AH69: TRUE
A70: P069 | B70: Lumpy Skin Disease Vaccine | C70: BR-KNG | D70: Kinga Vaccines (demo) | E70: BR-KNG | F70: C40 | G70: C40 | H70: Vaccines & biologicals | I70: AN-CAT | J70: LS-ALL | K70: general | L70: freeze_dried_vial | M70: injection_sc | N70: disease_prevention|immunity | O70: lumpy_skin | P70: Live attenuated LSD virus | V70: vaccine_biological | W70: TRUE | X70: TRUE | Y70: 2-8 C, do not freeze, protect from light | Z70: DEMO-VAC-0069 | AD70: Tanzania | AE70: chanjo|lsd|ugonjwa wa ngozi | AF70: Vaccine against lumpy skin disease in cattle. | AG70: =COUNTIF(Variants!$B:$B,A70) -> 1 | AH70: TRUE
A71: P070 | B71: Anthrax Spore Vaccine | C71: BR-KNG | D71: Kinga Vaccines (demo) | E71: BR-KNG | F71: C40 | G71: C40 | H71: Vaccines & biologicals | I71: AN-CAT|AN-GTS | J71: LS-ALL | K71: general | L71: freeze_dried_vial | M71: injection_sc | N71: disease_prevention|immunity | O71: anthrax | P71: Live Sterne spore | V71: vaccine_biological | W71: TRUE | X71: TRUE | Y71: 2-8 C, do not freeze, protect from light | Z71: DEMO-VAC-0070 | AD71: Tanzania | AE71: chanjo|kimeta|anthrax | AF71: Anthrax vaccine for cattle, goats and sheep. | AG71: =COUNTIF(Variants!$B:$B,A71) -> 1 | AH71: TRUE
A72: P071 | B72: PPR Vaccine | C72: BR-KNG | D72: Kinga Vaccines (demo) | E72: BR-KNG | F72: C40 | G72: C40 | H72: Vaccines & biologicals | I72: AN-GOT|AN-SHP | J72: LS-ALL | K72: general | L72: freeze_dried_vial | M72: injection_sc | N72: disease_prevention|immunity | O72: ppr | P72: Live attenuated PPR virus | V72: vaccine_biological | W72: TRUE | X72: TRUE | Y72: 2-8 C, do not freeze, protect from light | Z72: DEMO-VAC-0071 | AD72: Tanzania | AE72: chanjo|sotoka|ppr|mbuzi | AF72: Vaccine against PPR in goats and sheep. | AG72: =COUNTIF(Variants!$B:$B,A72) -> 1 | AH72: TRUE
A73: P072 | B73: Farm Disinfectant (Glutaraldehyde + Quat) | C73: BR-SFH | D73: SafiFarm Hygiene (demo) | E73: BR-SFH | F73: C50 | G73: C5010 | H73: Biosecurity & hygiene > Disinfectants & sanitisers | I73: AN-POU|AN-PIG|AN-CAT | J73: LS-ALL | K73: general | L73: liquid | M73: surface_application|spray_dip | N73: biosecurity | P73: Glutaraldehyde + quaternary ammonium | R73: Dilute as per label | V73: disinfectant | W73: FALSE | X73: FALSE | Y73: Cool, dry place below 30 C, off the floor | Z73: DEMO-DIS-0072 | AD73: South Africa | AE73: dawa ya kuua vijidudu|usafi wa banda|disinfectant | AF73: Broad-spectrum disinfectant for houses, equipment and foot dips. | AG73: =COUNTIF(Variants!$B:$B,A73) -> 2 | AH73: TRUE
A74: P073 | B74: Povidone Iodine Solution | C74: BR-SFH | D74: SafiFarm Hygiene (demo) | E74: BR-SFH | F74: C50 | G74: C5010 | H74: Biosecurity & hygiene > Disinfectants & sanitisers | I74: AN-POU|AN-PIG|AN-CAT|AN-GTS | J74: LS-ALL | K74: general | L74: liquid | M74: surface_application|topical | N74: biosecurity|wounds | P74: Povidone iodine 10% | V74: disinfectant | W74: FALSE | X74: FALSE | Y74: Cool, dry place below 30 C, off the floor | Z74: DEMO-DIS-0073 | AD74: South Africa | AE74: iodine|dawa ya kuua vijidudu | AF74: Iodine disinfectant and antiseptic. | AG74: =COUNTIF(Variants!$B:$B,A74) -> 1 | AH74: TRUE
A75: P074 | B75: Water Sanitiser Tablets | C75: BR-SFH | D75: SafiFarm Hygiene (demo) | E75: BR-SFH | F75: C50 | G75: C5010 | H75: Biosecurity & hygiene > Disinfectants & sanitisers | I75: AN-POU|AN-PIG | J75: LS-ALL | K75: general | L75: tablet | M75: drinking_water | N75: biosecurity | P75: Sodium dichloroisocyanurate | R75: As per label | V75: disinfectant | W75: FALSE | X75: FALSE | Y75: Cool, dry place below 30 C, off the floor | Z75: DEMO-DIS-0074 | AD75: South Africa | AE75: maji safi|usafi wa maji | AF75: Chlorine tablets for drinking water sanitation. | AG75: =COUNTIF(Variants!$B:$B,A75) -> 1 | AH75: TRUE
A76: P075 | B76: Rat Bait Blocks | C76: BR-SFH | D76: SafiFarm Hygiene (demo) | E76: BR-SFH | F76: C50 | G76: C5020 | H76: Biosecurity & hygiene > Pest & rodent control | I76: AN-POU|AN-PIG | J76: LS-ALL | K76: general | L76: block | M76: not_applicable | N76: rodents | P76: Brodifacoum 0.005% | V76: pesticide_acaricide | W76: FALSE | X76: FALSE | Y76: Locked store away from feed, children and animals | Z76: DEMO-PES-0075 | AD76: South Africa | AE76: panya|sumu ya panya | AF76: Rodenticide bait blocks for use in bait stations only. | AG76: =COUNTIF(Variants!$B:$B,A76) -> 1 | AH76: TRUE
A77: P076 | B77: Chick Drinker | C77: BR-BND | D77: Banda Equipment (demo) | E77: BR-BND | F77: C60 | G77: C6010 | H77: Equipment & supplies > Feeders & drinkers | I77: AN-POU | J77: LS-ALL | K77: general | L77: hardware | M77: not_applicable | N77: brooding | V77: equipment | W77: FALSE | X77: FALSE | AA77: 4 L | AD77: China | AE77: drinka|chombo cha maji|vifaranga | AF77: Plastic drinker for chicks. | AG77: =COUNTIF(Variants!$B:$B,A77) -> 1 | AH77: TRUE
A78: P077 | B78: Poultry Drinker | C78: BR-BND | D78: Banda Equipment (demo) | E78: BR-BND | F78: C60 | G78: C6010 | H78: Equipment & supplies > Feeders & drinkers | I78: AN-POU | J78: LS-ALL | K78: general | L78: hardware | M78: not_applicable | N78: equipment_general | V78: equipment | W78: FALSE | X78: FALSE | AA78: 10 L | AD78: China | AE78: drinka|chombo cha maji | AF78: Plastic drinker for growers and adult birds. | AG78: =COUNTIF(Variants!$B:$B,A78) -> 1 | AH78: TRUE
A79: P078 | B79: Hanging Poultry Feeder | C79: BR-BND | D79: Banda Equipment (demo) | E79: BR-BND | F79: C60 | G79: C6010 | H79: Equipment & supplies > Feeders & drinkers | I79: AN-POU | J79: LS-ALL | K79: general | L79: hardware | M79: not_applicable | N79: equipment_general | V79: equipment | W79: FALSE | X79: FALSE | AA79: 10 kg | AD79: China | AE79: fida|chombo cha chakula|feeder | AF79: Round hanging tube feeder. | AG79: =COUNTIF(Variants!$B:$B,A79) -> 1 | AH79: TRUE
A80: P079 | B80: Chick Feeder Tray | C80: BR-BND | D80: Banda Equipment (demo) | E80: BR-BND | F80: C60 | G80: C6010 | H80: Equipment & supplies > Feeders & drinkers | I80: AN-POU | J80: LS-ALL | K80: general | L80: hardware | M80: not_applicable | N80: brooding | V80: equipment | W80: FALSE | X80: FALSE | AA80: Approx. 50 chicks | AD80: China | AE80: fida|vifaranga|feeder tray | AF80: Flat feeder tray for the first week. | AG80: =COUNTIF(Variants!$B:$B,A80) -> 1 | AH80: TRUE
A81: P080 | B81: Nipple Drinker Line Kit | C81: BR-BND | D81: Banda Equipment (demo) | E81: BR-BND | F81: C60 | G81: C6010 | H81: Equipment & supplies > Feeders & drinkers | I81: AN-POU | J81: LS-ALL | K81: general | L81: hardware | M81: not_applicable | N81: equipment_general | V81: equipment | W81: FALSE | X81: FALSE | AA81: 10 nipples, 3 m pipe | AD81: China | AE81: nipple|drinka | AF81: Nipple drinker kit with pipe, nipples and header tank adaptor. | AG81: =COUNTIF(Variants!$B:$B,A81) -> 1 | AH81: TRUE
A82: P081 | B82: Pig Feeding Trough | C82: BR-BND | D82: Banda Equipment (demo) | E82: BR-BND | F82: C60 | G82: C6010 | H82: Equipment & supplies > Feeders & drinkers | I82: AN-PIG | J82: LS-ALL | K82: general | L82: hardware | M82: not_applicable | N82: equipment_general | V82: equipment | W82: FALSE | X82: FALSE | AA82: 1 m | AD82: China | AE82: nguruwe|hori|trough | AF82: Heavy plastic feeding trough for pigs. | AG82: =COUNTIF(Variants!$B:$B,A82) -> 1 | AH82: TRUE
A83: P082 | B83: Infrared Brooder Bulb 250W | C83: BR-BND | D83: Banda Equipment (demo) | E83: BR-BND | F83: C60 | G83: C6020 | H83: Equipment & supplies > Brooding & heating | I83: AN-POU|AN-PIG | J83: LS-ALL | K83: general | L83: hardware | M83: not_applicable | N83: brooding | V83: equipment | W83: FALSE | X83: FALSE | AA83: 250 W | AB83: electric | AD83: China | AE83: taa ya joto|bruda|brooder | AF83: Infrared heat bulb for brooding chicks or piglets. | AG83: =COUNTIF(Variants!$B:$B,A83) -> 1 | AH83: TRUE
A84: P083 | B84: Charcoal Brooder | C84: BR-BND | D84: Banda Equipment (demo) | E84: BR-BND | F84: C60 | G84: C6020 | H84: Equipment & supplies > Brooding & heating | I84: AN-POU | J84: LS-ALL | K84: general | L84: hardware | M84: not_applicable | N84: brooding | V84: equipment | W84: FALSE | X84: FALSE | AA84: Approx. 300 chicks | AB84: charcoal | AD84: Tanzania | AE84: bruda|jiko la vifaranga | AF84: Metal charcoal brooder for off-grid farms. | AG84: =COUNTIF(Variants!$B:$B,A84) -> 1 | AH84: TRUE
A85: P084 | B85: Layer Battery Cage (96 birds) | C85: BR-BND | D85: Banda Equipment (demo) | E85: BR-BND | F85: C60 | G85: C6030 | H85: Equipment & supplies > Housing, cages & nests | I85: AN-CHK | J85: LS-ALL | K85: general | L85: hardware | M85: not_applicable | N85: egg_production | V85: equipment | W85: FALSE | X85: FALSE | AA85: 96 birds, 3 tiers | AD85: China | AE85: kizimba|cage|banda | AF85: Galvanised 3-tier A-frame battery cage. | AG85: =COUNTIF(Variants!$B:$B,A85) -> 1 | AH85: TRUE
A86: P085 | B86: Laying Nest Box (10 holes) | C86: BR-BND | D86: Banda Equipment (demo) | E86: BR-BND | F86: C60 | G86: C6030 | H86: Equipment & supplies > Housing, cages & nests | I86: AN-CHK | J86: LS-ALL | K86: general | L86: hardware | M86: not_applicable | N86: egg_production | V86: equipment | W86: FALSE | X86: FALSE | AA86: 10 holes | AD86: China | AE86: kiota|nest | AF86: Metal community nest box. | AG86: =COUNTIF(Variants!$B:$B,A86) -> 1 | AH86: TRUE
A87: P086 | B87: Egg Incubator 64 Eggs | C87: BR-BND | D87: Banda Equipment (demo) | E87: BR-BND | F87: C60 | G87: C6040 | H87: Equipment & supplies > Incubators & hatching | I87: AN-POU | J87: LS-ALL | K87: general | L87: hardware | M87: not_applicable | N87: hatching | V87: equipment | W87: FALSE | X87: FALSE | AA87: 64 eggs | AB87: solar_electric | AD87: China | AE87: mashine ya kutotolesha|incubator | AF87: Small automatic incubator with 12 V solar input. | AG87: =COUNTIF(Variants!$B:$B,A87) -> 1 | AH87: TRUE
A88: P087 | B88: Egg Incubator 528 Eggs | C88: BR-BND | D88: Banda Equipment (demo) | E88: BR-BND | F88: C60 | G88: C6040 | H88: Equipment & supplies > Incubators & hatching | I88: AN-POU | J88: LS-ALL | K88: general | L88: hardware | M88: not_applicable | N88: hatching | V88: equipment | W88: FALSE | X88: FALSE | AA88: 528 eggs | AB88: solar_electric | AD88: China | AE88: mashine ya kutotolesha|incubator | AF88: Automatic incubator with turning and humidity control. | AG88: =COUNTIF(Variants!$B:$B,A88) -> 1 | AH88: TRUE
A89: P088 | B89: Egg Trays (30-egg) | C89: BR-BND | D89: Banda Equipment (demo) | E89: BR-BND | F89: C60 | G89: C6050 | H89: Equipment & supplies > Egg handling & packaging | I89: AN-CHK | J89: LS-ALL | K89: general | L89: hardware | M89: not_applicable | N89: egg_production | V89: equipment | W89: FALSE | X89: FALSE | AA89: 30 eggs per tray | AD89: Tanzania | AE89: trei za mayai|egg tray | AF89: Moulded-pulp egg trays, pack of 100. | AG89: =COUNTIF(Variants!$B:$B,A89) -> 1 | AH89: TRUE
A90: P089 | B90: Automatic Vaccination Syringe 5 ml | C90: BR-BND | D90: Banda Equipment (demo) | E90: BR-BND | F90: C60 | G90: C6060 | H90: Equipment & supplies > Veterinary tools | I90: AN-POU|AN-PIG|AN-CAT|AN-GTS | J90: LS-ALL | K90: general | L90: hardware | M90: not_applicable | N90: disease_prevention | V90: equipment | W90: FALSE | X90: FALSE | AA90: 5 ml | AD90: China | AE90: sindano|syringe | AF90: Continuous self-refilling syringe for mass vaccination. | AG90: =COUNTIF(Variants!$B:$B,A90) -> 1 | AH90: TRUE
A91: P090 | B91: Disposable Syringes 10 ml | C91: BR-BND | D91: Banda Equipment (demo) | E91: BR-BND | F91: C60 | G91: C6060 | H91: Equipment & supplies > Veterinary tools | I91: AN-POU|AN-PIG|AN-CAT|AN-GTS | J91: LS-ALL | K91: general | L91: hardware | M91: not_applicable | N91: equipment_general | V91: equipment | W91: FALSE | X91: FALSE | AA91: 10 ml | AD91: China | AE91: sindano|syringe | AF91: Box of 100 sterile disposable syringes with needles. | AG91: =COUNTIF(Variants!$B:$B,A91) -> 1 | AH91: TRUE
A92: P091 | B92: Drenching Gun 30 ml | C92: BR-BND | D92: Banda Equipment (demo) | E92: BR-BND | F92: C60 | G92: C6060 | H92: Equipment & supplies > Veterinary tools | I92: AN-CAT|AN-GTS | J92: LS-ALL | K92: general | L92: hardware | M92: not_applicable | N92: worms | V92: equipment | W92: FALSE | X92: FALSE | AA92: 30 ml | AD92: China | AE92: drench|dawa ya minyoo | AF92: Adjustable dose drenching gun. | AG92: =COUNTIF(Variants!$B:$B,A92) -> 1 | AH92: TRUE
A93: P092 | B93: Digital Veterinary Thermometer | C93: BR-BND | D93: Banda Equipment (demo) | E93: BR-BND | F93: C60 | G93: C6060 | H93: Equipment & supplies > Veterinary tools | I93: AN-CAT|AN-GTS|AN-PIG | J93: LS-ALL | K93: general | L93: hardware | M93: not_applicable | N93: equipment_general | V93: equipment | W93: FALSE | X93: FALSE | AA93: Fast read | AD93: China | AE93: kipimajoto|thermometer | AF93: Digital rectal thermometer for livestock. | AG93: =COUNTIF(Variants!$B:$B,A93) -> 1 | AH93: TRUE
A94: P093 | B94: Aluminium Milk Can 20 L | C94: BR-BND | D94: Banda Equipment (demo) | E94: BR-BND | F94: C60 | G94: C6070 | H94: Equipment & supplies > Milking & dairy equipment | I94: AN-DCT | J94: LS-ALL | K94: general | L94: hardware | M94: not_applicable | N94: milk_yield | V94: equipment | W94: FALSE | X94: FALSE | AA94: 20 L | AD94: China | AE94: chombo cha maziwa|milk can | AF94: Food-grade aluminium milk can. | AG94: =COUNTIF(Variants!$B:$B,A94) -> 1 | AH94: TRUE
A95: P094 | B95: Hanging Scale 50 kg | C95: BR-BND | D95: Banda Equipment (demo) | E95: BR-BND | F95: C60 | G95: C6080 | H95: Equipment & supplies > Weighing & measuring | I95: AN-POU|AN-PIG|AN-GTS | J95: LS-ALL | K95: general | L95: hardware | M95: not_applicable | N95: equipment_general | V95: equipment | W95: FALSE | X95: FALSE | AA95: 50 kg | AD95: China | AE95: mizani|scale | AF95: Spring hanging scale for weighing birds, piglets and feed. | AG95: =COUNTIF(Variants!$B:$B,A95) -> 1 | AH95: TRUE
A96: P095 | B96: Kibo Broiler Day-old Chicks | C96: BR-KIBO | D96: Kibo | E96: BR-KIBO | F96: C70 | G96: C7010 | H96: Live animals & genetics > Day-old chicks & hatching eggs | I96: AN-CHK | J96: LS-POU-STR | K96: broiler | L96: live | M96: not_applicable | N96: breeding | V96: live_animal | W96: FALSE | X96: FALSE | Y96: Collect on hatch/delivery date | AC96: Commercial broiler | AD96: Tanzania | AE96: vifaranga|vifaranga vya nyama|broila|kuku wa nyama|kibo | AF96: Day-old broiler chicks from Kibo, booked against a hatch date (see Hatch_Schedule). Minimum order 50 chicks. | AG96: =COUNTIF(Variants!$B:$B,A96) -> 1 | AH96: TRUE
A97: P096 | B97: Harsho Broiler Day-old Chicks | C97: BR-HARS | D97: Harsho | E97: BR-HARS | F97: C70 | G97: C7010 | H97: Live animals & genetics > Day-old chicks & hatching eggs | I97: AN-CHK | J97: LS-POU-STR | K97: broiler | L97: live | M97: not_applicable | N97: breeding | V97: live_animal | W97: FALSE | X97: FALSE | Y97: Collect on hatch/delivery date | AC97: Commercial broiler | AD97: Tanzania | AE97: vifaranga|vifaranga vya nyama|broila|kuku wa nyama|harsho | AF97: Day-old broiler chicks from Harsho, booked against a hatch date (see Hatch_Schedule). Minimum order 50 chicks. | AG97: =COUNTIF(Variants!$B:$B,A97) -> 1 | AH97: TRUE
A98: P097 | B98: Backbone Broiler Day-old Chicks | C98: BR-BACK | D98: Backbone | E98: BR-BACK | F98: C70 | G98: C7010 | H98: Live animals & genetics > Day-old chicks & hatching eggs | I98: AN-CHK | J98: LS-POU-STR | K98: broiler | L98: live | M98: not_applicable | N98: breeding | V98: live_animal | W98: FALSE | X98: FALSE | Y98: Collect on hatch/delivery date | AC98: Commercial broiler | AD98: Tanzania | AE98: vifaranga|vifaranga vya nyama|broila|kuku wa nyama|backbone | AF98: Day-old broiler chicks from Backbone, booked against a hatch date (see Hatch_Schedule). Minimum order 50 chicks. | AG98: =COUNTIF(Variants!$B:$B,A98) -> 1 | AH98: TRUE
A99: P098 | B99: Irvines Broiler Day-old Chicks | C99: BR-IRVN | D99: Irvines | E99: BR-IRVN | F99: C70 | G99: C7010 | H99: Live animals & genetics > Day-old chicks & hatching eggs | I99: AN-CHK | J99: LS-POU-STR | K99: broiler | L99: live | M99: not_applicable | N99: breeding | V99: live_animal | W99: FALSE | X99: FALSE | Y99: Collect on hatch/delivery date | AC99: Commercial broiler | AD99: Tanzania | AE99: vifaranga|vifaranga vya nyama|broila|kuku wa nyama|irvines | AF99: Day-old broiler chicks from Irvines, booked against a hatch date (see Hatch_Schedule). Minimum order 50 chicks. | AG99: =COUNTIF(Variants!$B:$B,A99) -> 1 | AH99: TRUE
A100: P099 | B100: Organia Broiler Day-old Chicks | C100: BR-ORGN | D100: Organia | E100: BR-ORGN | F100: C70 | G100: C7010 | H100: Live animals & genetics > Day-old chicks & hatching eggs | I100: AN-CHK | J100: LS-POU-STR | K100: broiler | L100: live | M100: not_applicable | N100: breeding | V100: live_animal | W100: FALSE | X100: FALSE | Y100: Collect on hatch/delivery date | AC100: Commercial broiler | AD100: Tanzania | AE100: vifaranga|vifaranga vya nyama|broila|kuku wa nyama|organia | AF100: Day-old broiler chicks from Organia, booked against a hatch date (see Hatch_Schedule). Minimum order 50 chicks. | AG100: =COUNTIF(Variants!$B:$B,A100) -> 1 | AH100: TRUE
A101: P100 | B101: Happy Chicks Broiler Day-old Chicks | C101: BR-HAPP | D101: Happy Chicks | E101: BR-HAPP | F101: C70 | G101: C7010 | H101: Live animals & genetics > Day-old chicks & hatching eggs | I101: AN-CHK | J101: LS-POU-STR | K101: broiler | L101: live | M101: not_applicable | N101: breeding | V101: live_animal | W101: FALSE | X101: FALSE | Y101: Collect on hatch/delivery date | AC101: Commercial broiler | AD101: Tanzania | AE101: vifaranga|vifaranga vya nyama|broila|kuku wa nyama|happy chicks | AF101: Day-old broiler chicks from Happy Chicks, booked against a hatch date (see Hatch_Schedule). Minimum order 50 chicks. | AG101: =COUNTIF(Variants!$B:$B,A101) -> 1 | AH101: TRUE
A102: P101 | B102: Central Chicks (Animal Care) Broiler Day-old Chicks | C102: BR-CENT | D102: Central Chicks (Animal Care) | E102: BR-CENT | F102: C70 | G102: C7010 | H102: Live animals & genetics > Day-old chicks & hatching eggs | I102: AN-CHK | J102: LS-POU-STR | K102: broiler | L102: live | M102: not_applicable | N102: breeding | V102: live_animal | W102: FALSE | X102: FALSE | Y102: Collect on hatch/delivery date | AC102: Commercial broiler | AD102: Tanzania | AE102: vifaranga|vifaranga vya nyama|broila|kuku wa nyama|central chicks (animal care) | AF102: Day-old broiler chicks from Central Chicks (Animal Care), booked against a hatch date (see Hatch_Schedule). Minimum order 50 chicks. | AG102: =COUNTIF(Variants!$B:$B,A102) -> 1 | AH102: TRUE
A103: P102 | B103: Tanzania Poultry Farms Broiler Day-old Chicks | C103: BR-TPF | D103: Tanzania Poultry Farms | E103: BR-TPF | F103: C70 | G103: C7010 | H103: Live animals & genetics > Day-old chicks & hatching eggs | I103: AN-CHK | J103: LS-POU-STR | K103: broiler | L103: live | M103: not_applicable | N103: breeding | V103: live_animal | W103: FALSE | X103: FALSE | Y103: Collect on hatch/delivery date | AC103: Commercial broiler | AD103: Tanzania | AE103: vifaranga|vifaranga vya nyama|broila|kuku wa nyama|tanzania poultry farms | AF103: Day-old broiler chicks from Tanzania Poultry Farms, booked against a hatch date (see Hatch_Schedule). Minimum order 50 chicks. | AG103: =COUNTIF(Variants!$B:$B,A103) -> 1 | AH103: TRUE
A104: P103 | B104: Tanzania Poultry Farms Layer Day-old Chicks | C104: BR-TPF | D104: Tanzania Poultry Farms | E104: BR-TPF | F104: C70 | G104: C7010 | H104: Live animals & genetics > Day-old chicks & hatching eggs | I104: AN-CHK | J104: LS-POU-STR | K104: layer | L104: live | M104: not_applicable | N104: breeding | V104: live_animal | W104: FALSE | X104: FALSE | Y104: Collect on hatch/delivery date | AC104: Commercial layer | AD104: Tanzania | AE104: vifaranga|vifaranga vya mayai|leya|kuku wa mayai|tanzania poultry farms | AF104: Day-old layer chicks from Tanzania Poultry Farms, booked against a hatch date (see Hatch_Schedule). Minimum order 50 chicks. | AG104: =COUNTIF(Variants!$B:$B,A104) -> 1 | AH104: TRUE
...

Sheet Variants
A1: sku | B1: product_id | C1: product_name | D1: variant_name | E1: display_name | F1: pack_size_value | G1: pack_size_unit | H1: selling_unit | I1: net_weight_kg | J1: gtin | K1: reference_price_tzs | L1: min_order_qty | M1: stocked_in_stores
A2: P001-25KG | B2: P001 | C2: Broiler Starter Crumbs | D2: 25 kg bag | E2: Broiler Starter Crumbs - 25 kg bag | F2: 25 | G2: kg | H2: bag | I2: 25.2 | J2: 2000000000015 | K2: 42000 | L2: 1 | M2: =IF(COUNTIF(Products!$A:$A,B2)=0,"",IF(INDEX(Products!$G:$G,MATCH(B2,Products!$A:$A,0))="C7010","Hatch_Schedule: "&COUNTIF(Hatch_Schedule!$B:$B,A2)&" dates",COUNTIF(Store_Inventory!$C:$C,A2))) -> 2
A3: P001-50KG | B3: P001 | C3: Broiler Starter Crumbs | D3: 50 kg bag | E3: Broiler Starter Crumbs - 50 kg bag | F3: 50 | G3: kg | H3: bag | I3: 50.3 | J3: 2000000000022 | K3: 82000 | L3: 1 | M3: =IF(COUNTIF(Products!$A:$A,B3)=0,"",IF(INDEX(Products!$G:$G,MATCH(B3,Products!$A:$A,0))="C7010","Hatch_Schedule: "&COUNTIF(Hatch_Schedule!$B:$B,A3)&" dates",COUNTIF(Store_Inventory!$C:$C,A3))) -> 5
A4: P002-25KG | B4: P002 | C4: Broiler Grower Pellets | D4: 25 kg bag | E4: Broiler Grower Pellets - 25 kg bag | F4: 25 | G4: kg | H4: bag | I4: 25.2 | J4: 2000000000039 | K4: 40000 | L4: 1 | M4: =IF(COUNTIF(Products!$A:$A,B4)=0,"",IF(INDEX(Products!$G:$G,MATCH(B4,Products!$A:$A,0))="C7010","Hatch_Schedule: "&COUNTIF(Hatch_Schedule!$B:$B,A4)&" dates",COUNTIF(Store_Inventory!$C:$C,A4))) -> 2
A5: P002-50KG | B5: P002 | C5: Broiler Grower Pellets | D5: 50 kg bag | E5: Broiler Grower Pellets - 50 kg bag | F5: 50 | G5: kg | H5: bag | I5: 50.3 | J5: 2000000000046 | K5: 78000 | L5: 1 | M5: =IF(COUNTIF(Products!$A:$A,B5)=0,"",IF(INDEX(Products!$G:$G,MATCH(B5,Products!$A:$A,0))="C7010","Hatch_Schedule: "&COUNTIF(Hatch_Schedule!$B:$B,A5)&" dates",COUNTIF(Store_Inventory!$C:$C,A5))) -> 4
A6: P003-25KG | B6: P003 | C6: Broiler Finisher Pellets | D6: 25 kg bag | E6: Broiler Finisher Pellets - 25 kg bag | F6: 25 | G6: kg | H6: bag | I6: 25.2 | J6: 2000000000053 | K6: 39000 | L6: 1 | M6: =IF(COUNTIF(Products!$A:$A,B6)=0,"",IF(INDEX(Products!$G:$G,MATCH(B6,Products!$A:$A,0))="C7010","Hatch_Schedule: "&COUNTIF(Hatch_Schedule!$B:$B,A6)&" dates",COUNTIF(Store_Inventory!$C:$C,A6))) -> 4
A7: P003-50KG | B7: P003 | C7: Broiler Finisher Pellets | D7: 50 kg bag | E7: Broiler Finisher Pellets - 50 kg bag | F7: 50 | G7: kg | H7: bag | I7: 50.3 | J7: 2000000000060 | K7: 76000 | L7: 1 | M7: =IF(COUNTIF(Products!$A:$A,B7)=0,"",IF(INDEX(Products!$G:$G,MATCH(B7,Products!$A:$A,0))="C7010","Hatch_Schedule: "&COUNTIF(Hatch_Schedule!$B:$B,A7)&" dates",COUNTIF(Store_Inventory!$C:$C,A7))) -> 3
A8: P004-50KG | B8: P004 | C8: Chick & Duck Mash | D8: 50 kg bag | E8: Chick & Duck Mash - 50 kg bag | F8: 50 | G8: kg | H8: bag | I8: 50.3 | J8: 2000000000077 | K8: 70000 | L8: 1 | M8: =IF(COUNTIF(Products!$A:$A,B8)=0,"",IF(INDEX(Products!$G:$G,MATCH(B8,Products!$A:$A,0))="C7010","Hatch_Schedule: "&COUNTIF(Hatch_Schedule!$B:$B,A8)&" dates",COUNTIF(Store_Inventory!$C:$C,A8))) -> 4
A9: P005-25KG | B9: P005 | C9: Growers Mash | D9: 25 kg bag | E9: Growers Mash - 25 kg bag | F9: 25 | G9: kg | H9: bag | I9: 25.2 | J9: 2000000000084 | K9: 32000 | L9: 1 | M9: =IF(COUNTIF(Products!$A:$A,B9)=0,"",IF(INDEX(Products!$G:$G,MATCH(B9,Products!$A:$A,0))="C7010","Hatch_Schedule: "&COUNTIF(Hatch_Schedule!$B:$B,A9)&" dates",COUNTIF(Store_Inventory!$C:$C,A9))) -> 5
A10: P005-50KG | B10: P005 | C10: Growers Mash | D10: 50 kg bag | E10: Growers Mash - 50 kg bag | F10: 50 | G10: kg | H10: bag | I10: 50.3 | J10: 2000000000091 | K10: 62000 | L10: 1 | M10: =IF(COUNTIF(Products!$A:$A,B10)=0,"",IF(INDEX(Products!$G:$G,MATCH(B10,Products!$A:$A,0))="C7010","Hatch_Schedule: "&COUNTIF(Hatch_Schedule!$B:$B,A10)&" dates",COUNTIF(Store_Inventory!$C:$C,A10))) -> 4
A11: P006-25KG | B11: P006 | C11: Layers Mash | D11: 25 kg bag | E11: Layers Mash - 25 kg bag | F11: 25 | G11: kg | H11: bag | I11: 25.2 | J11: 2000000000107 | K11: 31000 | L11: 1 | M11: =IF(COUNTIF(Products!$A:$A,B11)=0,"",IF(INDEX(Products!$G:$G,MATCH(B11,Products!$A:$A,0))="C7010","Hatch_Schedule: "&COUNTIF(Hatch_Schedule!$B:$B,A11)&" dates",COUNTIF(Store_Inventory!$C:$C,A11))) -> 3
A12: P006-50KG | B12: P006 | C12: Layers Mash | D12: 50 kg bag | E12: Layers Mash - 50 kg bag | F12: 50 | G12: kg | H12: bag | I12: 50.3 | J12: 2000000000114 | K12: 60000 | L12: 1 | M12: =IF(COUNTIF(Products!$A:$A,B12)=0,"",IF(INDEX(Products!$G:$G,MATCH(B12,Products!$A:$A,0))="C7010","Hatch_Schedule: "&COUNTIF(Hatch_Schedule!$B:$B,A12)&" dates",COUNTIF(Store_Inventory!$C:$C,A12))) -> 5
A13: P007-50KG | B13: P007 | C13: Kienyeji Grower Mash | D13: 50 kg bag | E13: Kienyeji Grower Mash - 50 kg bag | F13: 50 | G13: kg | H13: bag | I13: 50.3 | J13: 2000000000121 | K13: 58000 | L13: 1 | M13: =IF(COUNTIF(Products!$A:$A,B13)=0,"",IF(INDEX(Products!$G:$G,MATCH(B13,Products!$A:$A,0))="C7010","Hatch_Schedule: "&COUNTIF(Hatch_Schedule!$B:$B,A13)&" dates",COUNTIF(Store_Inventory!$C:$C,A13))) -> 5
... A151: P115-1S | B151: P115 | C151: Friesian Dairy Semen | D151: Per straw | E151: Friesian Dairy Semen (per straw) | F151: 1 | G151: straws | H151: straw | I151: 0.01 | J151: 2000000001500 | K151: 25000 | L151: 1 | M151: =IF(COUNTIF(Products!$A:$A,B151)=0,"",IF(INDEX(Products!$G:$G,MATCH(B151,Products!$A:$A,0))="C7010","Hatch_Schedule: "&COUNTIF(Hatch_Schedule!$B:$B,A151)&" dates",COUNTIF(Store_Inventory!$C:$C,A151))) -> 0

Sheet Store_Inventory
A1: inventory_id | B1: store_id | C1: sku | D1: product_name | E1: qty_on_hand | F1: reorder_level | G1: cost_price_tzs | H1: selling_price_tzs | I1: batch_no | J1: expiry_date | K1: listed_online | L1: online_qty | M1: stock_value_cost_tzs | N1: stock_value_selling_tzs | O1: margin_pct | P1: days_to_expiry | Q1: stock_status | R1: expiry_status | S1: test_scenario
A2: INV-00001 | B2: ST-AMS-TEG | C2: P001-25KG | D2: Broiler Starter Crumbs - 25 kg bag | E2: 116 | F2: 11 | G2: 34100 | H2: 42000 | I2: TEG-P00125KG-2602 | J2: 46430 | K2: TRUE | L2: 81 | M2: =E2*G2 -> 3955600 | N2: =E2*H2 -> 4872000 | O2: =IF(H2=0,"",(H2-G2)/H2) -> 0.18809524 | P2: =IF(J2="","",J2-README!$C$4) -> 108 | Q2: =IF(E2=0,"Out of stock",IF(E2<=F2,"Low stock","OK")) -> OK | R2: =IF(J2="","No expiry",IF(P2<0,"Expired",IF(P2<=30,"Expiring <=30 days","OK"))) -> OK
A3: INV-00002 | B3: ST-AMS-TEG | C3: P001-50KG | D3: Broiler Starter Crumbs - 50 kg bag | E3: 150 | F3: 11 | G3: 68600 | H3: 82000 | I3: TEG-P00150KG-2603 | J3: 46448 | K3: TRUE | L3: 105 | M3: =E3*G3 -> 10290000 | N3: =E3*H3 -> 12300000 | O3: =IF(H3=0,"",(H3-G3)/H3) -> 0.16341463 | P3: =IF(J3="","",J3-README!$C$4) -> 126 | Q3: =IF(E3=0,"Out of stock",IF(E3<=F3,"Low stock","OK")) -> OK | R3: =IF(J3="","No expiry",IF(P3<0,"Expired",IF(P3<=30,"Expiring <=30 days","OK"))) -> OK
A4: INV-00003 | B4: ST-AMS-TEG | C4: P002-25KG | D4: Broiler Grower Pellets - 25 kg bag | E4: 0 | F4: 11 | G4: 34800 | H4: 40000 | I4: TEG-P00225KG-2512 | J4: 46377 | K4: TRUE | L4: 0 | M4: =E4*G4 -> 0 | N4: =E4*H4 -> 0 | O4: =IF(H4=0,"",(H4-G4)/H4) -> 0.13 | P4: =IF(J4="","",J4-README!$C$4) -> 55 | Q4: =IF(E4=0,"Out of stock",IF(E4<=F4,"Low stock","OK")) -> Out of stock | R4: =IF(J4="","No expiry",IF(P4<0,"Expired",IF(P4<=30,"Expiring <=30 days","OK"))) -> OK | S4: Out of stock (mirrors live 'Chicken Grower 25KG - 0 bag left')
A5: INV-00004 | B5: ST-AMS-TEG | C5: P002-50KG | D5: Broiler Grower Pellets - 50 kg bag | E5: 56 | F5: 11 | G5: 67900 | H5: 78000 | I5: TEG-P00250KG-2603 | J5: 46471 | K5: TRUE | L5: 39 | M5: =E5*G5 -> 3802400 | N5: =E5*H5 -> 4368000 | O5: =IF(H5=0,"",(H5-G5)/H5) -> 0.12948718 | P5: =IF(J5="","",J5-README!$C$4) -> 149 | Q5: =IF(E5=0,"Out of stock",IF(E5<=F5,"Low stock","OK")) -> OK | R5: =IF(J5="","No expiry",IF(P5<0,"Expired",IF(P5<=30,"Expiring <=30 days","OK"))) -> OK
A6: INV-00005 | B6: ST-AMS-TEG | C6: P003-25KG | D6: Broiler Finisher Pellets - 25 kg bag | E6: 108 | F6: 11 | G6: 33500 | H6: 39000 | I6: TEG-P00325KG-2603 | J6: 46471 | K6: TRUE | L6: 75 | M6: =E6*G6 -> 3618000 | N6: =E6*H6 -> 4212000 | O6: =IF(H6=0,"",(H6-G6)/H6) -> 0.14102564 | P6: =IF(J6="","",J6-README!$C$4) -> 149 | Q6: =IF(E6=0,"Out of stock",IF(E6<=F6,"Low stock","OK")) -> OK | R6: =IF(J6="","No expiry",IF(P6<0,"Expired",IF(P6<=30,"Expiring <=30 days","OK"))) -> OK
A7: INV-00006 | B7: ST-AMS-TEG | C7: P003-50KG | D7: Broiler Finisher Pellets - 50 kg bag | E7: 78 | F7: 11 | G7: 61800 | H7: 76000 | I7: TEG-P00350KG-2512 | J7: 46384 | K7: TRUE | L7: 54 | M7: =E7*G7 -> 4820400 | N7: =E7*H7 -> 5928000 | O7: =IF(H7=0,"",(H7-G7)/H7) -> 0.18684211 | P7: =IF(J7="","",J7-README!$C$4) -> 62 | Q7: =IF(E7=0,"Out of stock",IF(E7<=F7,"Low stock","OK")) -> OK | R7: =IF(J7="","No expiry",IF(P7<0,"Expired",IF(P7<=30,"Expiring <=30 days","OK"))) -> OK
A8: INV-00007 | B8: ST-AMS-TEG | C8: P004-50KG | D8: Chick & Duck Mash - 50 kg bag | E8: 36 | F8: 11 | G8: 57400 | H8: 70000 | I8: TEG-P00450KG-2602 | J8: 46422 | K8: FALSE | L8: 0 | M8: =E8*G8 -> 2066400 | N8: =E8*H8 -> 2520000 | O8: =IF(H8=0,"",(H8-G8)/H8) -> 0.18 | P8: =IF(J8="","",J8-README!$C$4) -> 100 | Q8: =IF(E8=0,"Out of stock",IF(E8<=F8,"Low stock","OK")) -> OK | R8: =IF(J8="","No expiry",IF(P8<0,"Expired",IF(P8<=30,"Expiring <=30 days","OK"))) -> OK
A9: INV-00008 | B9: ST-AMS-TEG | C9: P005-25KG | D9: Growers Mash - 25 kg bag | E9: 122 | F9: 11 | G9: 27700 | H9: 32000 | I9: TEG-P00525KG-2601 | J9: 46395 | K9: TRUE | L9: 85 | M9: =E9*G9 -> 3379400 | N9: =E9*H9 -> 3904000 | O9: =IF(H9=0,"",(H9-G9)/H9) -> 0.134375 | P9: =IF(J9="","",J9-README!$C$4) -> 73 | Q9: =IF(E9=0,"Out of stock",IF(E9<=F9,"Low stock","OK")) -> OK | R9: =IF(J9="","No expiry",IF(P9<0,"Expired",IF(P9<=30,"Expiring <=30 days","OK"))) -> OK
A10: INV-00009 | B10: ST-AMS-TEG | C10: P005-50KG | D10: Growers Mash - 50 kg bag | E10: 126 | F10: 11 | G10: 53800 | H10: 62000 | I10: TEG-P00550KG-2602 | J10: 46440 | K10: TRUE | L10: 88 | M10: =E10*G10 -> 6778800 | N10: =E10*H10 -> 7812000 | O10: =IF(H10=0,"",(H10-G10)/H10) -> 0.13225806 | P10: =IF(J10="","",J10-README!$C$4) -> 118 | Q10: =IF(E10=0,"Out of stock",IF(E10<=F10,"Low stock","OK")) -> OK | R10: =IF(J10="","No expiry",IF(P10<0,"Expired",IF(P10<=30,"Expiring <=30 days","OK"))) -> OK
A11: INV-00010 | B11: ST-AMS-TEG | C11: P006-25KG | D11: Layers Mash - 25 kg bag | E11: 46 | F11: 11 | G11: 27100 | H11: 31000 | I11: TEG-P00625KG-2601 | J11: 46418 | K11: TRUE | L11: 32 | M11: =E11*G11 -> 1246600 | N11: =E11*H11 -> 1426000 | O11: =IF(H11=0,"",(H11-G11)/H11) -> 0.12580645 | P11: =IF(J11="","",J11-README!$C$4) -> 96 | Q11: =IF(E11=0,"Out of stock",IF(E11<=F11,"Low stock","OK")) -> OK | R11: =IF(J11="","No expiry",IF(P11<0,"Expired",IF(P11<=30,"Expiring <=30 days","OK"))) -> OK
A12: INV-00011 | B12: ST-AMS-TEG | C12: P006-50KG | D12: Layers Mash - 50 kg bag | E12: 50 | F12: 11 | G12: 50300 | H12: 60000 | I12: TEG-P00650KG-2512 | J12: 46375 | K12: TRUE | L12: 35 | M12: =E12*G12 -> 2515000 | N12: =E12*H12 -> 3000000 | O12: =IF(H12=0,"",(H12-G12)/H12) -> 0.16166667 | P12: =IF(J12="","",J12-README!$C$4) -> 53 | Q12: =IF(E12=0,"Out of stock",IF(E12<=F12,"Low stock","OK")) -> OK | R12: =IF(J12="","No expiry",IF(P12<0,"Expired",IF(P12<=30,"Expiring <=30 days","OK"))) -> OK
A13: INV-00012 | B13: ST-AMS-TEG | C13: P007-50KG | D13: Kienyeji Grower Mash - 50 kg bag | E13: 100 | F13: 11 | G13: 48800 | H13: 58000 | I13: TEG-P00750KG-2601 | J13: 46406 | K13: TRUE | L13: 70 | M13: =E13*G13 -> 4880000 | N13: =E13*H13 -> 5800000 | O13: =IF(H13=0,"",(H13-G13)/H13) -> 0.15862069 | P13: =IF(J13="","",J13-README!$C$4) -> 84 | Q13: =IF(E13=0,"Out of stock",IF(E13<=F13,"Low stock","OK")) -> OK | R13: =IF(J13="","No expiry",IF(P13<0,"Expired",IF(P13<=30,"Expiring <=30 days","OK"))) -> OK
A14: INV-00013 | B14: ST-AMS-TEG | C14: P008-25KG | D14: Pig Creep Pellets - 25 kg bag | E14: 108 | F14: 11 | G14: 42400 | H14: 48000 | I14: TEG-P00825KG-2512 | J14: 46361 | K14: FALSE | L14: 0 | M14: =E14*G14 -> 4579200 | N14: =E14*H14 -> 5184000 | O14: =IF(H14=0,"",(H14-G14)/H14) -> 0.11666667 | P14: =IF(J14="","",J14-README!$C$4) -> 39 | Q14: =IF(E14=0,"Out of stock",IF(E14<=F14,"Low stock","OK")) -> OK | R14: =IF(J14="","No expiry",IF(P14<0,"Expired",IF(P14<=30,"Expiring <=30 days","OK"))) -> OK
A15: INV-00014 | B15: ST-AMS-TEG | C15: P009-50KG | D15: Pig Grower Pellets - 50 kg bag | E15: 50 | F15: 11 | G15: 56800 | H15: 66000 | I15: TEG-P00950KG-2601 | J15: 46412 | K15: TRUE | L15: 35 | M15: =E15*G15 -> 2840000 | N15: =E15*H15 -> 3300000 | O15: =IF(H15=0,"",(H15-G15)/H15) -> 0.13939394 | P15: =IF(J15="","",J15-README!$C$4) -> 90 | Q15: =IF(E15=0,"Out of stock",IF(E15<=F15,"Low stock","OK")) -> OK | R15: =IF(J15="","No expiry",IF(P15<0,"Expired",IF(P15<=30,"Expiring <=30 days","OK"))) -> OK
A16: INV-00015 | B16: ST-AMS-TEG | C16: P010-50KG | D16: Sow & Weaner Meal - 50 kg bag | E16: 112 | F16: 11 | G16: 51400 | H16: 60000 | I16: TEG-P01050KG-2601 | J16: 46393 | K16: TRUE | L16: 78 | M16: =E16*G16 -> 5756800 | N16: =E16*H16 -> 6720000 | O16: =IF(H16=0,"",(H16-G16)/H16) -> 0.14333333 | P16: =IF(J16="","",J16-README!$C$4) -> 71 | Q16: =IF(E16=0,"Out of stock",IF(E16<=F16,"Low stock","OK")) -> OK | R16: =IF(J16="","No expiry",IF(P16<0,"Expired",IF(P16<=30,"Expiring <=30 days","OK"))) -> OK
... A25: INV-00024 | B25: ST-AMS-TEG | C25: P018-25KG | D25: Pig Protein Concentrate 20% - 25 kg bag | E25: 88 | F25: 11 | G25: 44100 | H25: 49000 | I25: TEG-P01825KG-2601 | J25: 46405 | K25: TRUE | L25: 61 | M25: =E25*G25 -> 3880800 | N25: =E25*H25 -> 4312000 | O25: =IF(H25=0,"",(H25-G25)/H25) -> 0.1 | P25: =IF(J25="","",J25-README!$C$4) -> 83 | Q25: =IF(E25=0,"Out of stock",IF(E25<=F25,"Low stock","OK")) -> OK | R25: =IF(J25="","No expiry",IF(P25<0,"Expired",IF(P25<=30,"Expiring <=30 days","OK"))) -> OK
A26: INV-00025 | B26: ST-AMS-TEG | C26: P018-50KG | D26: Pig Protein Concentrate 20% - 50 kg bag | E26: 6 | F26: 25 | G26: 78200 | H26: 95000 | I26: TEG-P01850KG-2603 | J26: 46468 | K26: FALSE | L26: 0 | M26: =E26*G26 -> 469200 | N26: =E26*H26 -> 570000 | O26: =IF(H26=0,"",(H26-G26)/H26) -> 0.17684211 | P26: =IF(J26="","",J26-README!$C$4) -> 146 | Q26: =IF(E26=0,"Out of stock",IF(E26<=F26,"Low stock","OK")) -> Low stock | R26: =IF(J26="","No expiry",IF(P26<0,"Expired",IF(P26<=30,"Expiring <=30 days","OK"))) -> OK | S26: Low stock
A27: INV-00026 | B27: ST-AMS-TEG | C27: P019-50KG | D27: Broiler Concentrate 30% - 50 kg bag | E27: 72 | F27: 11 | G27: 86600 | H27: 105000 | I27: TEG-P01950KG-2512 | J27: 46361 | K27: TRUE | L27: 50 | M27: =E27*G27 -> 6235200 | N27: =E27*H27 -> 7560000 | O27: =IF(H27=0,"",(H27-G27)/H27) -> 0.1752381 | P27: =IF(J27="","",J27-README!$C$4) -> 39 | Q27: =IF(E27=0,"Out of stock",IF(E27<=F27,"Low stock","OK")) -> OK | R27: =IF(J27="","No expiry",IF(P27<0,"Expired",IF(P27<=30,"Expiring <=30 days","OK"))) -> OK
A28: INV-00027 | B28: ST-AMS-TEG | C28: P020-50KG | D28: Layers Concentrate - 50 kg bag | E28: 118 | F28: 11 | G28: 82000 | H28: 92000 | I28: TEG-P02050KG-2603 | J28: 46467 | K28: TRUE | L28: 82 | M28: =E28*G28 -> 9676000 | N28: =E28*H28 -> 10856000 | O28: =IF(H28=0,"",(H28-G28)/H28) -> 0.10869565 | P28: =IF(J28="","",J28-README!$C$4) -> 145 | Q28: =IF(E28=0,"Out of stock",IF(E28<=F28,"Low stock","OK")) -> OK | R28: =IF(J28="","No expiry",IF(P28<0,"Expired",IF(P28<=30,"Expiring <=30 days","OK"))) -> OK
A29: INV-00028 | B29: ST-AMS-TEG | C29: P021-50KG | D29: Dairy Concentrate - 50 kg bag | E29: 90 | F29: 11 | G29: 57800 | H29: 70000 | I29: TEG-P02150KG-2603 | J29: 46472 | K29: TRUE | L29: 62 | M29: =E29*G29 -> 5202000 | N29: =E29*H29 -> 6300000 | O29: =IF(H29=0,"",(H29-G29)/H29) -> 0.17428571 | P29: =IF(J29="","",J29-README!$C$4) -> 150 | Q29: =IF(E29=0,"Out of stock",IF(E29<=F29,"Low stock","OK")) -> OK | R29: =IF(J29="","No expiry",IF(P29<0,"Expired",IF(P29<=30,"Expiring <=30 days","OK"))) -> OK
A30: INV-00029 | B30: ST-AMS-TEG | C30: P022-5KG | D30: Broiler Premix 2.5% - 5 kg bag | E30: 152 | F30: 11 | G30: 35400 | H30: 42000 | I30: TEG-P0225KG-2609 | J30: 46656 | K30: TRUE | L30: 106 | M30: =E30*G30 -> 5380800 | N30: =E30*H30 -> 6384000 | O30: =IF(H30=0,"",(H30-G30)/H30) -> 0.15714286 | P30: =IF(J30="","",J30-README!$C$4) -> 334 | Q30: =IF(E30=0,"Out of stock",IF(E30<=F30,"Low stock","OK")) -> OK | R30: =IF(J30="","No expiry",IF(P30<0,"Expired",IF(P30<=30,"Expiring <=30 days","OK"))) -> OK
A31: INV-00030 | B31: ST-AMS-TEG | C31: P023-1KG | D31: Layer Premix 2.5% - 1 kg pack | E31: 59 | F31: 8 | G31: 7300 | H31: 8500 | I31: TEG-P0231KG-2608 | J31: 46626 | K31: TRUE | L31: 41 | M31: =E31*G31 -> 430700 | N31: =E31*H31 -> 501500 | O31: =IF(H31=0,"",(H31-G31)/H31) -> 0.14117647 | P31: =IF(J31="","",J31-README!$C$4) -> 304 | Q31: =IF(E31=0,"Out of stock",IF(E31<=F31,"Low stock","OK")) -> OK | R31: =IF(J31="","No expiry",IF(P31<0,"Expired",IF(P31<=30,"Expiring <=30 days","OK"))) -> OK
A32: INV-00031 | B32: ST-AMS-TEG | C32: P023-5KG | D32: Layer Premix 2.5% - 5 kg bag | E32: 52 | F32: 11 | G32: 35700 | H32: 40000 | I32: TEG-P0235KG-2607 | J32: 46576 | K32: TRUE | L32: 36 | M32: =E32*G32 -> 1856400 | N32: =E32*H32 -> 2080000 | O32: =IF(H32=0,"",(H32-G32)/H32) -> 0.1075 | P32: =IF(J32="","",J32-README!$C$4) -> 254 | Q32: =IF(E32=0,"Out of stock",IF(E32<=F32,"Low stock","OK")) -> OK | R32: =IF(J32="","No expiry",IF(P32<0,"Expired",IF(P32<=30,"Expiring <=30 days","OK"))) -> OK
A33: INV-00032 | B33: ST-AMS-TEG | C33: P024-1KG | D33: Pig Premix 2.5% - 1 kg pack | E33: 23 | F33: 8 | G33: 7300 | H33: 8500 | I33: TEG-P0241KG-2604 | J33: 46490 | K33: FALSE | L33: 0 | M33: =E33*G33 -> 167900 | N33: =E33*H33 -> 195500 | O33: =IF(H33=0,"",(H33-G33)/H33) -> 0.14117647 | P33: =IF(J33="","",J33-README!$C$4) -> 168 | Q33: =IF(E33=0,"Out of stock",IF(E33<=F33,"Low stock","OK")) -> OK | R33: =IF(J33="","No expiry",IF(P33<0,"Expired",IF(P33<=30,"Expiring <=30 days","OK"))) -> OK
A34: INV-00033 | B34: ST-AMS-TEG | C34: P024-5KG | D34: Pig Premix 2.5% - 5 kg bag | E34: 86 | F34: 11 | G34: 34800 | H34: 40000 | I34: TEG-P0245KG-2603 | J34: 46473 | K34: TRUE | L34: 60 | M34: =E34*G34 -> 2992800 | N34: =E34*H34 -> 3440000 | O34: =IF(H34=0,"",(H34-G34)/H34) -> 0.13 | P34: =IF(J34="","",J34-README!$C$4) -> 151 | Q34: =IF(E34=0,"Out of stock",IF(E34<=F34,"Low stock","OK")) -> OK | R34: =IF(J34="","No expiry",IF(P34<0,"Expired",IF(P34<=30,"Expiring <=30 days","OK"))) -> OK
A35: INV-00034 | B35: ST-AMS-TEG | C35: P025-50KG | D35: Maize Bran - 50 kg bag | E35: 154 | F35: 11 | G35: 15100 | H35: 18000 | I35: TEG-P02550KG-2603 | J35: 46463 | K35: TRUE | L35: 107 | M35: =E35*G35 -> 2325400 | N35: =E35*H35 -> 2772000 | O35: =IF(H35=0,"",(H35-G35)/H35) -> 0.16111111 | P35: =IF(J35="","",J35-README!$C$4) -> 141 | Q35: =IF(E35=0,"Out of stock",IF(E35<=F35,"Low stock","OK")) -> OK | R35: =IF(J35="","No expiry",IF(P35<0,"Expired",IF(P35<=30,"Expiring <=30 days","OK"))) -> OK
A36: INV-00035 | B36: ST-AMS-TEG | C36: P026-50KG | D36: Sunflower Seed Cake - 50 kg bag | E36: 60 | F36: 11 | G36: 31300 | H36: 38000 | I36: TEG-P02650KG-2602 | J36: 46426 | K36: TRUE | L36: 42 | M36: =E36*G36 -> 1878000 | N36: =E36*H36 -> 2280000 | O36: =IF(H36=0,"",(H36-G36)/H36) -> 0.17631579 | P36: =IF(J36="","",J36-README!$C$4) -> 104 | Q36: =IF(E36=0,"Out of stock",IF(E36<=F36,"Low stock","OK")) -> OK | R36: =IF(J36="","No expiry",IF(P36<0,"Expired",IF(P36<=30,"Expiring <=30 days","OK"))) -> OK
A37: INV-00036 | B37: ST-AMS-TEG | C37: P027-50KG | D37: Soybean Meal - 50 kg bag | E37: 68 | F37: 11 | G37: 85900 | H37: 105000 | I37: TEG-P02750KG-2601 | J37: 46395 | K37: TRUE | L37: 47 | M37: =E37*G37 -> 5841200 | N37: =E37*H37 -> 7140000 | O37: =IF(H37=0,"",(H37-G37)/H37) -> 0.18190476 | P37: =IF(J37="","",J37-README!$C$4) -> 73 | Q37: =IF(E37=0,"Out of stock",IF(E37<=F37,"Low stock","OK")) -> OK | R37: =IF(J37="","No expiry",IF(P37<0,"Expired",IF(P37<=30,"Expiring <=30 days","OK"))) -> OK
A38: INV-00037 | B38: ST-AMS-TEG | C38: P028-25KG | D38: Fish Meal (Dagaa) - 25 kg bag | E38: 34 | F38: 11 | G38: 54400 | H38: 62000 | I38: TEG-P02825KG-2512 | J38: 46376 | K38: TRUE | L38: 23 | M38: =E38*G38 -> 1849600 | N38: =E38*H38 -> 2108000 | O38: =IF(H38=0,"",(H38-G38)/H38) -> 0.12258065 | P38: =IF(J38="","",J38-README!$C$4) -> 54 | Q38: =IF(E38=0,"Out of stock",IF(E38<=F38,"Low stock","OK")) -> OK | R38: =IF(J38="","No expiry",IF(P38<0,"Expired",IF(P38<=30,"Expiring <=30 days","OK"))) -> OK
... A42: INV-00041 | B42: ST-AMS-TEG | C42: P031-50KG | D42: Yellow Maize (Whole) - 50 kg bag | E42: 152 | F42: 11 | G42: 34700 | H42: 40000 | I42: TEG-P03150KG-2605 | J42: 46511 | K42: TRUE | L42: 106 | M42: =E42*G42 -> 5274400 | N42: =E42*H42 -> 6080000 | O42: =IF(H42=0,"",(H42-G42)/H42) -> 0.1325 | P42: =IF(J42="","",J42-README!$C$4) -> 189 | Q42: =IF(E42=0,"Out of stock",IF(E42<=F42,"Low stock","OK")) -> OK | R42: =IF(J42="","No expiry",IF(P42<0,"Expired",IF(P42<=30,"Expiring <=30 days","OK"))) -> OK
A43: INV-00042 | B43: ST-AMS-TEG | C43: P034-100G | D43: Vitamix Chick - 100 g sachet | E43: 124 | F43: 28 | G43: 3400 | H43: 4000 | I43: TEG-P034100G-2607 | J43: 46334 | K43: TRUE | L43: 86 | M43: =E43*G43 -> 421600 | N43: =E43*H43 -> 496000 | O43: =IF(H43=0,"",(H43-G43)/H43) -> 0.15 | P43: =IF(J43="","",J43-README!$C$4) -> 12 | Q43: =IF(E43=0,"Out of stock",IF(E43<=F43,"Low stock","OK")) -> OK | R43: =IF(J43="","No expiry",IF(P43<0,"Expired",IF(P43<=30,"Expiring <=30 days","OK"))) -> Expiring <=30 days | S43: Expiring within 30 days
A44: INV-00043 | B44: ST-AMS-TEG | C44: P034-250G | D44: Vitamix Chick - 250 g sachet | E44: 92 | F44: 28 | G44: 8100 | H44: 9000 | I44: TEG-P034250G-2610 | J44: 46678 | K44: TRUE | L44: 64 | M44: =E44*G44 -> 745200 | N44: =E44*H44 -> 828000 | O44: =IF(H44=0,"",(H44-G44)/H44) -> 0.1 | P44: =IF(J44="","",J44-README!$C$4) -> 356 | Q44: =IF(E44=0,"Out of stock",IF(E44<=F44,"Low stock","OK")) -> OK | R44: =IF(J44="","No expiry",IF(P44<0,"Expired",IF(P44<=30,"Expiring <=30 days","OK"))) -> OK
A45: INV-00044 | B45: ST-AMS-TEG | C45: P034-30G | D45: Vitamix Chick - 30 g sachet | E45: 86 | F45: 28 | G45: 1200 | H45: 1500 | I45: TEG-P03430G-2703 | J45: 46812 | K45: TRUE | L45: 60 | M45: =E45*G45 -> 103200 | N45: =E45*H45 -> 129000 | O45: =IF(H45=0,"",(H45-G45)/H45) -> 0.2 | P45: =IF(J45="","",J45-README!$C$4) -> 490 | Q45: =IF(E45=0,"Out of stock",IF(E45<=F45,"Low stock","OK")) -> OK | R45: =IF(J45="","No expiry",IF(P45<0,"Expired",IF(P45<=30,"Expiring <=30 days","OK"))) -> OK
A46: INV-00045 | B46: ST-AMS-TEG | C46: P035-100G | D46: Vitamix Plus - 100 g sachet | E46: 138 | F46: 28 | G46: 3800 | H46: 4500 | I46: TEG-P035100G-2603 | J46: 46451 | K46: TRUE | L46: 96 | M46: =E46*G46 -> 524400 | N46: =E46*H46 -> 621000 | O46: =IF(H46=0,"",(H46-G46)/H46) -> 0.15555556 | P46: =IF(J46="","",J46-README!$C$4) -> 129 | Q46: =IF(E46=0,"Out of stock",IF(E46<=F46,"Low stock","OK")) -> OK | R46: =IF(J46="","No expiry",IF(P46<0,"Expired",IF(P46<=30,"Expiring <=30 days","OK"))) -> OK | S46: Same SKU priced differently across stores - test 'compare sellers/stores'
A47: INV-00046 | B47: ST-AMS-TEG | C47: P035-250G | D47: Vitamix Plus - 250 g sachet | E47: 168 | F47: 28 | G47: 8400 | H47: 10000 | I47: TEG-P035250G-2606 | J47: 46562 | K47: TRUE | L47: 117 | M47: =E47*G47 -> 1411200 | N47: =E47*H47 -> 1680000 | O47: =IF(H47=0,"",(H47-G47)/H47) -> 0.16 | P47: =IF(J47="","",J47-README!$C$4) -> 240 | Q47: =IF(E47=0,"Out of stock",IF(E47<=F47,"Low stock","OK")) -> OK | R47: =IF(J47="","No expiry",IF(P47<0,"Expired",IF(P47<=30,"Expiring <=30 days","OK"))) -> OK
A48: INV-00047 | B48: ST-AMS-TEG | C48: P035-30G | D48: Vitamix Plus - 30 g sachet | E48: 96 | F48: 28 | G48: 1200 | H48: 1500 | I48: TEG-P03530G-2610 | J48: 46683 | K48: TRUE | L48: 67 | M48: =E48*G48 -> 115200 | N48: =E48*H48 -> 144000 | O48: =IF(H48=0,"",(H48-G48)/H48) -> 0.2 | P48: =IF(J48="","",J48-README!$C$4) -> 361 | Q48: =IF(E48=0,"Out of stock",IF(E48<=F48,"Low stock","OK")) -> OK | R48: =IF(J48="","No expiry",IF(P48<0,"Expired",IF(P48<=30,"Expiring <=30 days","OK"))) -> OK
A49: INV-00048 | B49: ST-AMS-TEG | C49: P036-100G | D49: Multivitamin Soluble Powder - 100 g sachet | E49: 162 | F49: 28 | G49: 3400 | H49: 4000 | I49: TEG-P036100G-2701 | J49: 46771 | K49: TRUE | L49: 113 | M49: =E49*G49 -> 550800 | N49: =E49*H49 -> 648000 | O49: =IF(H49=0,"",(H49-G49)/H49) -> 0.15 | P49: =IF(J49="","",J49-README!$C$4) -> 449 | Q49: =IF(E49=0,"Out of stock",IF(E49<=F49,"Low stock","OK")) -> OK | R49: =IF(J49="","No expiry",IF(P49<0,"Expired",IF(P49<=30,"Expiring <=30 days","OK"))) -> OK
A50: INV-00049 | B50: ST-AMS-TEG | C50: P036-1KG | D50: Multivitamin Soluble Powder - 1 kg tin | E50: 6 | F50: 3 | G50: 25100 | H50: 30000 | I50: TEG-P0361KG-2604 | J50: 46495 | K50: FALSE | L50: 0 | M50: =E50*G50 -> 150600 | N50: =E50*H50 -> 180000 | O50: =IF(H50=0,"",(H50-G50)/H50) -> 0.16333333 | P50: =IF(J50="","",J50-README!$C$4) -> 173 | Q50: =IF(E50=0,"Out of stock",IF(E50<=F50,"Low stock","OK")) -> OK | R50: =IF(J50="","No expiry",IF(P50<0,"Expired",IF(P50<=30,"Expiring <=30 days","OK"))) -> OK
A51: INV-00050 | B51: ST-AMS-TEG | C51: P037-100ML | D51: Vitamin AD3E Injectable - 100 ml bottle | E51: 26 | F51: 8 | G51: 9700 | H51: 12000 | I51: TEG-P037100ML-2604 | J51: 46494 | K51: TRUE | L51: 18 | M51: =E51*G51 -> 252200 | N51: =E51*H51 -> 312000 | O51: =IF(H51=0,"",(H51-G51)/H51) -> 0.19166667 | P51: =IF(J51="","",J51-README!$C$4) -> 172 | Q51: =IF(E51=0,"Out of stock",IF(E51<=F51,"Low stock","OK")) -> OK | R51: =IF(J51="","No expiry",IF(P51<0,"Expired",IF(P51<=30,"Expiring <=30 days","OK"))) -> OK
A52: INV-00051 | B52: ST-AMS-TEG | C52: P038-1L | D52: Layer Tonic (Egg Booster) - 1 L bottle | E52: 42 | F52: 8 | G52: 24500 | H52: 28000 | I52: TEG-P0381L-2607 | J52: 46577 | K52: TRUE | L52: 29 | M52: =E52*G52 -> 1029000 | N52: =E52*H52 -> 1176000 | O52: =IF(H52=0,"",(H52-G52)/H52) -> 0.125 | P52: =IF(J52="","",J52-README!$C$4) -> 255 | Q52: =IF(E52=0,"Out of stock",IF(E52<=F52,"Low stock","OK")) -> OK | R52: =IF(J52="","No expiry",IF(P52<0,"Expired",IF(P52<=30,"Expiring <=30 days","OK"))) -> OK
A53: INV-00052 | B53: ST-AMS-TEG | C53: P038-500ML | D53: Layer Tonic (Egg Booster) - 500 ml bottle | E53: 24 | F53: 8 | G53: 13400 | H53: 15000 | I53: TEG-P038500ML-2709 | J53: 47002 | K53: TRUE | L53: 16 | M53: =E53*G53 -> 321600 | N53: =E53*H53 -> 360000 | O53: =IF(H53=0,"",(H53-G53)/H53) -> 0.10666667 | P53: =IF(J53="","",J53-README!$C$4) -> 680 | Q53: =IF(E53=0,"Out of stock",IF(E53<=F53,"Low stock","OK")) -> OK | R53: =IF(J53="","No expiry",IF(P53<0,"Expired",IF(P53<=30,"Expiring <=30 days","OK"))) -> OK
A54: INV-00053 | B54: ST-AMS-TEG | C54: P039-100G | D54: Clear Heat Electrolyte - 100 g sachet | E54: 159 | F54: 28 | G54: 3000 | H54: 3500 | I54: TEG-P039100G-2703 | J54: 46814 | K54: TRUE | L54: 111 | M54: =E54*G54 -> 477000 | N54: =E54*H54 -> 556500 | O54: =IF(H54=0,"",(H54-G54)/H54) -> 0.14285714 | P54: =IF(J54="","",J54-README!$C$4) -> 492 | Q54: =IF(E54=0,"Out of stock",IF(E54<=F54,"Low stock","OK")) -> OK | R54: =IF(J54="","No expiry",IF(P54<0,"Expired",IF(P54<=30,"Expiring <=30 days","OK"))) -> OK
A55: INV-00054 | B55: ST-AMS-TEG | C55: P039-250G | D55: Clear Heat Electrolyte - 250 g sachet | E55: 93 | F55: 28 | G55: 6800 | H55: 8000 | I55: TEG-P039250G-2704 | J55: 46848 | K55: TRUE | L55: 65 | M55: =E55*G55 -> 632400 | N55: =E55*H55 -> 744000 | O55: =IF(H55=0,"",(H55-G55)/H55) -> 0.15 | P55: =IF(J55="","",J55-README!$C$4) -> 526 | Q55: =IF(E55=0,"Out of stock",IF(E55<=F55,"Low stock","OK")) -> OK | R55: =IF(J55="","No expiry",IF(P55<0,"Expired",IF(P55<=30,"Expiring <=30 days","OK"))) -> OK
A56: INV-00055 | B56: ST-AMS-TEG | C56: P039-30G | D56: Clear Heat Electrolyte - 30 g sachet | E56: 124 | F56: 28 | G56: 1000 | H56: 1200 | I56: TEG-P03930G-2604 | J56: 46505 | K56: TRUE | L56: 86 | M56: =E56*G56 -> 124000 | N56: =E56*H56 -> 148800 | O56: =IF(H56=0,"",(H56-G56)/H56) -> 0.16666667 | P56: =IF(J56="","",J56-README!$C$4) -> 183 | Q56: =IF(E56=0,"Out of stock",IF(E56<=F56,"Low stock","OK")) -> OK | R56: =IF(J56="","No expiry",IF(P56<0,"Expired",IF(P56<=30,"Expiring <=30 days","OK"))) -> OK
A57: INV-00056 | B57: ST-AMS-TEG | C57: P040-100G | D57: Livestock Oral Rehydration Salts - 100 g sachet | E57: 58 | F57: 28 | G57: 2400 | H57: 3000 | I57: TEG-P040100G-2608 | J57: 46607 | K57: TRUE | L57: 40 | M57: =E57*G57 -> 139200 | N57: =E57*H57 -> 174000 | O57: =IF(H57=0,"",(H57-G57)/H57) -> 0.2 | P57: =IF(J57="","",J57-README!$C$4) -> 285 | Q57: =IF(E57=0,"Out of stock",IF(E57<=F57,"Low stock","OK")) -> OK | R57: =IF(J57="","No expiry",IF(P57<0,"Expired",IF(P57<=30,"Expiring <=30 days","OK"))) -> OK
A58: INV-00057 | B58: ST-AMS-TEG | C58: P041-2KG | D58: Goat & Sheep Mineral Lick - 2 kg piece | E58: 7 | F58: 4 | G58: 6100 | H58: 7000 | I58: TEG-P0412KG-2607 | J58: 46599 | K58: TRUE | L58: 4 | M58: =E58*G58 -> 42700 | N58: =E58*H58 -> 49000 | O58: =IF(H58=0,"",(H58-G58)/H58) -> 0.12857143 | P58: =IF(J58="","",J58-README!$C$4) -> 277 | Q58: =IF(E58=0,"Out of stock",IF(E58<=F58,"Low stock","OK")) -> OK | R58: =IF(J58="","No expiry",IF(P58<0,"Expired",IF(P58<=30,"Expiring <=30 days","OK"))) -> OK
... A106: INV-00105 | B106: ST-AMS-TEG | C106: P075-500G | D106: Rat Bait Blocks - 500 g pack | E106: 43 | F106: 8 | G106: 6700 | H106: 8000 | I106: TEG-P075500G-2704 | J106: 46854 | K106: TRUE | L106: 30 | M106: =E106*G106 -> 288100 | N106: =E106*H106 -> 344000 | O106: =IF(H106=0,"",(H106-G106)/H106) -> 0.1625 | P106: =IF(J106="","",J106-README!$C$4) -> 532 | Q106: =IF(E106=0,"Out of stock",IF(E106<=F106,"Low stock","OK")) -> OK | R106: =IF(J106="","No expiry",IF(P106<0,"Expired",IF(P106<=30,"Expiring <=30 days","OK"))) -> OK
A107: INV-00106 | B107: ST-AMS-TEG | C107: P076-4L | D107: Chick Drinker - 4 L piece | E107: 15 | F107: 4 | G107: 4300 | H107: 5000 | K107: TRUE | L107: 10 | M107: =E107*G107 -> 64500 | N107: =E107*H107 -> 75000 | O107: =IF(H107=0,"",(H107-G107)/H107) -> 0.14 | P107: =IF(J107="","",J107-README!$C$4) | Q107: =IF(E107=0,"Out of stock",IF(E107<=F107,"Low stock","OK")) -> OK | R107: =IF(J107="","No expiry",IF(P107<0,"Expired",IF(P107<=30,"Expiring <=30 days","OK"))) -> No expiry
A108: INV-00107 | B108: ST-AMS-TEG | C108: P077-10L | D108: Poultry Drinker - 10 L piece | E108: 11 | F108: 4 | G108: 7600 | H108: 9000 | K108: TRUE | L108: 7 | M108: =E108*G108 -> 83600 | N108: =E108*H108 -> 99000 | O108: =IF(H108=0,"",(H108-G108)/H108) -> 0.15555556 | P108: =IF(J108="","",J108-README!$C$4) | Q108: =IF(E108=0,"Out of stock",IF(E108<=F108,"Low stock","OK")) -> OK | R108: =IF(J108="","No expiry",IF(P108<0,"Expired",IF(P108<=30,"Expiring <=30 days","OK"))) -> No expiry
A109: INV-00108 | B109: ST-AMS-TEG | C109: P078-10KG | D109: Hanging Poultry Feeder - 10 kg piece | E109: 23 | F109: 4 | G109: 10400 | H109: 12000 | K109: TRUE | L109: 16 | M109: =E109*G109 -> 239200 | N109: =E109*H109 -> 276000 | O109: =IF(H109=0,"",(H109-G109)/H109) -> 0.13333333 | P109: =IF(J109="","",J109-README!$C$4) | Q109: =IF(E109=0,"Out of stock",IF(E109<=F109,"Low stock","OK")) -> OK | R109: =IF(J109="","No expiry",IF(P109<0,"Expired",IF(P109<=30,"Expiring <=30 days","OK"))) -> No expiry
A110: INV-00109 | B110: ST-AMS-TEG | C110: P079-1PC | D110: Chick Feeder Tray | E110: 9 | F110: 4 | G110: 2400 | H110: 3000 | K110: TRUE | L110: 6 | M110: =E110*G110 -> 21600 | N110: =E110*H110 -> 27000 | O110: =IF(H110=0,"",(H110-G110)/H110) -> 0.2 | P110: =IF(J110="","",J110-README!$C$4) | Q110: =IF(E110=0,"Out of stock",IF(E110<=F110,"Low stock","OK")) -> OK | R110: =IF(J110="","No expiry",IF(P110<0,"Expired",IF(P110<=30,"Expiring <=30 days","OK"))) -> No expiry
A111: INV-00110 | B111: ST-AMS-TEG | C111: P080-1PC | D111: Nipple Drinker Line Kit | E111: 4 | F111: 1 | G111: 28800 | H111: 35000 | K111: TRUE | L111: 2 | M111: =E111*G111 -> 115200 | N111: =E111*H111 -> 140000 | O111: =IF(H111=0,"",(H111-G111)/H111) -> 0.17714286 | P111: =IF(J111="","",J111-README!$C$4) | Q111: =IF(E111=0,"Out of stock",IF(E111<=F111,"Low stock","OK")) -> OK | R111: =IF(J111="","No expiry",IF(P111<0,"Expired",IF(P111<=30,"Expiring <=30 days","OK"))) -> No expiry
A112: INV-00111 | B112: ST-AMS-TEG | C112: P081-1PC | D112: Pig Feeding Trough | E112: 12 | F112: 4 | G112: 20300 | H112: 25000 | K112: TRUE | L112: 8 | M112: =E112*G112 -> 243600 | N112: =E112*H112 -> 300000 | O112: =IF(H112=0,"",(H112-G112)/H112) -> 0.188 | P112: =IF(J112="","",J112-README!$C$4) | Q112: =IF(E112=0,"Out of stock",IF(E112<=F112,"Low stock","OK")) -> OK | R112: =IF(J112="","No expiry",IF(P112<0,"Expired",IF(P112<=30,"Expiring <=30 days","OK"))) -> No expiry
A113: INV-00112 | B113: ST-AMS-TEG | C113: P082-1PC | D113: Infrared Brooder Bulb 250W | E113: 21 | F113: 4 | G113: 15700 | H113: 18000 | K113: TRUE | L113: 14 | M113: =E113*G113 -> 329700 | N113: =E113*H113 -> 378000 | O113: =IF(H113=0,"",(H113-G113)/H113) -> 0.12777778 | P113: =IF(J113="","",J113-README!$C$4) | Q113: =IF(E113=0,"Out of stock",IF(E113<=F113,"Low stock","OK")) -> OK | R113: =IF(J113="","No expiry",IF(P113<0,"Expired",IF(P113<=30,"Expiring <=30 days","OK"))) -> No expiry
A114: INV-00113 | B114: ST-AMS-TEG | C114: P083-1PC | D114: Charcoal Brooder | E114: 17 | F114: 4 | G114: 31300 | H114: 35000 | K114: TRUE | L114: 11 | M114: =E114*G114 -> 532100 | N114: =E114*H114 -> 595000 | O114: =IF(H114=0,"",(H114-G114)/H114) -> 0.10571429 | P114: =IF(J114="","",J114-README!$C$4) | Q114: =IF(E114=0,"Out of stock",IF(E114<=F114,"Low stock","OK")) -> OK | R114: =IF(J114="","No expiry",IF(P114<0,"Expired",IF(P114<=30,"Expiring <=30 days","OK"))) -> No expiry
A115: INV-00114 | B115: ST-AMS-TEG | C115: P084-1PC | D115: Layer Battery Cage (96 birds) | E115: 4 | F115: 1 | G115: 551300 | H115: 650000 | K115: TRUE | L115: 2 | M115: =E115*G115 -> 2205200 | N115: =E115*H115 -> 2600000 | O115: =IF(H115=0,"",(H115-G115)/H115) -> 0.15184615 | P115: =IF(J115="","",J115-README!$C$4) | Q115: =IF(E115=0,"Out of stock",IF(E115<=F115,"Low stock","OK")) -> OK | R115: =IF(J115="","No expiry",IF(P115<0,"Expired",IF(P115<=30,"Expiring <=30 days","OK"))) -> No expiry
A116: INV-00115 | B116: ST-AMS-TEG | C116: P085-1PC | D116: Laying Nest Box (10 holes) | E116: 20 | F116: 4 | G116: 161100 | H116: 180000 | K116: FALSE | L116: 0 | M116: =E116*G116 -> 3222000 | N116: =E116*H116 -> 3600000 | O116: =IF(H116=0,"",(H116-G116)/H116) -> 0.105 | P116: =IF(J116="","",J116-README!$C$4) | Q116: =IF(E116=0,"Out of stock",IF(E116<=F116,"Low stock","OK")) -> OK | R116: =IF(J116="","No expiry",IF(P116<0,"Expired",IF(P116<=30,"Expiring <=30 days","OK"))) -> No expiry
A117: INV-00116 | B117: ST-AMS-TEG | C117: P086-1PC | D117: Egg Incubator 64 Eggs | E117: 4 | F117: 1 | G117: 329900 | H117: 380000 | K117: TRUE | L117: 2 | M117: =E117*G117 -> 1319600 | N117: =E117*H117 -> 1520000 | O117: =IF(H117=0,"",(H117-G117)/H117) -> 0.13184211 | P117: =IF(J117="","",J117-README!$C$4) | Q117: =IF(E117=0,"Out of stock",IF(E117<=F117,"Low stock","OK")) -> OK | R117: =IF(J117="","No expiry",IF(P117<0,"Expired",IF(P117<=30,"Expiring <=30 days","OK"))) -> No expiry
A118: INV-00117 | B118: ST-AMS-TEG | C118: P087-1PC | D118: Egg Incubator 528 Eggs | E118: 7 | F118: 1 | G118: 1716200 | H118: 1950000 | K118: TRUE | L118: 4 | M118: =E118*G118 -> 12013400 | N118: =E118*H118 -> 13650000 | O118: =IF(H118=0,"",(H118-G118)/H118) -> 0.11989744 | P118: =IF(J118="","",J118-README!$C$4) | Q118: =IF(E118=0,"Out of stock",IF(E118<=F118,"Low stock","OK")) -> OK | R118: =IF(J118="","No expiry",IF(P118<0,"Expired",IF(P118<=30,"Expiring <=30 days","OK"))) -> No expiry
... A126: INV-00125 | B126: ST-AMS-TEG | C126: P112-1B | D126: Point-of-Lay Pullets (per bird) | E126: 92 | F126: 18 | G126: 12800 | H126: 14000 | K126: TRUE | L126: 64 | M126: =E126*G126 -> 1177600 | N126: =E126*H126 -> 1288000 | O126: =IF(H126=0,"",(H126-G126)/H126) -> 0.085714286 | P126: =IF(J126="","",J126-README!$C$4) | Q126: =IF(E126=0,"Out of stock",IF(E126<=F126,"Low stock","OK")) -> OK | R126: =IF(J126="","No expiry",IF(P126<0,"Expired",IF(P126<=30,"Expiring <=30 days","OK"))) -> No expiry
A127: INV-00126 | B127: ST-AMS-PST | C127: P022-1KG | D127: Broiler Premix 2.5% - 1 kg pack | E127: 22 | F127: 8 | G127: 7900 | H127: 9300 | I127: PST-P0221KG-2606 | J127: 46557 | K127: TRUE | L127: 15 | M127: =E127*G127 -> 173800 | N127: =E127*H127 -> 204600 | O127: =IF(H127=0,"",(H127-G127)/H127) -> 0.15053763 | P127: =IF(J127="","",J127-README!$C$4) -> 235 | Q127: =IF(E127=0,"Out of stock",IF(E127<=F127,"Low stock","OK")) -> OK | R127: =IF(J127="","No expiry",IF(P127<0,"Expired",IF(P127<=30,"Expiring <=30 days","OK"))) -> OK
A128: INV-00127 | B128: ST-AMS-PST | C128: P024-1KG | D128: Pig Premix 2.5% - 1 kg pack | E128: 19 | F128: 8 | G128: 7100 | H128: 8800 | I128: PST-P0241KG-2607 | J128: 46584 | K128: FALSE | L128: 0 | M128: =E128*G128 -> 134900 | N128: =E128*H128 -> 167200 | O128: =IF(H128=0,"",(H128-G128)/H128) -> 0.19318182 | P128: =IF(J128="","",J128-README!$C$4) -> 262 | Q128: =IF(E128=0,"Out of stock",IF(E128<=F128,"Low stock","OK")) -> OK | R128: =IF(J128="","No expiry",IF(P128<0,"Expired",IF(P128<=30,"Expiring <=30 days","OK"))) -> OK
A129: INV-00128 | B129: ST-AMS-PST | C129: P034-100G | D129: Vitamix Chick - 100 g sachet | E129: 52 | F129: 28 | G129: 3500 | H129: 4100 | I129: PST-P034100G-2609 | J129: 46636 | K129: FALSE | L129: 0 | M129: =E129*G129 -> 182000 | N129: =E129*H129 -> 213200 | O129: =IF(H129=0,"",(H129-G129)/H129) -> 0.14634146 | P129: =IF(J129="","",J129-README!$C$4) -> 314 | Q129: =IF(E129=0,"Out of stock",IF(E129<=F129,"Low stock","OK")) -> OK | R129: =IF(J129="","No expiry",IF(P129<0,"Expired",IF(P129<=30,"Expiring <=30 days","OK"))) -> OK
A130: INV-00129 | B130: ST-AMS-PST | C130: P034-250G | D130: Vitamix Chick - 250 g sachet | E130: 80 | F130: 28 | G130: 8300 | H130: 9300 | I130: PST-P034250G-2705 | J130: 46882 | K130: TRUE | L130: 56 | M130: =E130*G130 -> 664000 | N130: =E130*H130 -> 744000 | O130: =IF(H130=0,"",(H130-G130)/H130) -> 0.10752688 | P130: =IF(J130="","",J130-README!$C$4) -> 560 | Q130: =IF(E130=0,"Out of stock",IF(E130<=F130,"Low stock","OK")) -> OK | R130: =IF(J130="","No expiry",IF(P130<0,"Expired",IF(P130<=30,"Expiring <=30 days","OK"))) -> OK
A131: INV-00130 | B131: ST-AMS-PST | C131: P034-30G | D131: Vitamix Chick - 30 g sachet | E131: 98 | F131: 28 | G131: 1200 | H131: 1500 | I131: PST-P03430G-2611 | J131: 46692 | K131: TRUE | L131: 68 | M131: =E131*G131 -> 117600 | N131: =E131*H131 -> 147000 | O131: =IF(H131=0,"",(H131-G131)/H131) -> 0.2 | P131: =IF(J131="","",J131-README!$C$4) -> 370 | Q131: =IF(E131=0,"Out of stock",IF(E131<=F131,"Low stock","OK")) -> OK | R131: =IF(J131="","No expiry",IF(P131<0,"Expired",IF(P131<=30,"Expiring <=30 days","OK"))) -> OK
A132: INV-00131 | B132: ST-AMS-PST | C132: P035-100G | D132: Vitamix Plus - 100 g sachet | E132: 32 | F132: 28 | G132: 4100 | H132: 4600 | I132: PST-P035100G-2605 | J132: 46526 | K132: TRUE | L132: 22 | M132: =E132*G132 -> 131200 | N132: =E132*H132 -> 147200 | O132: =IF(H132=0,"",(H132-G132)/H132) -> 0.10869565 | P132: =IF(J132="","",J132-README!$C$4) -> 204 | Q132: =IF(E132=0,"Out of stock",IF(E132<=F132,"Low stock","OK")) -> OK | R132: =IF(J132="","No expiry",IF(P132<0,"Expired",IF(P132<=30,"Expiring <=30 days","OK"))) -> OK
A133: INV-00132 | B133: ST-AMS-PST | C133: P035-250G | D133: Vitamix Plus - 250 g sachet | E133: 33 | F133: 28 | G133: 9000 | H133: 10500 | I133: PST-P035250G-2607 | J133: 46590 | K133: TRUE | L133: 23 | M133: =E133*G133 -> 297000 | N133: =E133*H133 -> 346500 | O133: =IF(H133=0,"",(H133-G133)/H133) -> 0.14285714 | P133: =IF(J133="","",J133-README!$C$4) -> 268 | Q133: =IF(E133=0,"Out of stock",IF(E133<=F133,"Low stock","OK")) -> OK | R133: =IF(J133="","No expiry",IF(P133<0,"Expired",IF(P133<=30,"Expiring <=30 days","OK"))) -> OK
A134: INV-00133 | B134: ST-AMS-PST | C134: P035-30G | D134: Vitamix Plus - 30 g sachet | E134: 30 | F134: 28 | G134: 1300 | H134: 1500 | I134: PST-P03530G-2704 | J134: 46859 | K134: TRUE | L134: 21 | M134: =E134*G134 -> 39000 | N134: =E134*H134 -> 45000 | O134: =IF(H134=0,"",(H134-G134)/H134) -> 0.13333333 | P134: =IF(J134="","",J134-README!$C$4) -> 537 | Q134: =IF(E134=0,"Out of stock",IF(E134<=F134,"Low stock","OK")) -> OK | R134: =IF(J134="","No expiry",IF(P134<0,"Expired",IF(P134<=30,"Expiring <=30 days","OK"))) -> OK
A135: INV-00134 | B135: ST-AMS-PST | C135: P036-100G | D135: Multivitamin Soluble Powder - 100 g sachet | E135: 67 | F135: 28 | G135: 3300 | H135: 4100 | I135: PST-P036100G-2706 | J135: 46927 | K135: TRUE | L135: 46 | M135: =E135*G135 -> 221100 | N135: =E135*H135 -> 274700 | O135: =IF(H135=0,"",(H135-G135)/H135) -> 0.19512195 | P135: =IF(J135="","",J135-README!$C$4) -> 605 | Q135: =IF(E135=0,"Out of stock",IF(E135<=F135,"Low stock","OK")) -> OK | R135: =IF(J135="","No expiry",IF(P135<0,"Expired",IF(P135<=30,"Expiring <=30 days","OK"))) -> OK
A136: INV-00135 | B136: ST-AMS-PST | C136: P036-1KG | D136: Multivitamin Soluble Powder - 1 kg tin | E136: 5 | F136: 3 | G136: 26000 | H136: 31000 | I136: PST-P0361KG-2607 | J136: 46588 | K136: FALSE | L136: 0 | M136: =E136*G136 -> 130000 | N136: =E136*H136 -> 155000 | O136: =IF(H136=0,"",(H136-G136)/H136) -> 0.16129032 | P136: =IF(J136="","",J136-README!$C$4) -> 266 | Q136: =IF(E136=0,"Out of stock",IF(E136<=F136,"Low stock","OK")) -> OK | R136: =IF(J136="","No expiry",IF(P136<0,"Expired",IF(P136<=30,"Expiring <=30 days","OK"))) -> OK
A137: INV-00136 | B137: ST-AMS-PST | C137: P037-100ML | D137: Vitamin AD3E Injectable - 100 ml bottle | E137: 26 | F137: 8 | G137: 11200 | H137: 12500 | I137: PST-P037100ML-2701 | J137: 46782 | K137: TRUE | L137: 18 | M137: =E137*G137 -> 291200 | N137: =E137*H137 -> 325000 | O137: =IF(H137=0,"",(H137-G137)/H137) -> 0.104 | P137: =IF(J137="","",J137-README!$C$4) -> 460 | Q137: =IF(E137=0,"Out of stock",IF(E137<=F137,"Low stock","OK")) -> OK | R137: =IF(J137="","No expiry",IF(P137<0,"Expired",IF(P137<=30,"Expiring <=30 days","OK"))) -> OK
A138: INV-00137 | B138: ST-AMS-PST | C138: P038-1L | D138: Layer Tonic (Egg Booster) - 1 L bottle | E138: 22 | F138: 8 | G138: 23300 | H138: 29000 | I138: PST-P0381L-2706 | J138: 46916 | K138: TRUE | L138: 15 | M138: =E138*G138 -> 512600 | N138: =E138*H138 -> 638000 | O138: =IF(H138=0,"",(H138-G138)/H138) -> 0.19655172 | P138: =IF(J138="","",J138-README!$C$4) -> 594 | Q138: =IF(E138=0,"Out of stock",IF(E138<=F138,"Low stock","OK")) -> OK | R138: =IF(J138="","No expiry",IF(P138<0,"Expired",IF(P138<=30,"Expiring <=30 days","OK"))) -> OK
... A140: INV-00139 | B140: ST-AMS-PST | C140: P039-100G | D140: Clear Heat Electrolyte - 100 g sachet | E140: 64 | F140: 28 | G140: 3000 | H140: 3600 | I140: PST-P039100G-2708 | J140: 46994 | K140: FALSE | L140: 0 | M140: =E140*G140 -> 192000 | N140: =E140*H140 -> 230400 | O140: =IF(H140=0,"",(H140-G140)/H140) -> 0.16666667 | P140: =IF(J140="","",J140-README!$C$4) -> 672 | Q140: =IF(E140=0,"Out of stock",IF(E140<=F140,"Low stock","OK")) -> OK | R140: =IF(J140="","No expiry",IF(P140<0,"Expired",IF(P140<=30,"Expiring <=30 days","OK"))) -> OK
A141: INV-00140 | B141: ST-AMS-PST | C141: P039-250G | D141: Clear Heat Electrolyte - 250 g sachet | E141: 0 | F141: 28 | G141: 7400 | H141: 8200 | I141: PST-P039250G-2701 | J141: 46781 | K141: TRUE | L141: 0 | M141: =E141*G141 -> 0 | N141: =E141*H141 -> 0 | O141: =IF(H141=0,"",(H141-G141)/H141) -> 0.097560976 | P141: =IF(J141="","",J141-README!$C$4) -> 459 | Q141: =IF(E141=0,"Out of stock",IF(E141<=F141,"Low stock","OK")) -> Out of stock | R141: =IF(J141="","No expiry",IF(P141<0,"Expired",IF(P141<=30,"Expiring <=30 days","OK"))) -> OK | S141: Out of stock
A142: INV-00141 | B142: ST-AMS-PST | C142: P039-30G | D142: Clear Heat Electrolyte - 30 g sachet | E142: 62 | F142: 28 | G142: 1000 | H142: 1200 | I142: PST-P03930G-2609 | J142: 46638 | K142: TRUE | L142: 43 | M142: =E142*G142 -> 62000 | N142: =E142*H142 -> 74400 | O142: =IF(H142=0,"",(H142-G142)/H142) -> 0.16666667 | P142: =IF(J142="","",J142-README!$C$4) -> 316 | Q142: =IF(E142=0,"Out of stock",IF(E142<=F142,"Low stock","OK")) -> OK | R142: =IF(J142="","No expiry",IF(P142<0,"Expired",IF(P142<=30,"Expiring <=30 days","OK"))) -> OK
A143: INV-00142 | B143: ST-AMS-PST | C143: P040-100G | D143: Livestock Oral Rehydration Salts - 100 g sachet | E143: 98 | F143: 28 | G143: 2800 | H143: 3100 | I143: PST-P040100G-2708 | J143: 46990 | K143: TRUE | L143: 68 | M143: =E143*G143 -> 274400 | N143: =E143*H143 -> 303800 | O143: =IF(H143=0,"",(H143-G143)/H143) -> 0.096774194 | P143: =IF(J143="","",J143-README!$C$4) -> 668 | Q143: =IF(E143=0,"Out of stock",IF(E143<=F143,"Low stock","OK")) -> OK | R143: =IF(J143="","No expiry",IF(P143<0,"Expired",IF(P143<=30,"Expiring <=30 days","OK"))) -> OK
A144: INV-00143 | B144: ST-AMS-PST | C144: P041-2KG | D144: Goat & Sheep Mineral Lick - 2 kg piece | E144: 12 | F144: 4 | G144: 6200 | H144: 7200 | I144: PST-P0412KG-2609 | J144: 46643 | K144: TRUE | L144: 8 | M144: =E144*G144 -> 74400 | N144: =E144*H144 -> 86400 | O144: =IF(H144=0,"",(H144-G144)/H144) -> 0.13888889 | P144: =IF(J144="","",J144-README!$C$4) -> 321 | Q144: =IF(E144=0,"Out of stock",IF(E144<=F144,"Low stock","OK")) -> OK | R144: =IF(J144="","No expiry",IF(P144<0,"Expired",IF(P144<=30,"Expiring <=30 days","OK"))) -> OK
A145: INV-00144 | B145: ST-AMS-PST | C145: P043-20KG | D145: Dairy Mineral Mix - 20 kg bag | E145: 35 | F145: 11 | G145: 86300 | H145: 98000 | I145: PST-P04320KG-2701 | J145: 46757 | K145: TRUE | L145: 24 | M145: =E145*G145 -> 3020500 | N145: =E145*H145 -> 3430000 | O145: =IF(H145=0,"",(H145-G145)/H145) -> 0.11938776 | P145: =IF(J145="","",J145-README!$C$4) -> 435 | Q145: =IF(E145=0,"Out of stock",IF(E145<=F145,"Low stock","OK")) -> OK | R145: =IF(J145="","No expiry",IF(P145<0,"Expired",IF(P145<=30,"Expiring <=30 days","OK"))) -> OK
A146: INV-00145 | B146: ST-AMS-PST | C146: P043-2KG | D146: Dairy Mineral Mix - 2 kg pack | E146: 10 | F146: 8 | G146: 10600 | H146: 12500 | I146: PST-P0432KG-2701 | J146: 46771 | K146: TRUE | L146: 7 | M146: =E146*G146 -> 106000 | N146: =E146*H146 -> 125000 | O146: =IF(H146=0,"",(H146-G146)/H146) -> 0.152 | P146: =IF(J146="","",J146-README!$C$4) -> 449 | Q146: =IF(E146=0,"Out of stock",IF(E146<=F146,"Low stock","OK")) -> OK | R146: =IF(J146="","No expiry",IF(P146<0,"Expired",IF(P146<=30,"Expiring <=30 days","OK"))) -> OK
A147: INV-00146 | B147: ST-AMS-PST | C147: P044-100G | D147: Poultry Probiotic - 100 g sachet | E147: 35 | F147: 28 | G147: 5500 | H147: 6200 | I147: PST-P044100G-2701 | J147: 46770 | K147: TRUE | L147: 24 | M147: =E147*G147 -> 192500 | N147: =E147*H147 -> 217000 | O147: =IF(H147=0,"",(H147-G147)/H147) -> 0.11290323 | P147: =IF(J147="","",J147-README!$C$4) -> 448 | Q147: =IF(E147=0,"Out of stock",IF(E147<=F147,"Low stock","OK")) -> OK | R147: =IF(J147="","No expiry",IF(P147<0,"Expired",IF(P147<=30,"Expiring <=30 days","OK"))) -> OK
A148: INV-00147 | B148: ST-AMS-PST | C148: P044-500G | D148: Poultry Probiotic - 500 g pack | E148: 26 | F148: 8 | G148: 21800 | H148: 26000 | I148: PST-P044500G-2607 | J148: 46589 | K148: TRUE | L148: 18 | M148: =E148*G148 -> 566800 | N148: =E148*H148 -> 676000 | O148: =IF(H148=0,"",(H148-G148)/H148) -> 0.16153846 | P148: =IF(J148="","",J148-README!$C$4) -> 267 | Q148: =IF(E148=0,"Out of stock",IF(E148<=F148,"Low stock","OK")) -> OK | R148: =IF(J148="","No expiry",IF(P148<0,"Expired",IF(P148<=30,"Expiring <=30 days","OK"))) -> OK
A149: INV-00148 | B149: ST-AMS-PST | C149: P045-1KG | D149: Phytase Feed Enzyme - 1 kg pack | E149: 16 | F149: 8 | G149: 28800 | H149: 36000 | I149: PST-P0451KG-2608 | J149: 46605 | K149: FALSE | L149: 0 | M149: =E149*G149 -> 460800 | N149: =E149*H149 -> 576000 | O149: =IF(H149=0,"",(H149-G149)/H149) -> 0.2 | P149: =IF(J149="","",J149-README!$C$4) -> 283 | Q149: =IF(E149=0,"Out of stock",IF(E149<=F149,"Low stock","OK")) -> OK | R149: =IF(J149="","No expiry",IF(P149<0,"Expired",IF(P149<=30,"Expiring <=30 days","OK"))) -> OK
A150: INV-00149 | B150: ST-AMS-PST | C150: P046-1KG | D150: Mycotoxin Binder - 1 kg pack | E150: 15 | F150: 8 | G150: 10100 | H150: 12500 | I150: PST-P0461KG-2612 | J150: 46725 | K150: TRUE | L150: 10 | M150: =E150*G150 -> 151500 | N150: =E150*H150 -> 187500 | O150: =IF(H150=0,"",(H150-G150)/H150) -> 0.192 | P150: =IF(J150="","",J150-README!$C$4) -> 403 | Q150: =IF(E150=0,"Out of stock",IF(E150<=F150,"Low stock","OK")) -> OK | R150: =IF(J150="","No expiry",IF(P150<0,"Expired",IF(P150<=30,"Expiring <=30 days","OK"))) -> OK
A151: INV-00150 | B151: ST-AMS-PST | C151: P046-25KG | D151: Mycotoxin Binder - 25 kg bag | E151: 19 | F151: 11 | G151: 213500 | H151: 257500 | I151: PST-P04625KG-2708 | J151: 46977 | K151: TRUE | L151: 13 | M151: =E151*G151 -> 4056500 | N151: =E151*H151 -> 4892500 | O151: =IF(H151=0,"",(H151-G151)/H151) -> 0.17087379 | P151: =IF(J151="","",J151-README!$C$4) -> 655 | Q151: =IF(E151=0,"Out of stock",IF(E151<=F151,"Low stock","OK")) -> OK | R151: =IF(J151="","No expiry",IF(P151<0,"Expired",IF(P151<=30,"Expiring <=30 days","OK"))) -> OK
A152: INV-00151 | B152: ST-AMS-PST | C152: P047-1L | D152: Liver Tonic & Amino Acids - 1 L bottle | E152: 24 | F152: 8 | G152: 21800 | H152: 27000 | I152: PST-P0471L-2606 | J152: 46559 | K152: TRUE | L152: 16 | M152: =E152*G152 -> 523200 | N152: =E152*H152 -> 648000 | O152: =IF(H152=0,"",(H152-G152)/H152) -> 0.19259259 | P152: =IF(J152="","",J152-README!$C$4) -> 237 | Q152: =IF(E152=0,"Out of stock",IF(E152<=F152,"Low stock","OK")) -> OK | R152: =IF(J152="","No expiry",IF(P152<0,"Expired",IF(P152<=30,"Expiring <=30 days","OK"))) -> OK
A153: INV-00152 | B153: ST-AMS-PST | C153: P047-500ML | D153: Liver Tonic & Amino Acids - 500 ml bottle | E153: 13 | F153: 8 | G153: 12000 | H153: 14500 | I153: PST-P047500ML-2609 | J153: 46638 | K153: TRUE | L153: 9 | M153: =E153*G153 -> 156000 | N153: =E153*H153 -> 188500 | O153: =IF(H153=0,"",(H153-G153)/H153) -> 0.17241379 | P153: =IF(J153="","",J153-README!$C$4) -> 316 | Q153: =IF(E153=0,"Out of stock",IF(E153<=F153,"Low stock","OK")) -> OK | R153: =IF(J153="","No expiry",IF(P153<0,"Expired",IF(P153<=30,"Expiring <=30 days","OK"))) -> OK
A154: INV-00153 | B154: ST-AMS-PST | C154: P048-100ML | D154: Oxytetracycline 20% LA Injection - 100 ml bottle | E154: 10 | F154: 5 | G154: 10600 | H154: 12500 | I154: PST-P048100ML-2601 | J154: 46662 | K154: TRUE | L154: 7 | M154: =E154*G154 -> 106000 | N154: =E154*H154 -> 125000 | O154: =IF(H154=0,"",(H154-G154)/H154) -> 0.152 | P154: =IF(J154="","",J154-README!$C$4) -> 340 | Q154: =IF(E154=0,"Out of stock",IF(E154<=F154,"Low stock","OK")) -> OK | R154: =IF(J154="","No expiry",IF(P154<0,"Expired",IF(P154<=30,"Expiring <=30 days","OK"))) -> OK | S154: Prescription item listed online - test Rx checkout
A155: INV-00154 | B155: ST-AMS-PST | C155: P048-50ML | D155: Oxytetracycline 20% LA Injection - 50 ml bottle | E155: 23 | F155: 8 | G155: 6200 | H155: 7200 | I155: PST-P04850ML-2709 | J155: 47004 | K155: TRUE | L155: 16 | M155: =E155*G155 -> 142600 | N155: =E155*H155 -> 165600 | O155: =IF(H155=0,"",(H155-G155)/H155) -> 0.13888889 | P155: =IF(J155="","",J155-README!$C$4) -> 682 | Q155: =IF(E155=0,"Out of stock",IF(E155<=F155,"Low stock","OK")) -> OK | R155: =IF(J155="","No expiry",IF(P155<0,"Expired",IF(P155<=30,"Expiring <=30 days","OK"))) -> OK
A156: INV-00155 | B156: ST-AMS-PST | C156: P049-100G | D156: Oxytetracycline Soluble Powder - 100 g sachet | E156: 31 | F156: 28 | G156: 4300 | H156: 5200 | I156: PST-P049100G-2605 | J156: 46517 | K156: TRUE | L156: 21 | M156: =E156*G156 -> 133300 | N156: =E156*H156 -> 161200 | O156: =IF(H156=0,"",(H156-G156)/H156) -> 0.17307692 | P156: =IF(J156="","",J156-README!$C$4) -> 195 | Q156: =IF(E156=0,"Out of stock",IF(E156<=F156,"Low stock","OK")) -> OK | R156: =IF(J156="","No expiry",IF(P156<0,"Expired",IF(P156<=30,"Expiring <=30 days","OK"))) -> OK
A157: INV-00156 | B157: ST-AMS-PST | C157: P051-100ML | D157: Penicillin-Streptomycin Injection - 100 ml bottle | E157: 13 | F157: 8 | G157: 12600 | H157: 14500 | I157: PST-P051100ML-2604 | J157: 46478 | K157: TRUE | L157: 9 | M157: =E157*G157 -> 163800 | N157: =E157*H157 -> 188500 | O157: =IF(H157=0,"",(H157-G157)/H157) -> 0.13103448 | P157: =IF(J157="","",J157-README!$C$4) -> 156 | Q157: =IF(E157=0,"Out of stock",IF(E157<=F157,"Low stock","OK")) -> OK | R157: =IF(J157="","No expiry",IF(P157<0,"Expired",IF(P157<=30,"Expiring <=30 days","OK"))) -> OK
A158: INV-00157 | B158: ST-AMS-PST | C158: P052-1L | D158: Albendazole 10% Oral Suspension - 1 L bottle | E158: 11 | F158: 8 | G158: 23700 | H158: 29000 | I158: PST-P0521L-2702 | J158: 46787 | K158: TRUE | L158: 7 | M158: =E158*G158 -> 260700 | N158: =E158*H158 -> 319000 | O158: =IF(H158=0,"",(H158-G158)/H158) -> 0.18275862 | P158: =IF(J158="","",J158-README!$C$4) -> 465 | Q158: =IF(E158=0,"Out of stock",IF(E158<=F158,"Low stock","OK")) -> OK | R158: =IF(J158="","No expiry",IF(P158<0,"Expired",IF(P158<=30,"Expiring <=30 days","OK"))) -> OK
A159: INV-00158 | B159: ST-AMS-PST | C159: P052-500ML | D159: Albendazole 10% Oral Suspension - 500 ml bottle | E159: 19 | F159: 8 | G159: 14400 | H159: 16500 | I159: PST-P052500ML-2706 | J159: 46930 | K159: TRUE | L159: 13 | M159: =E159*G159 -> 273600 | N159: =E159*H159 -> 313500 | O159: =IF(H159=0,"",(H159-G159)/H159) -> 0.12727273 | P159: =IF(J159="","",J159-README!$C$4) -> 608 | Q159: =IF(E159=0,"Out of stock",IF(E159<=F159,"Low stock","OK")) -> OK | R159: =IF(J159="","No expiry",IF(P159<0,"Expired",IF(P159<=30,"Expiring <=30 days","OK"))) -> OK
A160: INV-00159 | B160: ST-AMS-PST | C160: P053-100G | D160: Piperazine Soluble Powder - 100 g sachet | E160: 31 | F160: 28 | G160: 3200 | H160: 3600 | I160: PST-P053100G-2703 | J160: 46835 | K160: TRUE | L160: 21 | M160: =E160*G160 -> 99200 | N160: =E160*H160 -> 111600 | O160: =IF(H160=0,"",(H160-G160)/H160) -> 0.11111111 | P160: =IF(J160="","",J160-README!$C$4) -> 513 | Q160: =IF(E160=0,"Out of stock",IF(E160<=F160,"Low stock","OK")) -> OK | R160: =IF(J160="","No expiry",IF(P160<0,"Expired",IF(P160<=30,"Expiring <=30 days","OK"))) -> OK
A161: INV-00160 | B161: ST-AMS-PST | C161: P054-500ML | D161: Levamisole Oral Drench - 500 ml bottle | E161: 11 | F161: 8 | G161: 12900 | H161: 14500 | I161: PST-P054500ML-2701 | J161: 46781 | K161: TRUE | L161: 7 | M161: =E161*G161 -> 141900 | N161: =E161*H161 -> 159500 | O161: =IF(H161=0,"",(H161-G161)/H161) -> 0.11034483 | P161: =IF(J161="","",J161-README!$C$4) -> 459 | Q161: =IF(E161=0,"Out of stock",IF(E161<=F161,"Low stock","OK")) -> OK | R161: =IF(J161="","No expiry",IF(P161<0,"Expired",IF(P161<=30,"Expiring <=30 days","OK"))) -> OK
A162: INV-00161 | B162: ST-AMS-PST | C162: P055-100ML | D162: Ivermectin 1% Injection - 100 ml bottle | E162: 17 | F162: 8 | G162: 11900 | H162: 14500 | I162: PST-P055100ML-2702 | J162: 46784 | K162: FALSE | L162: 0 | M162: =E162*G162 -> 202300 | N162: =E162*H162 -> 246500 | O162: =IF(H162=0,"",(H162-G162)/H162) -> 0.17931034 | P162: =IF(J162="","",J162-README!$C$4) -> 462 | Q162: =IF(E162=0,"Out of stock",IF(E162<=F162,"Low stock","OK")) -> OK | R162: =IF(J162="","No expiry",IF(P162<0,"Expired",IF(P162<=30,"Expiring <=30 days","OK"))) -> OK
A163: INV-00162 | B163: ST-AMS-PST | C163: P055-50ML | D163: Ivermectin 1% Injection - 50 ml bottle | E163: 10 | F163: 8 | G163: 6900 | H163: 8200 | I163: PST-P05550ML-2706 | J163: 46933 | K163: TRUE | L163: 7 | M163: =E163*G163 -> 69000 | N163: =E163*H163 -> 82000 | O163: =IF(H163=0,"",(H163-G163)/H163) -> 0.15853659 | P163: =IF(J163="","",J163-README!$C$4) -> 611 | Q163: =IF(E163=0,"Out of stock",IF(E163<=F163,"Low stock","OK")) -> OK | R163: =IF(J163="","No expiry",IF(P163<0,"Expired",IF(P163<=30,"Expiring <=30 days","OK"))) -> OK
A164: INV-00163 | B164: ST-AMS-PST | C164: P056-100G | D164: Amprolium 20% Soluble Powder - 100 g sachet | E164: 35 | F164: 28 | G164: 4400 | H164: 5200 | I164: PST-P056100G-2701 | J164: 46781 | K164: TRUE | L164: 24 | M164: =E164*G164 -> 154000 | N164: =E164*H164 -> 182000 | O164: =IF(H164=0,"",(H164-G164)/H164) -> 0.15384615 | P164: =IF(J164="","",J164-README!$C$4) -> 459 | Q164: =IF(E164=0,"Out of stock",IF(E164<=F164,"Low stock","OK")) -> OK | R164: =IF(J164="","No expiry",IF(P164<0,"Expired",IF(P164<=30,"Expiring <=30 days","OK"))) -> OK
A165: INV-00164 | B165: ST-AMS-PST | C165: P056-1KG | D165: Amprolium 20% Soluble Powder - 1 kg tin | E165: 5 | F165: 3 | G165: 33800 | H165: 39000 | I165: PST-P0561KG-2612 | J165: 46741 | K165: TRUE | L165: 3 | M165: =E165*G165 -> 169000 | N165: =E165*H165 -> 195000 | O165: =IF(H165=0,"",(H165-G165)/H165) -> 0.13333333 | P165: =IF(J165="","",J165-README!$C$4) -> 419 | Q165: =IF(E165=0,"Out of stock",IF(E165<=F165,"Low stock","OK")) -> OK | R165: =IF(J165="","No expiry",IF(P165<0,"Expired",IF(P165<=30,"Expiring <=30 days","OK"))) -> OK
A166: INV-00165 | B166: ST-AMS-PST | C166: P057-100ML | D166: Toltrazuril 2.5% Oral Solution - 100 ml bottle | E166: 24 | F166: 8 | G166: 11100 | H166: 12500 | I166: PST-P057100ML-2611 | J166: 46706 | K166: TRUE | L166: 16 | M166: =E166*G166 -> 266400 | N166: =E166*H166 -> 300000 | O166: =IF(H166=0,"",(H166-G166)/H166) -> 0.112 | P166: =IF(J166="","",J166-README!$C$4) -> 384 | Q166: =IF(E166=0,"Out of stock",IF(E166<=F166,"Low stock","OK")) -> OK | R166: =IF(J166="","No expiry",IF(P166<0,"Expired",IF(P166<=30,"Expiring <=30 days","OK"))) -> OK
...

Sheet Hatch_Schedule
A1: schedule_id | B1: sku | C1: product_name | D1: seller_id | E1: hatch_date | F1: order_cutoff_date | G1: price_per_chick_tzs | H1: capacity_chicks | I1: booked_chicks | J1: available_chicks | K1: status | L1: oda_commission_per_chick_tzs | M1: commission_on_booked_tzs | N1: booked_value_tzs | O1: test_scenario
A2: HS-0001 | B2: P109-1B | C2: Silverlands Broiler Day-old Chicks | D2: SEL-SIL | E2: 46317 | F2: 46314 | G2: 2250 | H2: 17000 | I2: 17000 | J2: =MAX(0,H2-I2) -> 0 | K2: =IF(E2<README!$C$4,"Past",IF(I2>=H2,"FULL",IF(F2<README!$C$4,"Closed","Open"))) -> Past | L2: 60 | M2: =I2*L2 -> 1020000 | N2: =I2*G2 -> 38250000 | O2: Past hatch date - keep for order history, hide from booking
A3: HS-0002 | B3: P101-1B | C3: Central Chicks (Animal Care) Broiler Day-old Chicks | D3: SEL-CENT | E3: 46323 | F3: 46320 | G3: 2000 | H3: 14000 | I3: 5600 | J3: =MAX(0,H3-I3) -> 8400 | K3: =IF(E3<README!$C$4,"Past",IF(I3>=H3,"FULL",IF(F3<README!$C$4,"Closed","Open"))) -> Closed | L3: 60 | M3: =I3*L3 -> 336000 | N3: =I3*G3 -> 11200000
A4: HS-0003 | B4: P109-1B | C4: Silverlands Broiler Day-old Chicks | D4: SEL-SIL | E4: 46323 | F4: 46320 | G4: 2250 | H4: 17000 | I4: 9850 | J4: =MAX(0,H4-I4) -> 7150 | K4: =IF(E4<README!$C$4,"Past",IF(I4>=H4,"FULL",IF(F4<README!$C$4,"Closed","Open"))) -> Closed | L4: 60 | M4: =I4*L4 -> 591000 | N4: =I4*G4 -> 22162500
A5: HS-0004 | B5: P096-1B | C5: Harsho Broiler Day-old Chicks | D5: SEL-HARS | E5: 46324 | F5: 46321 | G5: 2000 | H5: 9000 | I5: 1500 | J5: =MAX(0,H5-I5) -> 7500 | K5: =IF(E5<README!$C$4,"Past",IF(I5>=H5,"FULL",IF(F5<README!$C$4,"Closed","Open"))) -> Closed | L5: 60 | M5: =I5*L5 -> 90000 | N5: =I5*G5 -> 3000000 | O5: Cut-off passed - Closed although capacity remains
A6: HS-0005 | B6: P106-1B | C6: Interchick Broiler Day-old Chicks | D6: SEL-INTR | E6: 46324 | F6: 46321 | G6: 2200 | H6: 8500 | I6: 4400 | J6: =MAX(0,H6-I6) -> 4100 | K6: =IF(E6<README!$C$4,"Past",IF(I6>=H6,"FULL",IF(F6<README!$C$4,"Closed","Open"))) -> Closed | L6: 60 | M6: =I6*L6 -> 264000 | N6: =I6*G6 -> 9680000
A7: HS-0006 | B7: P108-1B | C7: Interchick Tanbro Day-old Chicks | D7: SEL-INTR | E7: 46324 | F7: 46321 | G7: 2100 | H7: 6000 | I7: 1800 | J7: =MAX(0,H7-I7) -> 4200 | K7: =IF(E7<README!$C$4,"Past",IF(I7>=H7,"FULL",IF(F7<README!$C$4,"Closed","Open"))) -> Closed | L7: 60 | M7: =I7*L7 -> 108000 | N7: =I7*G7 -> 3780000
A8: HS-0007 | B8: P098-1B | C8: Irvines Broiler Day-old Chicks | D8: SEL-IRVN | E8: 46324 | F8: 46321 | G8: 2150 | H8: 9000 | I8: 7950 | J8: =MAX(0,H8-I8) -> 1050 | K8: =IF(E8<README!$C$4,"Past",IF(I8>=H8,"FULL",IF(F8<README!$C$4,"Closed","Open"))) -> Closed | L8: 60 | M8: =I8*L8 -> 477000 | N8: =I8*G8 -> 17092500
A9: HS-0008 | B9: P102-1B | C9: Tanzania Poultry Farms Broiler Day-old Chicks | D9: SEL-TPF | E9: 46324 | F9: 46321 | G9: 2100 | H9: 8500 | I9: 2650 | J9: =MAX(0,H9-I9) -> 5850 | K9: =IF(E9<README!$C$4,"Past",IF(I9>=H9,"FULL",IF(F9<README!$C$4,"Closed","Open"))) -> Closed | L9: 60 | M9: =I9*L9 -> 159000 | N9: =I9*G9 -> 5565000
A10: HS-0009 | B10: P107-1B | C10: Interchick Layer Day-old Chicks | D10: SEL-INTR | E10: 46326 | F10: 46323 | G10: 3100 | H10: 6500 | I10: 1450 | J10: =MAX(0,H10-I10) -> 5050 | K10: =IF(E10<README!$C$4,"Past",IF(I10>=H10,"FULL",IF(F10<README!$C$4,"Closed","Open"))) -> Open | L10: 60 | M10: =I10*L10 -> 87000 | N10: =I10*G10 -> 4495000
A11: HS-0010 | B11: P105-1B | C11: Mkuza Chicks Layer Day-old Chicks | D11: SEL-MKUZ | E11: 46326 | F11: 46323 | G11: 2950 | H11: 4000 | I11: 1700 | J11: =MAX(0,H11-I11) -> 2300 | K11: =IF(E11<README!$C$4,"Past",IF(I11>=H11,"FULL",IF(F11<README!$C$4,"Closed","Open"))) -> Open | L11: 60 | M11: =I11*L11 -> 102000 | N11: =I11*G11 -> 5015000
A12: HS-0011 | B12: P099-1B | C12: Organia Broiler Day-old Chicks | D12: SEL-ORGN | E12: 46326 | F12: 46323 | G12: 2200 | H12: 16000 | I12: 10400 | J12: =MAX(0,H12-I12) -> 5600 | K12: =IF(E12<README!$C$4,"Past",IF(I12>=H12,"FULL",IF(F12<README!$C$4,"Closed","Open"))) -> Open | L12: 60 | M12: =I12*L12 -> 624000 | N12: =I12*G12 -> 22880000
A13: HS-0012 | B13: P100-1B | C13: Happy Chicks Broiler Day-old Chicks | D13: SEL-HAPP | E13: 46327 | F13: 46324 | G13: 2050 | H13: 16000 | I13: 13450 | J13: =MAX(0,H13-I13) -> 2550 | K13: =IF(E13<README!$C$4,"Past",IF(I13>=H13,"FULL",IF(F13<README!$C$4,"Closed","Open"))) -> Open | L13: 60 | M13: =I13*L13 -> 807000 | N13: =I13*G13 -> 27572500
A14: HS-0013 | B14: P096-1B | C14: Harsho Broiler Day-old Chicks | D14: SEL-HARS | E14: 46327 | F14: 46324 | G14: 2000 | H14: 9000 | I14: 1950 | J14: =MAX(0,H14-I14) -> 7050 | K14: =IF(E14<README!$C$4,"Past",IF(I14>=H14,"FULL",IF(F14<README!$C$4,"Closed","Open"))) -> Open | L14: 60 | M14: =I14*L14 -> 117000 | N14: =I14*G14 -> 3900000
A15: HS-0014 | B15: P103-1B | C15: Tanzania Poultry Farms Layer Day-old Chicks | D15: SEL-TPF | E15: 46327 | F15: 46324 | G15: 3000 | H15: 9500 | I15: 5550 | J15: =MAX(0,H15-I15) -> 3950 | K15: =IF(E15<README!$C$4,"Past",IF(I15>=H15,"FULL",IF(F15<README!$C$4,"Closed","Open"))) -> Open | L15: 60 | M15: =I15*L15 -> 333000 | N15: =I15*G15 -> 16650000
A16: HS-0015 | B16: P097-1B | C16: Backbone Broiler Day-old Chicks | D16: SEL-BACK | E16: 46328 | F16: 46325 | G16: 1950 | H16: 7500 | I16: 2800 | J16: =MAX(0,H16-I16) -> 4700 | K16: =IF(E16<README!$C$4,"Past",IF(I16>=H16,"FULL",IF(F16<README!$C$4,"Closed","Open"))) -> Open | L16: 60 | M16: =I16*L16 -> 168000 | N16: =I16*G16 -> 5460000
A17: HS-0016 | B17: P095-1B | C17: Kibo Broiler Day-old Chicks | D17: SEL-KIBO | E17: 46328 | F17: 46325 | G17: 2100 | H17: 16000 | I17: 16000 | J17: =MAX(0,H17-I17) -> 0 | K17: =IF(E17<README!$C$4,"Past",IF(I17>=H17,"FULL",IF(F17<README!$C$4,"Closed","Open"))) -> FULL | L17: 60 | M17: =I17*L17 -> 960000 | N17: =I17*G17 -> 33600000 | O17: FULL - date must show as FULL and refuse bookings
A18: HS-0017 | B18: P104-1B | C18: Mkuza Chicks Broiler Day-old Chicks | D18: SEL-MKUZ | E18: 46328 | F18: 46325 | G18: 2050 | H18: 11500 | I18: 9450 | J18: =MAX(0,H18-I18) -> 2050 | K18: =IF(E18<README!$C$4,"Past",IF(I18>=H18,"FULL",IF(F18<README!$C$4,"Closed","Open"))) -> Open | L18: 60 | M18: =I18*L18 -> 567000 | N18: =I18*G18 -> 19372500
A19: HS-0018 | B19: P110-1B | C19: Silverlands Layer Day-old Chicks | D19: SEL-SIL | E19: 46328 | F19: 46325 | G19: 3150 | H19: 5500 | I19: 3450 | J19: =MAX(0,H19-I19) -> 2050 | K19: =IF(E19<README!$C$4,"Past",IF(I19>=H19,"FULL",IF(F19<README!$C$4,"Closed","Open"))) -> Open | L19: 60 | M19: =I19*L19 -> 207000 | N19: =I19*G19 -> 10867500
A20: HS-0019 | B20: P111-1B | C20: Silverlands Sasso Day-old Chicks | D20: SEL-SIL | E20: 46328 | F20: 46325 | G20: 2250 | H20: 2500 | I20: 2400 | J20: =MAX(0,H20-I20) -> 100 | K20: =IF(E20<README!$C$4,"Past",IF(I20>=H20,"FULL",IF(F20<README!$C$4,"Closed","Open"))) -> Open | L20: 60 | M20: =I20*L20 -> 144000 | N20: =I20*G20 -> 5400000 | O20: Nearly full - only 100 left; an order of 150 must be refused
A21: HS-0020 | B21: P101-1B | C21: Central Chicks (Animal Care) Broiler Day-old Chicks | D21: SEL-CENT | E21: 46330 | F21: 46327 | G21: 2000 | H21: 14000 | I21: 4700 | J21: =MAX(0,H21-I21) -> 9300 | K21: =IF(E21<README!$C$4,"Past",IF(I21>=H21,"FULL",IF(F21<README!$C$4,"Closed","Open"))) -> Open | L21: 60 | M21: =I21*L21 -> 282000 | N21: =I21*G21 -> 9400000
A22: HS-0021 | B22: P109-1B | C22: Silverlands Broiler Day-old Chicks | D22: SEL-SIL | E22: 46330 | F22: 46327 | G22: 2250 | H22: 14500 | I22: 9350 | J22: =MAX(0,H22-I22) -> 5150 | K22: =IF(E22<README!$C$4,"Past",IF(I22>=H22,"FULL",IF(F22<README!$C$4,"Closed","Open"))) -> Open | L22: 60 | M22: =I22*L22 -> 561000 | N22: =I22*G22 -> 21037500
A23: HS-0022 | B23: P106-1B | C23: Interchick Broiler Day-old Chicks | D23: SEL-INTR | E23: 46331 | F23: 46328 | G23: 2200 | H23: 6500 | I23: 5300 | J23: =MAX(0,H23-I23) -> 1200 | K23: =IF(E23<README!$C$4,"Past",IF(I23>=H23,"FULL",IF(F23<README!$C$4,"Closed","Open"))) -> Open | L23: 60 | M23: =I23*L23 -> 318000 | N23: =I23*G23 -> 11660000
A24: HS-0023 | B24: P108-1B | C24: Interchick Tanbro Day-old Chicks | D24: SEL-INTR | E24: 46331 | F24: 46328 | G24: 2100 | H24: 2500 | I24: 2500 | J24: =MAX(0,H24-I24) -> 0 | K24: =IF(E24<README!$C$4,"Past",IF(I24>=H24,"FULL",IF(F24<README!$C$4,"Closed","Open"))) -> FULL | L24: 60 | M24: =I24*L24 -> 150000 | N24: =I24*G24 -> 5250000 | O24: FULL (exclusive chick type)
A25: HS-0024 | B25: P098-1B | C25: Irvines Broiler Day-old Chicks | D25: SEL-IRVN | E25: 46331 | F25: 46328 | G25: 2150 | H25: 17000 | I25: 13550 | J25: =MAX(0,H25-I25) -> 3450 | K25: =IF(E25<README!$C$4,"Past",IF(I25>=H25,"FULL",IF(F25<README!$C$4,"Closed","Open"))) -> Open | L25: 60 | M25: =I25*L25 -> 813000 | N25: =I25*G25 -> 29132500
A26: HS-0025 | B26: P102-1B | C26: Tanzania Poultry Farms Broiler Day-old Chicks | D26: SEL-TPF | E26: 46331 | F26: 46328 | G26: 2100 | H26: 18000 | I26: 13450 | J26: =MAX(0,H26-I26) -> 4550 | K26: =IF(E26<README!$C$4,"Past",IF(I26>=H26,"FULL",IF(F26<README!$C$4,"Closed","Open"))) -> Open | L26: 60 | M26: =I26*L26 -> 807000 | N26: =I26*G26 -> 28245000
A27: HS-0026 | B27: P107-1B | C27: Interchick Layer Day-old Chicks | D27: SEL-INTR | E27: 46333 | F27: 46330 | G27: 3100 | H27: 6000 | I27: 4900 | J27: =MAX(0,H27-I27) -> 1100 | K27: =IF(E27<README!$C$4,"Past",IF(I27>=H27,"FULL",IF(F27<README!$C$4,"Closed","Open"))) -> Open | L27: 60 | M27: =I27*L27 -> 294000 | N27: =I27*G27 -> 15190000
A28: HS-0027 | B28: P105-1B | C28: Mkuza Chicks Layer Day-old Chicks | D28: SEL-MKUZ | E28: 46333 | F28: 46330 | G28: 2950 | H28: 3000 | I28: 850 | J28: =MAX(0,H28-I28) -> 2150 | K28: =IF(E28<README!$C$4,"Past",IF(I28>=H28,"FULL",IF(F28<README!$C$4,"Closed","Open"))) -> Open | L28: 60 | M28: =I28*L28 -> 51000 | N28: =I28*G28 -> 2507500
A29: HS-0028 | B29: P099-1B | C29: Organia Broiler Day-old Chicks | D29: SEL-ORGN | E29: 46333 | F29: 46330 | G29: 2200 | H29: 17000 | I29: 2550 | J29: =MAX(0,H29-I29) -> 14450 | K29: =IF(E29<README!$C$4,"Past",IF(I29>=H29,"FULL",IF(F29<README!$C$4,"Closed","Open"))) -> Open | L29: 60 | M29: =I29*L29 -> 153000 | N29: =I29*G29 -> 5610000
A30: HS-0029 | B30: P100-1B | C30: Happy Chicks Broiler Day-old Chicks | D30: SEL-HAPP | E30: 46334 | F30: 46331 | G30: 2050 | H30: 7000 | I30: 1850 | J30: =MAX(0,H30-I30) -> 5150 | K30: =IF(E30<README!$C$4,"Past",IF(I30>=H30,"FULL",IF(F30<README!$C$4,"Closed","Open"))) -> Open | L30: 60 | M30: =I30*L30 -> 111000 | N30: =I30*G30 -> 3792500
A31: HS-0030 | B31: P096-1B | C31: Harsho Broiler Day-old Chicks | D31: SEL-HARS | E31: 46334 | F31: 46331 | G31: 2000 | H31: 10000 | I31: 7100 | J31: =MAX(0,H31-I31) -> 2900 | K31: =IF(E31<README!$C$4,"Past",IF(I31>=H31,"FULL",IF(F31<README!$C$4,"Closed","Open"))) -> Open | L31: 60 | M31: =I31*L31 -> 426000 | N31: =I31*G31 -> 14200000
A32: HS-0031 | B32: P103-1B | C32: Tanzania Poultry Farms Layer Day-old Chicks | D32: SEL-TPF | E32: 46334 | F32: 46331 | G32: 3000 | H32: 5500 | I32: 750 | J32: =MAX(0,H32-I32) -> 4750 | K32: =IF(E32<README!$C$4,"Past",IF(I32>=H32,"FULL",IF(F32<README!$C$4,"Closed","Open"))) -> Open | L32: 60 | M32: =I32*L32 -> 45000 | N32: =I32*G32 -> 2250000
A33: HS-0032 | B33: P097-1B | C33: Backbone Broiler Day-old Chicks | D33: SEL-BACK | E33: 46335 | F33: 46332 | G33: 1950 | H33: 17000 | I33: 13200 | J33: =MAX(0,H33-I33) -> 3800 | K33: =IF(E33<README!$C$4,"Past",IF(I33>=H33,"FULL",IF(F33<README!$C$4,"Closed","Open"))) -> Open | L33: 60 | M33: =I33*L33 -> 792000 | N33: =I33*G33 -> 25740000
A34: HS-0033 | B34: P095-1B | C34: Kibo Broiler Day-old Chicks | D34: SEL-KIBO | E34: 46335 | F34: 46332 | G34: 2100 | H34: 9500 | I34: 2900 | J34: =MAX(0,H34-I34) -> 6600 | K34: =IF(E34<README!$C$4,"Past",IF(I34>=H34,"FULL",IF(F34<README!$C$4,"Closed","Open"))) -> Open | L34: 60 | M34: =I34*L34 -> 174000 | N34: =I34*G34 -> 6090000
A35: HS-0034 | B35: P104-1B | C35: Mkuza Chicks Broiler Day-old Chicks | D35: SEL-MKUZ | E35: 46335 | F35: 46332 | G35: 2050 | H35: 7500 | I35: 5250 | J35: =MAX(0,H35-I35) -> 2250 | K35: =IF(E35<README!$C$4,"Past",IF(I35>=H35,"FULL",IF(F35<README!$C$4,"Closed","Open"))) -> Open | L35: 60 | M35: =I35*L35 -> 315000 | N35: =I35*G35 -> 10762500
A36: HS-0035 | B36: P110-1B | C36: Silverlands Layer Day-old Chicks | D36: SEL-SIL | E36: 46335 | F36: 46332 | G36: 3150 | H36: 4000 | I36: 1750 | J36: =MAX(0,H36-I36) -> 2250 | K36: =IF(E36<README!$C$4,"Past",IF(I36>=H36,"FULL",IF(F36<README!$C$4,"Closed","Open"))) -> Open | L36: 60 | M36: =I36*L36 -> 105000 | N36: =I36*G36 -> 5512500
... A61: HS-0060 | B61: P107-1B | C61: Interchick Layer Day-old Chicks | D61: SEL-INTR | E61: 46347 | F61: 46344 | G61: 3150 | H61: 5500 | I61: 850 | J61: =MAX(0,H61-I61) -> 4650 | K61: =IF(E61<README!$C$4,"Past",IF(I61>=H61,"FULL",IF(F61<README!$C$4,"Closed","Open"))) -> Open | L61: 60 | M61: =I61*L61 -> 51000 | N61: =I61*G61 -> 2677500
A62: HS-0061 | B62: P105-1B | C62: Mkuza Chicks Layer Day-old Chicks | D62: SEL-MKUZ | E62: 46347 | F62: 46344 | G62: 3000 | H62: 6000 | I62: 4800 | J62: =MAX(0,H62-I62) -> 1200 | K62: =IF(E62<README!$C$4,"Past",IF(I62>=H62,"FULL",IF(F62<README!$C$4,"Closed","Open"))) -> Open | L62: 60 | M62: =I62*L62 -> 288000 | N62: =I62*G62 -> 14400000 | O62: Price differs by hatch date (+50 TZS on later dates)
A63: HS-0062 | B63: P099-1B | C63: Organia Broiler Day-old Chicks | D63: SEL-ORGN | E63: 46347 | F63: 46344 | G63: 2250 | H63: 19500 | I63: 2650 | J63: =MAX(0,H63-I63) -> 16850 | K63: =IF(E63<README!$C$4,"Past",IF(I63>=H63,"FULL",IF(F63<README!$C$4,"Closed","Open"))) -> Open | L63: 60 | M63: =I63*L63 -> 159000 | N63: =I63*G63 -> 5962500
A64: HS-0063 | B64: P100-1B | C64: Happy Chicks Broiler Day-old Chicks | D64: SEL-HAPP | E64: 46348 | F64: 46345 | G64: 2100 | H64: 8500 | I64: 1100 | J64: =MAX(0,H64-I64) -> 7400 | K64: =IF(E64<README!$C$4,"Past",IF(I64>=H64,"FULL",IF(F64<README!$C$4,"Closed","Open"))) -> Open | L64: 60 | M64: =I64*L64 -> 66000 | N64: =I64*G64 -> 2310000
A65: HS-0064 | B65: P096-1B | C65: Harsho Broiler Day-old Chicks | D65: SEL-HARS | E65: 46348 | F65: 46345 | G65: 2050 | H65: 9000 | I65: 6350 | J65: =MAX(0,H65-I65) -> 2650 | K65: =IF(E65<README!$C$4,"Past",IF(I65>=H65,"FULL",IF(F65<README!$C$4,"Closed","Open"))) -> Open | L65: 60 | M65: =I65*L65 -> 381000 | N65: =I65*G65 -> 13017500
A66: HS-0065 | B66: P103-1B | C66: Tanzania Poultry Farms Layer Day-old Chicks | D66: SEL-TPF | E66: 46348 | F66: 46345 | G66: 3050 | H66: 8000 | I66: 2350 | J66: =MAX(0,H66-I66) -> 5650 | K66: =IF(E66<README!$C$4,"Past",IF(I66>=H66,"FULL",IF(F66<README!$C$4,"Closed","Open"))) -> Open | L66: 60 | M66: =I66*L66 -> 141000 | N66: =I66*G66 -> 7167500
A67: HS-0066 | B67: P097-1B | C67: Backbone Broiler Day-old Chicks | D67: SEL-BACK | E67: 46349 | F67: 46346 | G67: 2000 | H67: 19000 | I67: 16150 | J67: =MAX(0,H67-I67) -> 2850 | K67: =IF(E67<README!$C$4,"Past",IF(I67>=H67,"FULL",IF(F67<README!$C$4,"Closed","Open"))) -> Open | L67: 60 | M67: =I67*L67 -> 969000 | N67: =I67*G67 -> 32300000
A68: HS-0067 | B68: P095-1B | C68: Kibo Broiler Day-old Chicks | D68: SEL-KIBO | E68: 46349 | F68: 46346 | G68: 2150 | H68: 15500 | I68: 9500 | J68: =MAX(0,H68-I68) -> 6000 | K68: =IF(E68<README!$C$4,"Past",IF(I68>=H68,"FULL",IF(F68<README!$C$4,"Closed","Open"))) -> Open | L68: 60 | M68: =I68*L68 -> 570000 | N68: =I68*G68 -> 20425000
A69: HS-0068 | B69: P104-1B | C69: Mkuza Chicks Broiler Day-old Chicks | D69: SEL-MKUZ | E69: 46349 | F69: 46346 | G69: 2100 | H69: 10000 | I69: 1700 | J69: =MAX(0,H69-I69) -> 8300 | K69: =IF(E69<README!$C$4,"Past",IF(I69>=H69,"FULL",IF(F69<README!$C$4,"Closed","Open"))) -> Open | L69: 60 | M69: =I69*L69 -> 102000 | N69: =I69*G69 -> 3570000
A70: HS-0069 | B70: P110-1B | C70: Silverlands Layer Day-old Chicks | D70: SEL-SIL | E70: 46349 | F70: 46346 | G70: 3200 | H70: 8000 | I70: 3700 | J70: =MAX(0,H70-I70) -> 4300 | K70: =IF(E70<README!$C$4,"Past",IF(I70>=H70,"FULL",IF(F70<README!$C$4,"Closed","Open"))) -> Open | L70: 60 | M70: =I70*L70 -> 222000 | N70: =I70*G70 -> 11840000
A71: HS-0070 | B71: P111-1B | C71: Silverlands Sasso Day-old Chicks | D71: SEL-SIL | E71: 46349 | F71: 46346 | G71: 2300 | H71: 4500 | I71: 2500 | J71: =MAX(0,H71-I71) -> 2000 | K71: =IF(E71<README!$C$4,"Past",IF(I71>=H71,"FULL",IF(F71<README!$C$4,"Closed","Open"))) -> Open | L71: 60 | M71: =I71*L71 -> 150000 | N71: =I71*G71 -> 5750000
A72: HS-0071 | B72: P101-1B | C72: Central Chicks (Animal Care) Broiler Day-old Chicks | D72: SEL-CENT | E72: 46351 | F72: 46348 | G72: 2050 | H72: 13500 | I72: 3900 | J72: =MAX(0,H72-I72) -> 9600 | K72: =IF(E72<README!$C$4,"Past",IF(I72>=H72,"FULL",IF(F72<README!$C$4,"Closed","Open"))) -> Open | L72: 60 | M72: =I72*L72 -> 234000 | N72: =I72*G72 -> 7995000
A73: HS-0072 | B73: P109-1B | C73: Silverlands Broiler Day-old Chicks | D73: SEL-SIL | E73: 46351 | F73: 46348 | G73: 2300 | H73: 5000 | I73: 3250 | J73: =MAX(0,H73-I73) -> 1750 | K73: =IF(E73<README!$C$4,"Past",IF(I73>=H73,"FULL",IF(F73<README!$C$4,"Closed","Open"))) -> Open | L73: 60 | M73: =I73*L73 -> 195000 | N73: =I73*G73 -> 7475000
A74: HS-0073 | B74: P106-1B | C74: Interchick Broiler Day-old Chicks | D74: SEL-INTR | E74: 46352 | F74: 46349 | G74: 2250 | H74: 13500 | I74: 6050 | J74: =MAX(0,H74-I74) -> 7450 | K74: =IF(E74<README!$C$4,"Past",IF(I74>=H74,"FULL",IF(F74<README!$C$4,"Closed","Open"))) -> Open | L74: 60 | M74: =I74*L74 -> 363000 | N74: =I74*G74 -> 13612500
... A88: HS-0087 | B88: P111-1B | C88: Silverlands Sasso Day-old Chicks | D88: SEL-SIL | E88: 46356 | F88: 46353 | G88: 2300 | H88: 2500 | I88: 1700 | J88: =MAX(0,H88-I88) -> 800 | K88: =IF(E88<README!$C$4,"Past",IF(I88>=H88,"FULL",IF(F88<README!$C$4,"Closed","Open"))) -> Open | L88: 60 | M88: =I88*L88 -> 102000 | N88: =I88*G88 -> 3910000

Sheet Map_Categories
A1: dimension | B1: live_value | C1: new_id | D1: new_name | E1: migration_rule
A2: category | B2: Feed | C2: C10 | D2: Feed | E2: Keep as level-1 parent.
A3: category | B3: Feed > Starter | C3: C1010 | D3: Feed > Complete feed | E3: Set life_stages = starter for the product's animal (e.g. LS-POU-STR).
A4: category | B4: Feed > Grower | C4: C1010 | D4: Feed > Complete feed | E4: Set life_stages = grower for the right animal (chicken LS-POU-GRW, pig LS-PIG-GRW). Fixes 'grower' search mixing pigs and chickens.
A5: category | B5: Feed > Finisher | C5: C1010 | D5: Feed > Complete feed | E5: Set life_stages = finisher.
A6: category | B6: Feed > Layers Mash | C6: C1010 | D6: Feed > Complete feed | E6: Set life_stages = LS-POU-LAY and production_purpose = layer.
A7: category | B7: Feed > Concentrates | C7: C1020 | D7: Feed > Concentrates | E7: Keep.
A8: category | B8: Feed (no sub-category: Dairy Meal, Tilapia Feed) | C8: C1010 | D8: Feed > Complete feed | E8: Items sitting on bare 'Feed' must be given a level-2 category.
A9: category | B9: Vaccines | C9: C40 | D9: Vaccines & biologicals | E9: Keep. Add disease_target and cold_chain_required to every item.
A10: category | B10: Medicines | C10: C30 > C3010-C3060 | D10: Medicines > (sub-category) | E10: Assign each item a sub-category (antibiotics, dewormers ...).
A11: category | B11: Vitamins & Supplements | C11: C20 > C2010-C2060 | D11: Supplements & additives > (sub-category) | E11: Split: vitamins, electrolytes, minerals/licks, probiotics, toxin binders, tonics.
A12: category | B12: Equipment | C12: C60 | D12: Equipment & supplies | E12: Keep as parent.
... A26: animal | B26: Other Livestock / Animals | C26: AN-OTH | D26: Other animals | E26: Keep.

Sheet Map_Live_Products
A1: live_product_name | B1: live_producer | C1: live_animal | D1: live_category | E1: live_unit | F1: live_inventory | G1: issues_found | H1: new_product_id | I1: new_product_name | J1: new_sku | K1: new_category_id | L1: new_category_path | M1: new_animal_types | N1: new_life_stages | O1: migration_action | P1: decision_needed
A2: Albendazole Dewormer 1L | C2: Cattle | D2: Medicines | E2: bottle | F2: Not stocked | G2: Single animal only (goat/sheep farmers can't find it); no sub-category; no brand; pack size in name. | H2: P052 | I2: Albendazole 10% Oral Suspension | J2: P052-1L | K2: C3020 | L2: Medicines > Dewormers | M2: AN-CAT|AN-GTS | N2: LS-ALL | O2: Rename, set animals Cattle+Goats+Sheep, category Dewormers, add brand, attach 1 L as a variant.
A3: Chick Drinker 4L | C3: Poultry | D3: Equipment > Feeders & Drinkers | E3: piece | F3: Not stocked | G3: Pack/capacity in name; no brand. | H3: P076 | I3: Chick Drinker | J3: P076-4L | K3: C6010 | L3: Equipment & supplies > Feeders & drinkers | M3: AN-POU | N3: LS-ALL | O3: Rename; 4 L becomes capacity/variant.
A4: Chicken Finisher 25KG | B4: Silverlands | C4: Chicken | D4: Feed > Finisher | E4: bag | F4: Not stocked | G4: Stage used as category; pack in name; broiler vs other not stated. | H4: P003 | I4: Broiler Finisher Pellets | J4: P003-25KG | K4: C1010 | L4: Feed > Complete feed | M4: AN-CHK | N4: LS-POU-FIN | O4: Move to Complete feed + finisher + broiler.
A5: Chicken Grower 25KG | B5: Silverlands | C5: Chicken | D5: Feed > Grower | E5: bag | F5: 1 item (0 bags - low stock) | G5: Stage used as category; ambiguous whether broiler grower or layer (pullet) grower. | H5: P002 | I5: Broiler Grower Pellets | J5: P002-25KG | K5: C1010 | L5: Feed > Complete feed | M5: AN-CHK | N5: LS-POU-GRW | O5: Move to Complete feed + grower + purpose. | P5: Confirm with Silverlands: broiler or layer grower?
A6: Chicken Grower 25KG | B6: Bora Feeds (demo) | C6: Chicken | D6: Feed > Grower | E6: bag | F6: 1 item | G6: Same display name as the Silverlands item - buyers can't tell them apart without the producer line. | H6: P005 | I6: Growers Mash | J6: P005-25KG | K6: C1010 | L6: Feed > Complete feed | M6: AN-CHK | N6: LS-POU-GRW | O6: Rename to a distinct product name; move to Complete feed + grower + layer. | P6: Assumed layer-pullet grower; confirm.
A7: Chicken Starter 25KG | B7: Silverlands | C7: Chicken | D7: Feed > Starter | E7: bag | F7: 1 item | G7: Stage used as category; broiler vs layer chick not stated. | H7: P001 | I7: Broiler Starter Crumbs | J7: P001-25KG | K7: C1010 | L7: Feed > Complete feed | M7: AN-CHK | N7: LS-POU-STR | O7: Move to Complete feed + starter + broiler. | P7: Confirm broiler starter vs chick & duck mash.
A8: Dairy Meal 70KG | C8: Cattle | D8: Feed | E8: bag | F8: 1 item | G8: No level-2 category; no producer; should be Dairy cattle, not all Cattle. | H8: P011 | I8: Dairy Meal | J8: P011-70KG | K8: C1010 | L8: Feed > Complete feed | M8: AN-DCT | N8: LS-CAT-LAC | O8: Complete feed + lactating + dairy; add producer.
A9: Goat & Sheep Mineral Lick 2KG | C9: Goats & Sheep | D9: Vitamins & Supplements | E9: piece | F9: Not stocked | G9: Lumped with vitamins. | H9: P041 | I9: Goat & Sheep Mineral Lick | J9: P041-2KG | K9: C2030 | L9: Supplements & additives > Minerals & licks | M9: AN-GOT|AN-SHP | N9: LS-ALL | O9: Move to Minerals & licks.
A10: Gumboro Vaccine 1000 doses | C10: Chicken | D10: Vaccines | E10: vial | F10: 1 item | G10: No brand, disease, cold-chain or prescription flag. | H10: P065 | I10: Gumboro (IBD) Vaccine | J10: P065-1000D | K10: C40 | L10: Vaccines & biologicals | M10: AN-CHK | N10: LS-POU-STR | O10: Add disease_target, cold chain, Rx flag; doses become variant.
A11: Layers Mash 50KG | B11: Silverlands | C11: Chicken | D11: Feed > Layers Mash | E11: bag | F11: Not stocked | G11: Product used as a category. | H11: P006 | I11: Layers Mash | J11: P006-50KG | K11: C1010 | L11: Feed > Complete feed | M11: AN-CHK | N11: LS-POU-LAY | O11: Complete feed + laying + layer.
A12: Newcastle Disease Vaccine (Lasota) 100 doses | C12: Chicken | D12: Vaccines | E12: vial | F12: Not stocked | G12: As Gumboro. | H12: P063 | I12: Newcastle Disease Vaccine (LaSota) | J12: P063-100D | K12: C40 | L12: Vaccines & biologicals | M12: AN-CHK | N12: LS-ALL | O12: Add disease_target newcastle + Kiswahili 'kideri'.
A13: Oxytetracycline 20% Injection 100ml | C13: Cattle | D13: Medicines | E13: bottle | F13: Not stocked | G13: Single animal; prescription status not captured but listed for open sale. | H13: P048 | I13: Oxytetracycline 20% LA Injection | J13: P048-100ML | K13: C3010 | L13: Medicines > Antibiotics & antibacterials | M13: AN-CAT|AN-GTS|AN-PIG | N13: LS-ALL | O13: Animals Cattle+Goats+Sheep+Pigs; Antibiotics; Rx flag. | P13: Confirm prescription status under the vet regulations.
A14: Pig Grower Pellets 50KG | C14: Pigs | D14: Feed > Grower | E14: bag | F14: Not stocked | G14: Shares 'Grower' bucket with chicken feed. | H14: P009 | I14: Pig Grower Pellets | J14: P009-50KG | K14: C1010 | L14: Feed > Complete feed | M14: AN-PIG | N14: LS-PIG-GRW | O14: Complete feed + LS-PIG-GRW; add producer.
A15: Poultry Multivitamin 100g | C15: Poultry | D15: Vitamins & Supplements | E15: sachet | F15: Not stocked | G15: Generic, brandless entry - sellers will link branded products (e.g. Vitamix Plus) to it and the brand is lost. | H15: P035 | I15: Vitamix Plus | J15: P035-100G | K15: C2010 | L15: Supplements & additives > Vitamins & multivitamins | M15: AN-POU | N15: LS-ALL | O15: Retire; relink any inventory to the branded product actually stocked. | P15: Retire generic entries? (recommended)
A16: Tilapia Floating Feed 25KG | C16: Fish / Aquaculture | D16: Feed | E16: bag | F16: Not stocked | G16: No level-2 category; pellet size and stage unknown. | H16: P015 | I16: Tilapia Floating Feed 4 mm | J16: P015-25KG | K16: C1010 | L16: Feed > Complete feed | M16: AN-TIL | N16: LS-FSH-GRO | O16: Complete feed + Tilapia + grow-out. | P16: Confirm pellet size.

Sheet Map_Stores_Sellers
A1: type | B1: live_value | C1: new_id | D1: new_value | E1: action | F1: decision_needed
A2: seller | B2: Amsterderm Group | C2: SEL-AMS | D2: Amsterdam Group | E2: Rename to match the brand on packs and website.
A3: store | B3: Amsterdem Group - Main | C3: ST-AMS-TEG | D3: Amsterdam Group - Tegeta (HQ & Warehouse) | E3: Confirmed 27 Oct: Main is Tegeta. Rename the existing store record; keep its id, stock and sales history.
A4: store | B4: Amsterdem Group - Ubungo | C4: (not in new list) | D4: - | E4: Not among the branches you listed. | F4: Keep Ubungo as a 7th store, or close it and transfer its stock?
A5: seller | B5: Kilimo Bora Agrovet | C5: (unchanged) | D5: - | E5: Other sellers keep their accounts; relink their inventory to the new catalogue IDs.
A6: seller | B6: Mbezi Livestock Supplies | C6: (unchanged) | D6: - | E6: As above.
A7: seller | B7: Oda tenants (11 hatcheries) | C7: SEL-KIBO ... SEL-SIL | D7: Hatchery sellers | E7: Create one seller per Oda tenant; see Map_Oda_Chicks for order of steps. | F7: Confirm legal names and Selcom merchant ids.
A8: domain | B8: odaamsterdermhub.co.tz | C8: - | D8: - | E8: Spelling differs from 'Amsterdam'. Branding decision, outside this data file. | F8: Keep or change?

Sheet Map_Oda_Chicks
A1: step | B1: type | C1: oda_today | D1: in_the_hub | E1: where_in_workbook | F1: migration_note
A2: 1 | B2: concept | C2: Tenant (supplier) with subdomain, e.g. kibo.oda.co.tz | D2: Seller with seller_type = Hatchery | E2: Sellers | F2: Create one seller per tenant and keep the slug as its storefront slug; redirect the old subdomain to the storefront.
A3: 2 | B3: concept | C3: Selcom merchant account per supplier, split disbursement | D3: Payment settings on the seller | E3: Sellers (notes) | F3: Carry each merchant id over unchanged so split payouts keep working from day one.
A4: 3 | B4: concept | C4: Chick types offered by each tenant | D4: One product per hatchery x chick type in C7010 | E4: Products, Variants | F4: Create products before schedules. Chick type maps to production_purpose and breed_strain; selling unit = bird, min order 50.
A5: 4 | B5: concept | C5: Hatch dates with price and fixed capacity | D5: Hatch_Schedule row (seller x SKU x hatch date) | E5: Hatch_Schedule | F5: Import future dates only. Past dates stay as order history.
A6: 5 | B6: concept | C6: Auto-FULL when booked >= capacity | D6: status = FULL (same rule) | E6: Hatch_Schedule.status | F6: Keep the rule server-side; the sheet formula shows the expected result for testing.
A7: 6 | B7: concept | C7: CSV upload: 3 columns (single type) / 4 columns (multi type) | D7: Same CSV, mapped to sku + hatch_date + price + capacity | E7: Hatch_Schedule | F7: For multi-type hatcheries the chick-type column resolves to that hatchery's SKU.
A8: 7 | B8: concept | C8: Customer flow: chick type > supplier list > hatch date > quantity & delivery | D8: Day-old chicks category page > filter by type > compare hatcheries > pick hatch date > quantity (min 50) > delivery | E8: - | F8: Keep Oda's 4-step flow as the product-page behaviour for C7010 only; every other category uses the normal cart.
A9: 8 | B9: concept | C9: Supplier commission 50-70 TZS per chick | D9: oda_commission_per_chick_tzs on each schedule row | E9: Hatch_Schedule | F9: Dummy 60 TZS here. Decide whether the rate is set per seller or per hatch date before go-live.
A10: 9 | B10: concept | C10: tenant_admin role | D10: Seller staff role scoped to that seller | E10: - | F10: Map existing tenant_admin users to seller staff.
A11: 10 | B11: concept | C11: Open chick orders | D11: Hub orders referencing sku + schedule_id | E11: - | F11: Migrate open orders last, then switch Oda traffic to the hub. Run a parallel check on booked counts before cut-over.
B12: hatchery x type | C12: Kibo - Broiler | D12: P095 Kibo Broiler Day-old Chicks / SEL-KIBO | E12: Products, Hatch_Schedule
B13: hatchery x type | C13: Harsho - Broiler | D13: P096 Harsho Broiler Day-old Chicks / SEL-HARS | E13: Products, Hatch_Schedule
B14: hatchery x type | C14: Backbone - Broiler | D14: P097 Backbone Broiler Day-old Chicks / SEL-BACK | E14: Products, Hatch_Schedule
B15: hatchery x type | C15: Irvines - Broiler | D15: P098 Irvines Broiler Day-old Chicks / SEL-IRVN | E15: Products, Hatch_Schedule
B16: hatchery x type | C16: Organia - Broiler | D16: P099 Organia Broiler Day-old Chicks / SEL-ORGN | E16: Products, Hatch_Schedule
B17: hatchery x type | C17: Happy Chicks - Broiler | D17: P100 Happy Chicks Broiler Day-old Chicks / SEL-HAPP | E17: Products, Hatch_Schedule
B18: hatchery x type | C18: Central Chicks (Animal Care) - Broiler | D18: P101 Central Chicks (Animal Care) Broiler Day-old Chicks / SEL-CENT | E18: Products, Hatch_Schedule
B19: hatchery x type | C19: Tanzania Poultry Farms - Broiler | D19: P102 Tanzania Poultry Farms Broiler Day-old Chicks / SEL-TPF | E19: Products, Hatch_Schedule
B20: hatchery x type | C20: Tanzania Poultry Farms - Layer | D20: P103 Tanzania Poultry Farms Layer Day-old Chicks / SEL-TPF | E20: Products, Hatch_Schedule
B21: hatchery x type | C21: Mkuza Chicks - Broiler | D21: P104 Mkuza Chicks Broiler Day-old Chicks / SEL-MKUZ | E21: Products, Hatch_Schedule
B22: hatchery x type | C22: Mkuza Chicks - Layer | D22: P105 Mkuza Chicks Layer Day-old Chicks / SEL-MKUZ | E22: Products, Hatch_Schedule
B23: hatchery x type | C23: Interchick - Broiler | D23: P106 Interchick Broiler Day-old Chicks / SEL-INTR | E23: Products, Hatch_Schedule
B24: hatchery x type | C24: Interchick - Layer | D24: P107 Interchick Layer Day-old Chicks / SEL-INTR | E24: Products, Hatch_Schedule
B25: hatchery x type | C25: Interchick - Tanbro | D25: P108 Interchick Tanbro Day-old Chicks / SEL-INTR | E25: Products, Hatch_Schedule | F25: Exclusive to this hatchery
B26: hatchery x type | C26: Silverlands - Broiler | D26: P109 Silverlands Broiler Day-old Chicks / SEL-SIL | E26: Products, Hatch_Schedule
B27: hatchery x type | C27: Silverlands - Layer | D27: P110 Silverlands Layer Day-old Chicks / SEL-SIL | E27: Products, Hatch_Schedule
B28: hatchery x type | C28: Silverlands - Sasso | D28: P111 Silverlands Sasso Day-old Chicks / SEL-SIL | E28: Products, Hatch_Schedule | F28: Exclusive to this hatchery
